Workbook

Sheet Hoja1
A1: Codigo | B1: Programa | C1: Campus | D1: Turno | E1: Venta Nueva | F1: Modalidad
A2: 2017479897 | B2: ADMNE | C2: INDEP | D2: A | E2: SI | F2: Presencial
A3: 2017505616 | B3: ADMNI | C3: SURCO | D3: A | E3: SI | F3: Presencial
A4: 2017503757 | B4: GYGEC | C4: VILLA | D4: N | E4: SI | F4: Presencial
A5: 2017505709 | B5: ADMBF | C5: INDEP | D5: N | E5: SI | F5: Presencial
A6: 2017505732 | B6: FISIO | C6: SURCO | D6: C | E6: SI | F6: Presencial
A7: 2017505741 | B7: SWSIS | C7: VILLA | D7: A | E7: SI | F7: Presencial
A8: 2017505760 | B8: SALUD | C8: INDEP | D8: C | E8: SI | F8: Presencial
A9: 2017505803 | B9: DYGMO | C9: STABE | D9: C | E9: SI | F9: Presencial
A10: 2017503832 | B10: DYGMO | C10: ATE | D10: C | E10: SI | F10: Semipresencial
A11: 2017503868 | B11: PA | C11: CANTU | D11: A | E11: SI | F11: Semipresencial
A12: 2017505675 | B12: GYGEC | C12: ATE | D12: A | E12: SI | F12: Semipresencial
A13: 2017505698 | B13: GYGEC | C13: SJL | D13: N | E13: SI | F13: Semipresencial
... A28: 2017418165 | B28: CONTA | C28: VIRTU | D28: M | E28: SI | F28: Virtual

Sheet sheet1
A1: Ciclo | B1: Sección | C1: Nº Clase | D1: Campus | E1: Nombre Curso | F1: Turno | G1: ID Curso | H1: Programa | I1: Venta Nueva | J1: Modalidad | K1: Estado
A2: C1B1 | B2: M0001 | C2: 2026 | D2: STABE | E2: INTRODUCCIÓN A LA MODA | F2: C | G2: 668650 | H2: DYGMO | I2: SI / NO | J2: Presencial | K2: Aperturado
A3: C1B1 | B3: M0001 | C3: 2027 | D3: STABE | E3: DIBUJO TÉCNICO DE LA MODA | F3: C | G3: 668651 | H3: DYGMO | I3: SI / NO | J3: Presencial | K3: Aperturado
A4: C1B1 | B4: M0001 | C4: 1988 | D4: STABE | E4: METOD. PARA UN APREND. EFIC. | F4: C | G4: 668513 | H4: DYGMO | I4: SI / NO | J4: Presencial | K4: Aperturado
A5: C1B1 | B5: M0002 | C5: 1575 | D5: INDEP | E5: INTRODUCCIÓN A LA MODA | F5: C | G5: 668650 | H5: DYGMO | I5: SI / NO | J5: Presencial | K5: Aperturado
A6: C1B1 | B6: M0002 | C6: 1576 | D6: INDEP | E6: DIBUJO TÉCNICO DE LA MODA | F6: C | G6: 668651 | H6: DYGMO | I6: SI / NO | J6: Presencial | K6: Aperturado
A7: C1B1 | B7: M0002 | C7: 1516 | D7: INDEP | E7: METOD. PARA UN APREND. EFIC. | F7: C | G7: 668513 | H7: DYGMO | I7: SI / NO | J7: Presencial | K7: Aperturado
A8: C1B1 | B8: M0004 | C8: 2400 | D8: SURCO | E8: DIBUJO TÉCNICO DE LA MODA | F8: C | G8: 668651 | H8: DYGMO | I8: SI / NO | J8: Presencial | K8: Aperturado
A9: C1B1 | B9: M0004 | C9: 2399 | D9: SURCO | E9: INTRODUCCIÓN A LA MODA | F9: C | G9: 668650 | H9: DYGMO | I9: SI / NO | J9: Presencial | K9: Aperturado
A10: C1B1 | B10: M0004 | C10: 2290 | D10: SURCO | E10: METOD. PARA UN APREND. EFIC. | F10: C | G10: 668513 | H10: DYGMO | I10: SI / NO | J10: Presencial | K10: Aperturado
A11: C1B1 | B11: M0005 | C11: 1759 | D11: SJL | E11: DIBUJO TÉCNICO DE LA MODA | F11: A | G11: 668651 | H11: DYGMO | I11: SI / NO | J11: Presencial | K11: Aperturado
A12: C1B1 | B12: M0005 | C12: 1758 | D12: SJL | E12: INTRODUCCIÓN A LA MODA | F12: A | G12: 668650 | H12: DYGMO | I12: SI / NO | J12: Presencial | K12: Aperturado
A13: C1B1 | B13: M0005 | C13: 1706 | D13: SJL | E13: METOD. PARA UN APREND. EFIC. | F13: A | G13: 668513 | H13: DYGMO | I13: SI / NO | J13: Presencial | K13: Aperturado
... A1059: C1B2 | B1059: I0123 | C1059: 2653 | D1059: VENTN | E1059: T. DE COM. EF. Y RES. DE CONF. | F1059: N | G1059: 668952 | H1059: FISIO | I1059: SI / NO | J1059: Presencial | K1059: Aperturado

Sheet sheet2
A1: Nº Clase | B1: Campus | C1: ID | D1: ID Curso | E1: Nombre Curso | F1: Componente | G1: Sección | H1: Capacidad Inscripción | I1: Tot Inscr | J1: Nombre | K1: Turno Acad | L1: Ciclo | M1: Programas
A2: 2848 | B2: VIRTU | C2: 2017103040 | D2: 668832 | E2: CREATIVIDAD | F2: MIX | G2: 1T6 | H2: 40 | I2: 14 | J2: IPANAQUE PINGO,GISELA ISABEL | K2: N | L2: =VLOOKUP(D2,CONSOLIDADO!$L$1:$AG$893,22,FALSE) -> #N/A | M2: =VLOOKUP(D2,CONSOLIDADO!$L$1:$AI$893,24,FALSE) -> #N/A
A3: 2832 | B3: VIRTU | C3: 2017111229 | D3: 668743 | E3: CREATIVIDAD E INNOVACIÓN | F3: MIX | G3: 2R15 | H3: 40 | I3: 34 | J3: CUYA ESPICHAN,PERCY | K3: N | L3: =VLOOKUP(D3,CONSOLIDADO!$L$1:$AG$893,22,FALSE) -> #N/A | M3: =VLOOKUP(D3,CONSOLIDADO!$L$1:$AI$893,24,FALSE) -> #N/A
A4: 2831 | B4: VIRTU | C4: 2017163027 | D4: 668743 | E4: CREATIVIDAD E INNOVACIÓN | F4: MIX | G4: 2G25 | H4: 40 | I4: 14 | J4: CHIANG DIAZ,CARLOS ALBERTO | K4: M | L4: =VLOOKUP(D4,CONSOLIDADO!$L$1:$AG$893,22,FALSE) -> #N/A | M4: =VLOOKUP(D4,CONSOLIDADO!$L$1:$AI$893,24,FALSE) -> #N/A
A5: 2864 | B5: VIRTU | C5: 2017169984 | D5: 669100 | E5: COMERCIO INTERNACIONAL | F5: MIX | G5: 3S4 | H5: 40 | I5: 28 | J5: SALAZAR MORALES,ANIBAL FRANCISCO | K5: N | L5: =VLOOKUP(D5,CONSOLIDADO!$L$1:$AG$893,22,FALSE) -> #N/A | M5: =VLOOKUP(D5,CONSOLIDADO!$L$1:$AI$893,24,FALSE) -> #N/A
A6: 2806 | B6: VIRTU | C6: 2017185513 | D6: 668528 | E6: T. DE MET. ÁGIL. PARA LA INNO. | F6: MIX | G6: 3W1 | H6: 40 | I6: 27 | J6: Romero Azabache,Miguel Arturo | K6: N | L6: =VLOOKUP(D6,CONSOLIDADO!$L$1:$AG$893,22,FALSE) -> #N/A | M6: =VLOOKUP(D6,CONSOLIDADO!$L$1:$AI$893,24,FALSE) -> #N/A
A7: 2795 | B7: VIRTU | C7: 2017214605 | D7: 668513 | E7: METOD. PARA UN APREND. EFIC. | F7: MIX | G7: 1V9 | H7: 40 | I7: 35 | J7: GONZALEZ ANGELATS,EVA ANA | K7: N | L7: =VLOOKUP(D7,CONSOLIDADO!$L$1:$AG$893,22,FALSE) -> #N/A | M7: =VLOOKUP(D7,CONSOLIDADO!$L$1:$AI$893,24,FALSE) -> #N/A
A8: 2793 | B8: VIRTU | C8: 2017214605 | D8: 668513 | E8: METOD. PARA UN APREND. EFIC. | F8: MIX | G8: 1W1 | H8: 40 | I8: 19 | J8: GONZALEZ ANGELATS,EVA ANA | K8: N | L8: =VLOOKUP(D8,CONSOLIDADO!$L$1:$AG$893,22,FALSE) -> #N/A | M8: =VLOOKUP(D8,CONSOLIDADO!$L$1:$AI$893,24,FALSE) -> #N/A
A9: 2857 | B9: VIRTU | C9: 2017236914 | D9: 668905 | E9: CONTABILIDAD INTERMEDIA | F9: MIX | G9: 3S4 | H9: 40 | I9: 9 | J9: ACUNA APARCANA,ALDO ALI | K9: N | L9: =VLOOKUP(D9,CONSOLIDADO!$L$1:$AG$893,22,FALSE) -> #N/A | M9: =VLOOKUP(D9,CONSOLIDADO!$L$1:$AI$893,24,FALSE) -> #N/A
A10: 2809 | B10: VIRTU | C10: 2017252688 | D10: 668530 | E10: INTRODUCCIÓN DE LAS REDES | F10: MIX | G10: 3V3 | H10: 20 | I10: 12 | J10: ALCANTARA ALVAN,ADRIAN ANGELO | K10: N | L10: =VLOOKUP(D10,CONSOLIDADO!$L$1:$AG$893,22,FALSE) -> #N/A | M10: =VLOOKUP(D10,CONSOLIDADO!$L$1:$AI$893,24,FALSE) -> #N/A
A11: 2830 | B11: VIRTU | C11: 2017266298 | D11: 668742 | E11: CONTABILIDAD I | F11: MIX | G11: 2W1 | H11: 40 | I11: 29 | J11: Lagos Dominguez,Jorge Carlos | K11: N | L11: =VLOOKUP(D11,CONSOLIDADO!$L$1:$AG$893,22,FALSE) -> #N/A | M11: =VLOOKUP(D11,CONSOLIDADO!$L$1:$AI$893,24,FALSE) -> #N/A
A12: 2838 | B12: VIRTU | C12: 2017266298 | D12: 668749 | E12: CONTABILIDAD II | F12: MIX | G12: 3W1 | H12: 40 | I12: 26 | J12: Lagos Dominguez,Jorge Carlos | K12: N | L12: =VLOOKUP(D12,CONSOLIDADO!$L$1:$AG$893,22,FALSE) -> #N/A | M12: =VLOOKUP(D12,CONSOLIDADO!$L$1:$AI$893,24,FALSE) -> #N/A
A13: 2841 | B13: VIRTU | C13: 2017266298 | D13: 668754 | E13: ECONOMÍA PARA LOS NEGOCIOS | F13: MIX | G13: 4W1 | H13: 40 | I13: 14 | J13: Lagos Dominguez,Jorge Carlos | K13: N | L13: =VLOOKUP(D13,CONSOLIDADO!$L$1:$AG$893,22,FALSE) -> #N/A | M13: =VLOOKUP(D13,CONSOLIDADO!$L$1:$AI$893,24,FALSE) -> #N/A
... A36: 2816 | B36: VIRTU | C36: 2017505415 | D36: 668686 | E36: ADMINISTRACIÓN GENERAL | F36: MIX | G36: 1R15 | H36: 40 | I36: 19 | J36: Quiroz Huaman,Sarai Raquel | K36: N | L36: =VLOOKUP(D36,CONSOLIDADO!$L$1:$AG$893,22,FALSE) -> #N/A | M36: =VLOOKUP(D36,CONSOLIDADO!$L$1:$AI$893,24,FALSE) -> #N/A
A37: 2824 | B37: VIRTU | C37: I100000772 | D37: 668741 | E37: ESTADÍS. APLIC. A LOS NEGOCIOS | F37: MIX | G37: 2R15 | H37: 40 | I37: 24 | J37: AGUIRRE QUISPE, YANINA DINA | K37: N | L37: =VLOOKUP(D37,CONSOLIDADO!$L$1:$AG$893,22,FALSE) -> #N/A | M37: =VLOOKUP(D37,CONSOLIDADO!$L$1:$AI$893,24,FALSE) -> #N/A
A38: 2842 | B38: VIRTU | C38: I100000891 | D38: 668755 | E38: ADMINISTRACIÓN DE LA PRODUCCIÓ | F38: MIX | G38: 4R | H38: 40 | I38: 20 | J38: CHUMPITAZ SANCHEZ,VICTOR ANDRES | K38: N | L38: =VLOOKUP(D38,CONSOLIDADO!$L$1:$AG$893,22,FALSE) -> #N/A | M38: =VLOOKUP(D38,CONSOLIDADO!$L$1:$AI$893,24,FALSE) -> #N/A
A39: 2796 | B39: VIRTU | C39: I100000910 | D39: 668514 | E39: REDES DE COMPUTADORAS | F39: MIX | G39: 1V9 | H39: 40 | I39: 15 | J39: CRUZ RAMOS, WALDIR CIRO | K39: N | L39: =VLOOKUP(D39,CONSOLIDADO!$L$1:$AG$893,22,FALSE) -> #N/A | M39: =VLOOKUP(D39,CONSOLIDADO!$L$1:$AI$893,24,FALSE) -> #N/A
A40: 2819 | B40: VIRTU | C40: I100000923 | D40: 668692 | E40: MATEMÁTICA COMERCIAL | F40: MIX | G40: 1G25 | H40: 40 | I40: 18 | J40: DELROSARIO SORIA, PEDRO RICHARD | K40: M | L40: =VLOOKUP(D40,CONSOLIDADO!$L$1:$AG$893,22,FALSE) -> #N/A | M40: =VLOOKUP(D40,CONSOLIDADO!$L$1:$AI$893,24,FALSE) -> #N/A
A41: 2802 | B41: VIRTU | C41: I100000928 | D41: 668516 | E41: T. DE INFORM. PARA LA EMPLEAB. | F41: MIX | G41: 2W1 | H41: 40 | I41: 24 | J41: DELGADO SALAS, EDUARDO MANUEL | K41: N | L41: =VLOOKUP(D41,CONSOLIDADO!$L$1:$AG$893,22,FALSE) -> #N/A | M41: =VLOOKUP(D41,CONSOLIDADO!$L$1:$AI$893,24,FALSE) -> #N/A
A42: 2846 | B42: VIRTU | C42: I100000928 | D42: 668823 | E42: EXCEL AVAN. Y AC. EMPRE. | F42: MIX | G42: 4W1 | H42: 40 | I42: 12 | J42: DELGADO SALAS, EDUARDO MANUEL | K42: N | L42: =VLOOKUP(D42,CONSOLIDADO!$L$1:$AG$893,22,FALSE) -> #N/A | M42: =VLOOKUP(D42,CONSOLIDADO!$L$1:$AI$893,24,FALSE) -> #N/A
A43: 2804 | B43: VIRTU | C43: I100000936 | D43: 668516 | E43: T. DE INFORM. PARA LA EMPLEAB. | F43: MIX | G43: 2V2 | H43: 40 | I43: 17 | J43: DONGO TERNERO,JOSE RICARDO | K43: N | L43: =VLOOKUP(D43,CONSOLIDADO!$L$1:$AG$893,22,FALSE) -> #N/A | M43: =VLOOKUP(D43,CONSOLIDADO!$L$1:$AI$893,24,FALSE) -> #N/A
A44: 2823 | B44: VIRTU | C44: I100000941 | D44: 668705 | E44: FUNDAMENTOS DE MARKETING | F44: MIX | G44: 1W1 | H44: 40 | I44: 19 | J44: ELIAS TEJADA,MARIA YSABEL | K44: N | L44: =VLOOKUP(D44,CONSOLIDADO!$L$1:$AG$893,22,FALSE) -> #N/A | M44: =VLOOKUP(D44,CONSOLIDADO!$L$1:$AI$893,24,FALSE) -> #N/A
A45: 2844 | B45: VIRTU | C45: I100000941 | D45: 668817 | E45: REDACCIÓN COMERCIAL | F45: MIX | G45: 2W1 | H45: 40 | I45: 28 | J45: ELIAS TEJADA,MARIA YSABEL | K45: N | L45: =VLOOKUP(D45,CONSOLIDADO!$L$1:$AG$893,22,FALSE) -> #N/A | M45: =VLOOKUP(D45,CONSOLIDADO!$L$1:$AI$893,24,FALSE) -> #N/A
A46: 2860 | B46: VIRTU | C46: I100000985 | D46: 668952 | E46: T. DE COM. EF. Y RES. DE CONF. | F46: MIX | G46: 1G25 | H46: 40 | I46: 20 | J46: GARRIAZO RAMOS, FLOR DE MARIA | K46: M | L46: =VLOOKUP(D46,CONSOLIDADO!$L$1:$AG$893,22,FALSE) -> #N/A | M46: =VLOOKUP(D46,CONSOLIDADO!$L$1:$AI$893,24,FALSE) -> #N/A
A47: 2790 | B47: VIRTU | C47: I100000996 | D47: 668513 | E47: METOD. PARA UN APREND. EFIC. | F47: MIX | G47: 1R14 | H47: 40 | I47: 38 | J47: GONZALES VALVERDE, LOURDES CECILIA | K47: N | L47: =VLOOKUP(D47,CONSOLIDADO!$L$1:$AG$893,22,FALSE) -> #N/A | M47: =VLOOKUP(D47,CONSOLIDADO!$L$1:$AI$893,24,FALSE) -> #N/A
A48: 2791 | B48: VIRTU | C48: I100000996 | D48: 668513 | E48: METOD. PARA UN APREND. EFIC. | F48: MIX | G48: 1R15 | H48: 40 | I48: 20 | J48: GONZALES VALVERDE, LOURDES CECILIA | K48: N | L48: =VLOOKUP(D48,CONSOLIDADO!$L$1:$AG$893,22,FALSE) -> #N/A | M48: =VLOOKUP(D48,CONSOLIDADO!$L$1:$AI$893,24,FALSE) -> #N/A
... A91: 2866 | B91: VIRTU | C91: I100093338 | D91: 669102 | E91: COMERCIO INTERNACIONAL | F91: MIX | G91: 3W1 | H91: 40 | I91: 28 | J91: CHAVEZ COCA,MONICA | K91: N | L91: =VLOOKUP(D91,CONSOLIDADO!$L$1:$AG$893,22,FALSE) -> #N/A | M91: =VLOOKUP(D91,CONSOLIDADO!$L$1:$AI$893,24,FALSE) -> #N/A
A92: 2684 | B92: VILLA | C92: 100060543 | D92: 668516 | E92: T. DE INFORM. PARA LA EMPLEAB. | F92: MIX | G92: 2X1 | H92: 22 | I92: 18 | J92: DE LA CRUZ RODRIGUEZ,PORFIRIO JIMMY | K92: N | L92: =VLOOKUP(D92,CONSOLIDADO!$L$1:$AG$893,22,FALSE) -> #N/A | M92: =VLOOKUP(D92,CONSOLIDADO!$L$1:$AI$893,24,FALSE) -> #N/A
A93: 2773 | B93: VILLA | C93: 1100001183 | D93: 668952 | E93: T. DE COM. EF. Y RES. DE CONF. | F93: MIX | G93: 1I3 | H93: 35 | I93: 13 | J93: PINGLO VELA,MANUEL | K93: M | L93: =VLOOKUP(D93,CONSOLIDADO!$L$1:$AG$893,22,FALSE) -> #N/A | M93: =VLOOKUP(D93,CONSOLIDADO!$L$1:$AI$893,24,FALSE) -> #N/A
A94: 2892 | B94: VILLA | C94: 1100004606 | D94: 668724 | E94: COCINA LATINOAMERICANA | F94: MIX | G94: 2M11 | H94: 20 | I94: 0 | J94: XXXXXXXX XXXXXXX,XXXXXXXX | K94: T | L94: =VLOOKUP(D94,CONSOLIDADO!$L$1:$AG$893,22,FALSE) -> #N/A | M94: =VLOOKUP(D94,CONSOLIDADO!$L$1:$AI$893,24,FALSE) -> #N/A
A95: 2769 | B95: VILLA | C95: 2017025183 | D95: 668902 | E95: CONTABILIDAD BÁSICA | F95: MIX | G95: 2R | H95: 22 | I95: 1 | J95: Sanchez Roman,Beatriz Alejandra | K95: N | L95: =VLOOKUP(D95,CONSOLIDADO!$L$1:$AG$893,22,FALSE) -> #N/A | M95: =VLOOKUP(D95,CONSOLIDADO!$L$1:$AI$893,24,FALSE) -> #N/A
A96: 2775 | B96: VILLA | C96: 2017095838 | D96: 668952 | E96: T. DE COM. EF. Y RES. DE CONF. | F96: MIX | G96: 1X2 | H96: 34 | I96: 3 | J96: Cerna Pulido,Anthony Toshio Alexander | K96: N | L96: =VLOOKUP(D96,CONSOLIDADO!$L$1:$AG$893,22,FALSE) -> #N/A | M96: =VLOOKUP(D96,CONSOLIDADO!$L$1:$AI$893,24,FALSE) -> #N/A
A97: 2667 | B97: VILLA | C97: 2017104703 | D97: 9044 | E97: AUDITORÍA ADMINISTRATIVA | F97: MIX | G97: 6R | H97: 19 | I97: 10 | J97: Torres Centeno,Fredy Ronald | K97: N | L97: =VLOOKUP(D97,CONSOLIDADO!$L$1:$AG$893,22,FALSE) -> C6B2 | M97: =VLOOKUP(D97,CONSOLIDADO!$L$1:$AI$893,24,FALSE) -> ADMNE
A98: 2779 | B98: VILLA | C98: 2017111229 | D98: 669100 | E98: COMERCIO INTERNACIONAL | F98: MIX | G98: 3R | H98: 40 | I98: 40 | J98: CUYA ESPICHAN,PERCY | K98: N | L98: =VLOOKUP(D98,CONSOLIDADO!$L$1:$AG$893,22,FALSE) -> #N/A | M98: =VLOOKUP(D98,CONSOLIDADO!$L$1:$AI$893,24,FALSE) -> #N/A
A99: 2730 | B99: VILLA | C99: 2017139552 | D99: 668719 | E99: HIGIENE Y SEGURIDAD ALIMENTARI | F99: MIX | G99: 1Z5 | H99: 40 | I99: 19 | J99: VILLANUEVA CARBONERO,JOSE MARTIN RAFAEL | K99: N | L99: =VLOOKUP(D99,CONSOLIDADO!$L$1:$AG$893,22,FALSE) -> #N/A | M99: =VLOOKUP(D99,CONSOLIDADO!$L$1:$AI$893,24,FALSE) -> #N/A
A100: 2704 | B100: VILLA | C100: 2017162082 | D100: 668579 | E100: F. QUÍ. Y BIOQ. EN EL SER HUM. | F100: MIX | G100: 1X2 | H100: 20 | I100: 3 | J100: Vila Sulca,Yusver Isael | K100: N | L100: =VLOOKUP(D100,CONSOLIDADO!$L$1:$AG$893,22,FALSE) -> #N/A | M100: =VLOOKUP(D100,CONSOLIDADO!$L$1:$AI$893,24,FALSE) -> #N/A
A101: 2709 | B101: VILLA | C101: 2017162082 | D101: 668582 | E101: BIOSEGURIDAD | F101: MIX | G101: 2I1 | H101: 40 | I101: 16 | J101: Vila Sulca,Yusver Isael | K101: M | L101: =VLOOKUP(D101,CONSOLIDADO!$L$1:$AG$893,22,FALSE) -> #N/A | M101: =VLOOKUP(D101,CONSOLIDADO!$L$1:$AI$893,24,FALSE) -> #N/A
A102: 2689 | B102: VILLA | C102: 2017163027 | D102: 668528 | E102: T. DE MET. ÁGIL. PARA LA INNO. | F102: MIX | G102: 3G | H102: 40 | I102: 25 | J102: CHIANG DIAZ,CARLOS ALBERTO | K102: M | L102: =VLOOKUP(D102,CONSOLIDADO!$L$1:$AG$893,22,FALSE) -> #N/A | M102: =VLOOKUP(D102,CONSOLIDADO!$L$1:$AI$893,24,FALSE) -> #N/A
A103: 2674 | B103: VILLA | C103: 2017171362 | D103: 668513 | E103: METOD. PARA UN APREND. EFIC. | F103: MIX | G103: 1D | H103: 20 | I103: 16 | J103: Ortega Zorrilla,Ruth Maria | K103: M | L103: =VLOOKUP(D103,CONSOLIDADO!$L$1:$AG$893,22,FALSE) -> #N/A | M103: =VLOOKUP(D103,CONSOLIDADO!$L$1:$AI$893,24,FALSE) -> #N/A
... A166: 2694 | B166: VILLA | C166: 9200910538 | D166: 668535 | E166: T. DE TÉCN. PARA LA ARGUMENT. | F166: MIX | G166: 4I1 | H166: 24 | I166: 17 | J166: MELENDEZ ESPICHAN,JORGE HERNAN | K166: M | L166: =VLOOKUP(D166,CONSOLIDADO!$L$1:$AG$893,22,FALSE) -> #N/A | M166: =VLOOKUP(D166,CONSOLIDADO!$L$1:$AI$893,24,FALSE) -> #N/A
A167: 2722 | B167: VILLA | C167: I100000772 | D167: 668692 | E167: MATEMÁTICA COMERCIAL | F167: MIX | G167: 1G | H167: 22 | I167: 8 | J167: AGUIRRE QUISPE, YANINA DINA | K167: M | L167: =VLOOKUP(D167,CONSOLIDADO!$L$1:$AG$893,22,FALSE) -> #N/A | M167: =VLOOKUP(D167,CONSOLIDADO!$L$1:$AI$893,24,FALSE) -> #N/A
A168: 2744 | B168: VILLA | C168: I100000772 | D168: 668741 | E168: ESTADÍS. APLIC. A LOS NEGOCIOS | F168: MIX | G168: 2G | H168: 40 | I168: 21 | J168: AGUIRRE QUISPE, YANINA DINA | K168: M | L168: =VLOOKUP(D168,CONSOLIDADO!$L$1:$AG$893,22,FALSE) -> #N/A | M168: =VLOOKUP(D168,CONSOLIDADO!$L$1:$AI$893,24,FALSE) -> #N/A
A169: 2745 | B169: VILLA | C169: I100000772 | D169: 668741 | E169: ESTADÍS. APLIC. A LOS NEGOCIOS | F169: MIX | G169: 2R | H169: 40 | I169: 24 | J169: AGUIRRE QUISPE, YANINA DINA | K169: N | L169: =VLOOKUP(D169,CONSOLIDADO!$L$1:$AG$893,22,FALSE) -> #N/A | M169: =VLOOKUP(D169,CONSOLIDADO!$L$1:$AI$893,24,FALSE) -> #N/A
A170: 2761 | B170: VILLA | C170: I100000812 | D170: 668835 | E170: DISEÑO DIGITAL ILLUSTRATOR | F170: MIX | G170: 1C | H170: 20 | I170: 14 | J170: AYALA CABEZAS, YONATAN | K170: M | L170: =VLOOKUP(D170,CONSOLIDADO!$L$1:$AG$893,22,FALSE) -> #N/A | M170: =VLOOKUP(D170,CONSOLIDADO!$L$1:$AI$893,24,FALSE) -> #N/A
A171: 2766 | B171: VILLA | C171: I100000812 | D171: 668844 | E171: DISEÑO DIGITAL (INDESIGN) | F171: MIX | G171: 3D | H171: 20 | I171: 7 | J171: AYALA CABEZAS, YONATAN | K171: M | L171: =VLOOKUP(D171,CONSOLIDADO!$L$1:$AG$893,22,FALSE) -> #N/A | M171: =VLOOKUP(D171,CONSOLIDADO!$L$1:$AI$893,24,FALSE) -> #N/A
A172: 2772 | B172: VILLA | C172: I100000996 | D172: 668952 | E172: T. DE COM. EF. Y RES. DE CONF. | F172: MIX | G172: 1G | H172: 22 | I172: 8 | J172: GONZALES VALVERDE, LOURDES CECILIA | K172: M | L172: =VLOOKUP(D172,CONSOLIDADO!$L$1:$AG$893,22,FALSE) -> #N/A | M172: =VLOOKUP(D172,CONSOLIDADO!$L$1:$AI$893,24,FALSE) -> #N/A
A173: 2678 | B173: VILLA | C173: I100001325 | D173: 668515 | E173: ALGORITMOS Y TALLER DE PROGR. | F173: MIX | G173: 1D | H173: 22 | I173: 17 | J173: URIBE PACHECO, LUIS MIGUEL | K173: M | L173: =VLOOKUP(D173,CONSOLIDADO!$L$1:$AG$893,22,FALSE) -> #N/A | M173: =VLOOKUP(D173,CONSOLIDADO!$L$1:$AI$893,24,FALSE) -> #N/A
A174: 2677 | B174: VILLA | C174: I100001339 | D174: 668514 | E174: REDES DE COMPUTADORAS | F174: MIX | G174: 1D | H174: 20 | I174: 16 | J174: VALLEJOS PAULETT,ANDRES | K174: M | L174: =VLOOKUP(D174,CONSOLIDADO!$L$1:$AG$893,22,FALSE) -> #N/A | M174: =VLOOKUP(D174,CONSOLIDADO!$L$1:$AI$893,24,FALSE) -> #N/A
A175: 2686 | B175: VILLA | C175: I100002625 | D175: 668516 | E175: T. DE INFORM. PARA LA EMPLEAB. | F175: MIX | G175: 2A10 | H175: 22 | I175: 16 | J175: ALZAMORA WILSON,ROMINA LUZERO | K175: M | L175: =VLOOKUP(D175,CONSOLIDADO!$L$1:$AG$893,22,FALSE) -> #N/A | M175: =VLOOKUP(D175,CONSOLIDADO!$L$1:$AI$893,24,FALSE) -> #N/A
A176: 2680 | B176: VILLA | C176: I100002625 | D176: 668516 | E176: T. DE INFORM. PARA LA EMPLEAB. | F176: MIX | G176: 2I1 | H176: 22 | I176: 15 | J176: ALZAMORA WILSON,ROMINA LUZERO | K176: M | L176: =VLOOKUP(D176,CONSOLIDADO!$L$1:$AG$893,22,FALSE) -> #N/A | M176: =VLOOKUP(D176,CONSOLIDADO!$L$1:$AI$893,24,FALSE) -> #N/A
A177: 2687 | B177: VILLA | C177: I100002625 | D177: 668516 | E177: T. DE INFORM. PARA LA EMPLEAB. | F177: MIX | G177: 2M11 | H177: 22 | I177: 0 | J177: ALZAMORA WILSON,ROMINA LUZERO | K177: T | L177: =VLOOKUP(D177,CONSOLIDADO!$L$1:$AG$893,22,FALSE) -> #N/A | M177: =VLOOKUP(D177,CONSOLIDADO!$L$1:$AI$893,24,FALSE) -> #N/A
A178: 2692 | B178: VILLA | C178: I100002983 | D178: 668528 | E178: T. DE MET. ÁGIL. PARA LA INNO. | F178: MIX | G178: 3R | H178: 49 | I178: 49 | J178: MIRANDA FUENTES,WILLIAM DANIEL | K178: N | L178: =VLOOKUP(D178,CONSOLIDADO!$L$1:$AG$893,22,FALSE) -> #N/A | M178: =VLOOKUP(D178,CONSOLIDADO!$L$1:$AI$893,24,FALSE) -> #N/A
... A205: 2679 | B205: VILLA | C205: I100092467 | D205: 668516 | E205: T. DE INFORM. PARA LA EMPLEAB. | F205: MIX | G205: 2G | H205: 30 | I205: 13 | J205: Guevara Montenegro,Andres | K205: M | L205: =VLOOKUP(D205,CONSOLIDADO!$L$1:$AG$893,22,FALSE) -> #N/A | M205: =VLOOKUP(D205,CONSOLIDADO!$L$1:$AI$893,24,FALSE) -> #N/A
A206: 2568 | B206: VENTN | C206: 2017095552 | D206: 9045 | E206: GESTIÓN DE PROCESOS | F206: TER | G206: 6R8 | H206: 21 | I206: 13 | J206: Gutierrez Pilco,Jorge Joel | K206: N | L206: =VLOOKUP(D206,CONSOLIDADO!$L$1:$AG$893,22,FALSE) -> C6B2 | M206: =VLOOKUP(D206,CONSOLIDADO!$L$1:$AI$893,24,FALSE) -> ADMNE
A207: 2643 | B207: VENTN | C207: 2017126200 | D207: 668747 | E207: TÉCNICAS DE VENTAS | F207: MIX | G207: 3R10 | H207: 26 | I207: 8 | J207: FRANCO LAZARTE,ERICK GIOVANNI | K207: N | L207: =VLOOKUP(D207,CONSOLIDADO!$L$1:$AG$893,22,FALSE) -> #N/A | M207: =VLOOKUP(D207,CONSOLIDADO!$L$1:$AI$893,24,FALSE) -> #N/A
A208: 2574 | B208: VENTN | C208: 2017162964 | D208: 668513 | E208: METOD. PARA UN APREND. EFIC. | F208: MIX | G208: 1I21 | H208: 29 | I208: 4 | J208: SALVADOR ESCOBAR,JONY EDUARDO | K208: M | L208: =VLOOKUP(D208,CONSOLIDADO!$L$1:$AG$893,22,FALSE) -> #N/A | M208: =VLOOKUP(D208,CONSOLIDADO!$L$1:$AI$893,24,FALSE) -> #N/A
A209: 2651 | B209: VENTN | C209: 2017162964 | D209: 668952 | E209: T. DE COM. EF. Y RES. DE CONF. | F209: MIX | G209: 1G07 | H209: 19 | I209: 19 | J209: SALVADOR ESCOBAR,JONY EDUARDO | K209: M | L209: =VLOOKUP(D209,CONSOLIDADO!$L$1:$AG$893,22,FALSE) -> #N/A | M209: =VLOOKUP(D209,CONSOLIDADO!$L$1:$AI$893,24,FALSE) -> #N/A
A210: 2652 | B210: VENTN | C210: 2017162964 | D210: 668952 | E210: T. DE COM. EF. Y RES. DE CONF. | F210: MIX | G210: 1G08 | H210: 29 | I210: 11 | J210: SALVADOR ESCOBAR,JONY EDUARDO | K210: M | L210: =VLOOKUP(D210,CONSOLIDADO!$L$1:$AG$893,22,FALSE) -> #N/A | M210: =VLOOKUP(D210,CONSOLIDADO!$L$1:$AI$893,24,FALSE) -> #N/A
A211: 2639 | B211: VENTN | C211: 2017167780 | D211: 668742 | E211: CONTABILIDAD I | F211: MIX | G211: 2R14 | H211: 26 | I211: 7 | J211: VILLANUEVA HERNANDEZ,EDGAR | K211: N | L211: =VLOOKUP(D211,CONSOLIDADO!$L$1:$AG$893,22,FALSE) -> #N/A | M211: =VLOOKUP(D211,CONSOLIDADO!$L$1:$AI$893,24,FALSE) -> #N/A
A212: 2642 | B212: VENTN | C212: 2017167780 | D212: 668747 | E212: TÉCNICAS DE VENTAS | F212: MIX | G212: 3G08 | H212: 16 | I212: 7 | J212: VILLANUEVA HERNANDEZ,EDGAR | K212: M | L212: =VLOOKUP(D212,CONSOLIDADO!$L$1:$AG$893,22,FALSE) -> #N/A | M212: =VLOOKUP(D212,CONSOLIDADO!$L$1:$AI$893,24,FALSE) -> #N/A
A213: 2645 | B213: VENTN | C213: 2017167780 | D213: 668749 | E213: CONTABILIDAD II | F213: MIX | G213: 3R10 | H213: 22 | I213: 8 | J213: VILLANUEVA HERNANDEZ,EDGAR | K213: N | L213: =VLOOKUP(D213,CONSOLIDADO!$L$1:$AG$893,22,FALSE) -> #N/A | M213: =VLOOKUP(D213,CONSOLIDADO!$L$1:$AI$893,24,FALSE) -> #N/A
A214: 2623 | B214: VENTN | C214: 2017255679 | D214: 668588 | E214: MATEMÁTICA APLICADA EN SALUD | F214: MIX | G214: 3I10 | H214: 40 | I214: 31 | J214: CHAVARRIA CARRASCO,LISVET MANUELA | K214: M | L214: =VLOOKUP(D214,CONSOLIDADO!$L$1:$AG$893,22,FALSE) -> #N/A | M214: =VLOOKUP(D214,CONSOLIDADO!$L$1:$AI$893,24,FALSE) -> #N/A
A215: 2624 | B215: VENTN | C215: 2017255679 | D215: 668588 | E215: MATEMÁTICA APLICADA EN SALUD | F215: MIX | G215: 3I11 | H215: 40 | I215: 24 | J215: CHAVARRIA CARRASCO,LISVET MANUELA | K215: M | L215: =VLOOKUP(D215,CONSOLIDADO!$L$1:$AG$893,22,FALSE) -> #N/A | M215: =VLOOKUP(D215,CONSOLIDADO!$L$1:$AI$893,24,FALSE) -> #N/A
A216: 2593 | B216: VENTN | C216: 2017266302 | D216: 668576 | E216: ANATOMÍA Y FISIOLOGÍA HUMANA | F216: MIX | G216: 1I20 | H216: 32 | I216: 32 | J216: MATIAS NOMBERTO,LUIS ALBERTO | K216: M | L216: =VLOOKUP(D216,CONSOLIDADO!$L$1:$AG$893,22,FALSE) -> #N/A | M216: =VLOOKUP(D216,CONSOLIDADO!$L$1:$AI$893,24,FALSE) -> #N/A
A217: 2595 | B217: VENTN | C217: 2017266302 | D217: 668576 | E217: ANATOMÍA Y FISIOLOGÍA HUMANA | F217: MIX | G217: 1I22 | H217: 32 | I217: 25 | J217: MATIAS NOMBERTO,LUIS ALBERTO | K217: M | L217: =VLOOKUP(D217,CONSOLIDADO!$L$1:$AG$893,22,FALSE) -> #N/A | M217: =VLOOKUP(D217,CONSOLIDADO!$L$1:$AI$893,24,FALSE) -> #N/A
... A261: 2646 | B261: VENTN | C261: 2201511347 | D261: 668836 | E261: TÉC. DE LA COMUNIC. AUDIOV. | F261: MIX | G261: 2C6 | H261: 16 | I261: 7 | J261: Espinoza Ruiz,Alexander Jordan | K261: M | L261: =VLOOKUP(D261,CONSOLIDADO!$L$1:$AG$893,22,FALSE) -> #N/A | M261: =VLOOKUP(D261,CONSOLIDADO!$L$1:$AI$893,24,FALSE) -> #N/A
A262: 2633 | B262: VENTN | C262: I100001015 | D262: 668692 | E262: MATEMÁTICA COMERCIAL | F262: MIX | G262: 1G07 | H262: 19 | I262: 19 | J262: HINOSTROZA ROCA, ELIEZER GERSON | K262: M | L262: =VLOOKUP(D262,CONSOLIDADO!$L$1:$AG$893,22,FALSE) -> #N/A | M262: =VLOOKUP(D262,CONSOLIDADO!$L$1:$AI$893,24,FALSE) -> #N/A
A263: 2634 | B263: VENTN | C263: I100001015 | D263: 668692 | E263: MATEMÁTICA COMERCIAL | F263: MIX | G263: 1G08 | H263: 29 | I263: 11 | J263: HINOSTROZA ROCA, ELIEZER GERSON | K263: M | L263: =VLOOKUP(D263,CONSOLIDADO!$L$1:$AG$893,22,FALSE) -> #N/A | M263: =VLOOKUP(D263,CONSOLIDADO!$L$1:$AI$893,24,FALSE) -> #N/A
A264: 2637 | B264: VENTN | C264: I100001015 | D264: 668741 | E264: ESTADÍS. APLIC. A LOS NEGOCIOS | F264: MIX | G264: 2G09 | H264: 40 | I264: 36 | J264: HINOSTROZA ROCA, ELIEZER GERSON | K264: M | L264: =VLOOKUP(D264,CONSOLIDADO!$L$1:$AG$893,22,FALSE) -> #N/A | M264: =VLOOKUP(D264,CONSOLIDADO!$L$1:$AI$893,24,FALSE) -> #N/A
A265: 2573 | B265: VENTN | C265: I100001299 | D265: 668513 | E265: METOD. PARA UN APREND. EFIC. | F265: MIX | G265: 1I20 | H265: 28 | I265: 28 | J265: SOTO MARCHENA,DAVID OMAR | K265: M | L265: =VLOOKUP(D265,CONSOLIDADO!$L$1:$AG$893,22,FALSE) -> #N/A | M265: =VLOOKUP(D265,CONSOLIDADO!$L$1:$AI$893,24,FALSE) -> #N/A
A266: 2575 | B266: VENTN | C266: I100001299 | D266: 668513 | E266: METOD. PARA UN APREND. EFIC. | F266: MIX | G266: 1I22 | H266: 32 | I266: 25 | J266: SOTO MARCHENA,DAVID OMAR | K266: M | L266: =VLOOKUP(D266,CONSOLIDADO!$L$1:$AG$893,22,FALSE) -> #N/A | M266: =VLOOKUP(D266,CONSOLIDADO!$L$1:$AI$893,24,FALSE) -> #N/A
A267: 2571 | B267: VENTN | C267: I100001299 | D267: 668513 | E267: METOD. PARA UN APREND. EFIC. | F267: MIX | G267: 1R12 | H267: 22 | I267: 22 | J267: SOTO MARCHENA,DAVID OMAR | K267: N | L267: =VLOOKUP(D267,CONSOLIDADO!$L$1:$AG$893,22,FALSE) -> #N/A | M267: =VLOOKUP(D267,CONSOLIDADO!$L$1:$AI$893,24,FALSE) -> #N/A
A268: 2653 | B268: VENTN | C268: I100001299 | D268: 668952 | E268: T. DE COM. EF. Y RES. DE CONF. | F268: MIX | G268: 1X19 | H268: 32 | I268: 7 | J268: SOTO MARCHENA,DAVID OMAR | K268: N | L268: =VLOOKUP(D268,CONSOLIDADO!$L$1:$AG$893,22,FALSE) -> #N/A | M268: =VLOOKUP(D268,CONSOLIDADO!$L$1:$AI$893,24,FALSE) -> #N/A
A269: 2581 | B269: VENTN | C269: I100003172 | D269: 668516 | E269: T. DE INFORM. PARA LA EMPLEAB. | F269: MIX | G269: 2G09 | H269: 20 | I269: 16 | J269: ABAD GUTIERREZ,RAQUEL SONIA | K269: M | L269: =VLOOKUP(D269,CONSOLIDADO!$L$1:$AG$893,22,FALSE) -> #N/A | M269: =VLOOKUP(D269,CONSOLIDADO!$L$1:$AI$893,24,FALSE) -> #N/A
A270: 2582 | B270: VENTN | C270: I100003247 | D270: 668516 | E270: T. DE INFORM. PARA LA EMPLEAB. | F270: MIX | G270: 2R14 | H270: 26 | I270: 7 | J270: YAURI CORDERO,JAYSUN ANTONI | K270: N | L270: =VLOOKUP(D270,CONSOLIDADO!$L$1:$AG$893,22,FALSE) -> #N/A | M270: =VLOOKUP(D270,CONSOLIDADO!$L$1:$AI$893,24,FALSE) -> #N/A
A271: 2587 | B271: VENTN | C271: I100003247 | D271: 668516 | E271: T. DE INFORM. PARA LA EMPLEAB. | F271: MIX | G271: 2X10 | H271: 26 | I271: 13 | J271: YAURI CORDERO,JAYSUN ANTONI | K271: N | L271: =VLOOKUP(D271,CONSOLIDADO!$L$1:$AG$893,22,FALSE) -> #N/A | M271: =VLOOKUP(D271,CONSOLIDADO!$L$1:$AI$893,24,FALSE) -> #N/A
A272: 2586 | B272: VENTN | C272: I100003247 | D272: 668516 | E272: T. DE INFORM. PARA LA EMPLEAB. | F272: MIX | G272: 2X9 | H272: 26 | I272: 12 | J272: YAURI CORDERO,JAYSUN ANTONI | K272: N | L272: =VLOOKUP(D272,CONSOLIDADO!$L$1:$AG$893,22,FALSE) -> #N/A | M272: =VLOOKUP(D272,CONSOLIDADO!$L$1:$AI$893,24,FALSE) -> #N/A
A273: 2570 | B273: VENTN | C273: I100003843 | D273: 9047 | E273: EXPE FORMATIVAS ESPECIALIZADAS | F273: PRC | G273: 6R8 | H273: 40 | I273: 18 | J273: RIOS ROCA, ROSARIO RINA | K273: N | L273: =VLOOKUP(D273,CONSOLIDADO!$L$1:$AG$893,22,FALSE) -> C6B2 | M273: =VLOOKUP(D273,CONSOLIDADO!$L$1:$AI$893,24,FALSE) -> ADMLO / ADMNE / ADMNI / MARKT
... A282: 2615 | B282: VENTN | C282: I100093428 | D282: 668582 | E282: BIOSEGURIDAD | F282: MIX | G282: 2X9 | H282: 40 | I282: 11 | J282: ENCINAS COLAN,HUGO ROGER | K282: N | L282: =VLOOKUP(D282,CONSOLIDADO!$L$1:$AG$893,22,FALSE) -> #N/A | M282: =VLOOKUP(D282,CONSOLIDADO!$L$1:$AI$893,24,FALSE) -> #N/A
A283: 2306 | B283: SURCO | C283: 100060543 | D283: 668516 | E283: T. DE INFORM. PARA LA EMPLEAB. | F283: MIX | G283: 2C11 | H283: 23 | I283: 16 | J283: DE LA CRUZ RODRIGUEZ,PORFIRIO JIMMY | K283: M | L283: =VLOOKUP(D283,CONSOLIDADO!$L$1:$AG$893,22,FALSE) -> #N/A | M283: =VLOOKUP(D283,CONSOLIDADO!$L$1:$AI$893,24,FALSE) -> #N/A
A284: 2327 | B284: SURCO | C284: 100060543 | D284: 668528 | E284: T. DE MET. ÁGIL. PARA LA INNO. | F284: MIX | G284: 3V1 | H284: 40 | I284: 21 | J284: DE LA CRUZ RODRIGUEZ,PORFIRIO JIMMY | K284: N | L284: =VLOOKUP(D284,CONSOLIDADO!$L$1:$AG$893,22,FALSE) -> #N/A | M284: =VLOOKUP(D284,CONSOLIDADO!$L$1:$AI$893,24,FALSE) -> #N/A
A285: 2549 | B285: SURCO | C285: 2017023502 | D285: 668994 | E285: FUND. BÁS. DEL DISE. INTERIOR | F285: MIX | G285: 1T | H285: 19 | I285: 17 | J285: Campos Sosa,Edgard Melvin | K285: N | L285: =VLOOKUP(D285,CONSOLIDADO!$L$1:$AG$893,22,FALSE) -> #N/A | M285: =VLOOKUP(D285,CONSOLIDADO!$L$1:$AI$893,24,FALSE) -> #N/A
A286: 2428 | B286: SURCO | C286: 2017025183 | D286: 668742 | E286: CONTABILIDAD I | F286: MIX | G286: 2R4 | H286: 19 | I286: 7 | J286: Sanchez Roman,Beatriz Alejandra | K286: N | L286: =VLOOKUP(D286,CONSOLIDADO!$L$1:$AG$893,22,FALSE) -> #N/A | M286: =VLOOKUP(D286,CONSOLIDADO!$L$1:$AI$893,24,FALSE) -> #N/A
A287: 2329 | B287: SURCO | C287: 2017031334 | D287: 668535 | E287: T. DE TÉCN. PARA LA ARGUMENT. | F287: MIX | G287: 4I2 | H287: 18 | I287: 14 | J287: Aranda Fuertes,Yoel Luciano | K287: M | L287: =VLOOKUP(D287,CONSOLIDADO!$L$1:$AG$893,22,FALSE) -> #N/A | M287: =VLOOKUP(D287,CONSOLIDADO!$L$1:$AI$893,24,FALSE) -> #N/A
A288: 2243 | B288: SURCO | C288: 2017095554 | D288: 9037 | E288: GESTIÓN DEL TALENTO HUMANO | F288: MIX | G288: 5R2 | H288: 40 | I288: 40 | J288: OLIVERA BEGAZO,MARCO ANTONIO ARMANDO | K288: N | L288: =VLOOKUP(D288,CONSOLIDADO!$L$1:$AG$893,22,FALSE) -> C5B2 | M288: =VLOOKUP(D288,CONSOLIDADO!$L$1:$AI$893,24,FALSE) -> ADMNE
A289: 2562 | B289: SURCO | C289: 2017103040 | D289: 669068 | E289: DISEÑO PUBLICITARIO | F289: MIX | G289: 3P | H289: 40 | I289: 7 | J289: IPANAQUE PINGO,GISELA ISABEL | K289: M | L289: =VLOOKUP(D289,CONSOLIDADO!$L$1:$AG$893,22,FALSE) -> #N/A | M289: =VLOOKUP(D289,CONSOLIDADO!$L$1:$AI$893,24,FALSE) -> #N/A
A290: 2104 | B290: SURCO | C290: 2017110522 | D290: 4235 | E290: DISEÑO DE PRENDAS DE ALTA COST | F290: PRC | G290: 5C1 | H290: 18 | I290: 11 | J290: OTSU SANCHEZ,MITSUKO MARIA | K290: M | L290: =VLOOKUP(D290,CONSOLIDADO!$L$1:$AG$893,22,FALSE) -> C5B1 | M290: =VLOOKUP(D290,CONSOLIDADO!$L$1:$AI$893,24,FALSE) -> DYGMO
A291: 2462 | B291: SURCO | C291: 2017111229 | D291: 668781 | E291: INTRODUCCIÓN A LA LOGÍSTICA | F291: MIX | G291: 1G | H291: 40 | I291: 22 | J291: CUYA ESPICHAN,PERCY | K291: M | L291: =VLOOKUP(D291,CONSOLIDADO!$L$1:$AG$893,22,FALSE) -> #N/A | M291: =VLOOKUP(D291,CONSOLIDADO!$L$1:$AI$893,24,FALSE) -> #N/A
A292: 2470 | B292: SURCO | C292: 2017111229 | D292: 668803 | E292: GESTIÓN DE ALMACENES | F292: MIX | G292: 4G | H292: 40 | I292: 6 | J292: CUYA ESPICHAN,PERCY | K292: M | L292: =VLOOKUP(D292,CONSOLIDADO!$L$1:$AG$893,22,FALSE) -> #N/A | M292: =VLOOKUP(D292,CONSOLIDADO!$L$1:$AI$893,24,FALSE) -> #N/A
A293: 2113 | B293: SURCO | C293: 2017112426 | D293: 5372 | E293: TALLER DE PROGRAMACION WEB | F293: PRC | G293: 5V2 | H293: 40 | I293: 32 | J293: DIAZ GARCIA,MIGUEL ANGEL | K293: N | L293: =VLOOKUP(D293,CONSOLIDADO!$L$1:$AG$893,22,FALSE) -> C5B1 | M293: =VLOOKUP(D293,CONSOLIDADO!$L$1:$AI$893,24,FALSE) -> SWSIS
A294: 2312 | B294: SURCO | C294: 2017123198 | D294: 668516 | E294: T. DE INFORM. PARA LA EMPLEAB. | F294: MIX | G294: 2T1 | H294: 20 | I294: 15 | J294: YATACO HINOSTROZA,LUIS EDUARDO | K294: N | L294: =VLOOKUP(D294,CONSOLIDADO!$L$1:$AG$893,22,FALSE) -> #N/A | M294: =VLOOKUP(D294,CONSOLIDADO!$L$1:$AI$893,24,FALSE) -> #N/A
... A502: 2902 | B502: SURCO | C502: 2017496105 | D502: 668632 | E502: TRASTORNOS DE LENGUAJE | F502: MIX | G502: 4X4 | H502: 17 | I502: 12 | J502: Mendoza Zea,Raquel Cecilia | K502: N | L502: =VLOOKUP(D502,CONSOLIDADO!$L$1:$AG$893,22,FALSE) -> #N/A | M502: =VLOOKUP(D502,CONSOLIDADO!$L$1:$AI$893,24,FALSE) -> #N/A
A503: 2904 | B503: SURCO | C503: 2017496105 | D503: 668634 | E503: VALORACIÓN FUNCIONAL MUSCULAR | F503: MIX | G503: 4X4 | H503: 16 | I503: 12 | J503: Mendoza Zea,Raquel Cecilia | L503: =VLOOKUP(D503,CONSOLIDADO!$L$1:$AG$893,22,FALSE) -> #N/A | M503: =VLOOKUP(D503,CONSOLIDADO!$L$1:$AI$893,24,FALSE) -> #N/A
A504: 2184 | B504: SURCO | C504: 2017496108 | D504: 7138 | E504: METO DE EXTRA E IDENTIFICACIÓN | F504: PRC | G504: 5X11 | H504: 27 | I504: 22 | J504: Minaya Alvarez,Martin Eduardo | K504: N | L504: =VLOOKUP(D504,CONSOLIDADO!$L$1:$AG$893,22,FALSE) -> C5B1 | M504: =VLOOKUP(D504,CONSOLIDADO!$L$1:$AI$893,24,FALSE) -> TECFA
A505: 2192 | B505: SURCO | C505: 2017496253 | D505: 7155 | E505: BIOMECÁNICA | F505: PRC | G505: 4X11 | H505: 17 | I505: 17 | J505: Tasayco Suarez,Judith Rubi | K505: N | L505: =VLOOKUP(D505,CONSOLIDADO!$L$1:$AG$893,22,FALSE) -> C4B1 | M505: =VLOOKUP(D505,CONSOLIDADO!$L$1:$AI$893,24,FALSE) -> FISIO
A506: 2903 | B506: SURCO | C506: 2017496253 | D506: 668633 | E506: INTR. A. AGE. FÍSI. EN FISIO. | F506: MIX | G506: 4X4 | H506: 16 | I506: 13 | J506: Tasayco Suarez,Judith Rubi | K506: N | L506: =VLOOKUP(D506,CONSOLIDADO!$L$1:$AG$893,22,FALSE) -> #N/A | M506: =VLOOKUP(D506,CONSOLIDADO!$L$1:$AI$893,24,FALSE) -> #N/A
A507: 2126 | B507: SURCO | C507: 2017500965 | D507: 5573 | E507: PRODUC. TELEVISIVA Y RAD. | F507: PRC | G507: 5C | H507: 31 | I507: 29 | J507: Quinones Chira,Anibal | K507: M | L507: =VLOOKUP(D507,CONSOLIDADO!$L$1:$AG$893,22,FALSE) -> C5B2 | M507: =VLOOKUP(D507,CONSOLIDADO!$L$1:$AI$893,24,FALSE) -> COMAU
A508: 2481 | B508: SURCO | C508: 2017500965 | D508: 668836 | E508: TÉC. DE LA COMUNIC. AUDIOV. | F508: MIX | G508: 2C1 | H508: 25 | I508: 9 | J508: Quinones Chira,Anibal | K508: M | L508: =VLOOKUP(D508,CONSOLIDADO!$L$1:$AG$893,22,FALSE) -> #N/A | M508: =VLOOKUP(D508,CONSOLIDADO!$L$1:$AI$893,24,FALSE) -> #N/A
A509: 2483 | B509: SURCO | C509: 2017500965 | D509: 668836 | E509: TÉC. DE LA COMUNIC. AUDIOV. | F509: MIX | G509: 2C12 | H509: 25 | I509: 19 | J509: Quinones Chira,Anibal | K509: M | L509: =VLOOKUP(D509,CONSOLIDADO!$L$1:$AG$893,22,FALSE) -> #N/A | M509: =VLOOKUP(D509,CONSOLIDADO!$L$1:$AI$893,24,FALSE) -> #N/A
A510: 2547 | B510: SURCO | C510: 2017500968 | D510: 668992 | E510: FUNDAMENTOS DEL DIBUJO TÉCNICO | F510: MIX | G510: 1T | H510: 19 | I510: 17 | J510: Cabrera Hernandez,Ian Marcelo | K510: N | L510: =VLOOKUP(D510,CONSOLIDADO!$L$1:$AG$893,22,FALSE) -> #N/A | M510: =VLOOKUP(D510,CONSOLIDADO!$L$1:$AI$893,24,FALSE) -> #N/A
...

Sheet sheet3
A1: Ciclo Lectivo | B1: Institución Académica | C1: Grado Académico | D1: Id_Alumno | E1: Nombre | F1: Programa Académico | G1: Descripción | H1: Plan Académico | I1: C1B1 | J1: C1B2 | K1: C2B1 | L1: C2B2 | M1: C3B1 | N1: C3B2 | O1: C4B1 | P1: C4B2 | Q1: C5B1 | R1: C5B2 | S1: C6B1 | T1: C6B2
A2: 3123 | B2: SISE | C2: PRGS | D2: 100009860 | E2: OSORIO CUYA,JESICA CAROLINA | F2: ADMNE | G2: ADMINISTRACION DE EMPRESAS | H2: ADM2020 | I2: OK | J2: OK | K2: 4 | L2: OK | M2: 4 | N2: 4 | O2: 3 | P2: 4 | Q2: 3 | R2: 4 | S2: 4 | T2: 4
A3: 3123 | B3: SISE | C3: PRGS | D3: 100026056 | E3: CAM SERNA,JHEXAEL YENYHIS | F3: SALUD | G3: ENFERMERIA TECNICA | H3: ENFTEC2020 | I3: OK | J3: OK | K3: OK | L3: 4 | M3: 4 | N3: 5 | O3: 4 | P3: 4 | Q3: 3 | R3: 4 | S3: 4 | T3: 4
A4: 3123 | B4: SISE | C4: PRGS | D4: 100054831 | E4: CARBAJAL ALIPAZAGA,YASUMI ALISON | F4: SALUD | G4: ENFERMERIA TECNICA | H4: ENFTEC2020 | I4: OK | J4: 2 | K4: OK | L4: 4 | M4: 4 | N4: 5 | O4: 4 | P4: 4 | Q4: 3 | R4: 4 | S4: 4 | T4: 4
A5: 3123 | B5: SISE | C5: PRGS | D5: 100072270 | E5: CALLE HUAMAN,CARLOS EDUARDO | F5: SWSIS | G5: DES DE SISTEMAS DE INFORMACION | H5: SOFT2020 | I5: OK | J5: OK | K5: OK | L5: OK | M5: OK | N5: OK | O5: 3 | P5: 4 | Q5: 3 | R5: 4 | S5: 4 | T5: 4
A6: 3123 | B6: SISE | C6: PRGS | D6: 100078635 | E6: CASTRO BRAVO,JEAN PIERRE | F6: ADMLO | G6: GESTIÓN LOGÍSTICA | H6: ADMLO2020 | I6: OK | J6: OK | K6: 4 | L6: 4 | M6: 4 | N6: 4 | O6: 3 | P6: 4 | Q6: 3 | R6: 4 | S6: 4 | T6: 4
A7: 3123 | B7: SISE | C7: PRGS | D7: 100083438 | E7: VILCHEZ TIJERO, PABLO ESTEBAN | F7: SWSIS | G7: DES DE SISTEMAS DE INFORMACION | H7: SOFT2020 | I7: 1 | J7: 1 | K7: 4 | L7: OK | M7: 3 | N7: 4 | O7: 3 | P7: 4 | Q7: 3 | R7: 4 | S7: 4 | T7: 4
A8: 3123 | B8: SISE | C8: PRGS | D8: 2017092999 | E8: CERRON CHAMBERGO,LIZBET KAREN | F8: TECFA | G8: TECNICA EN FARMACIA | H8: TECNFM2020 | I8: OK | J8: 4 | K8: 4 | L8: 4 | M8: 4 | N8: 4 | O8: 4 | P8: 4 | Q8: 4 | R8: 5 | S8: 4 | T8: 5
A9: 3123 | B9: SISE | C9: PRGS | D9: 100086971 | E9: Romo Cotos,Marcos Esteban | F9: ADMBF | G9: ADM. BANCARIA Y FINANCIERA | H9: ABF2020 | I9: OK | J9: OK | K9: 4 | L9: OK | M9: 4 | N9: 4 | O9: 3 | P9: 4 | Q9: 3 | R9: 4 | S9: 4 | T9: 4
A10: 3123 | B10: SISE | C10: PRGS | D10: 100088901 | E10: GARCIA MANCILLA,EVELIN DEYSI | F10: MARKT | G10: MARKETING | H10: MKT2020 | I10: OK | J10: 5 | K10: 4 | L10: 4 | M10: 4 | N10: 4 | O10: 3 | P10: 4 | Q10: 3 | R10: 4 | S10: 4 | T10: 4
A11: 3123 | B11: SISE | C11: PRGS | D11: 1100046612 | E11: GARCIA LUNA, JOSE SANTIAGO CRISTOPHER | F11: SALUD | G11: ENFERMERIA TECNICA | H11: ENFTEC2020 | I11: OK | J11: 6 | K11: 5 | L11: 4 | M11: 4 | N11: 5 | O11: 4 | P11: 4 | Q11: 3 | R11: 4 | S11: 4 | T11: 4
A12: 3123 | B12: SISE | C12: PRGS | D12: 1100072372 | E12: BALDERA TITO, ANGEL ROSSEL | F12: COMAU | G12: COMUNICACION AUDIOVISUAL | H12: COAU2020 | I12: 5 | J12: 5 | K12: 5 | L12: 4 | M12: 4 | N12: 4 | O12: 4 | P12: 4 | Q12: 4 | R12: 4 | S12: 5 | T12: 5
A13: 3123 | B13: SISE | C13: PRGS | D13: 1100081332 | E13: TEJADA DIAZ,ANGIE KRISTEL | F13: ADMNE | G13: ADMINISTRACION DE EMPRESAS | H13: ADM2020 | I13: OK | J13: OK | K13: 4 | L13: OK | M13: 4 | N13: 4 | O13: 3 | P13: 4 | Q13: 3 | R13: 4 | S13: 4 | T13: 4
A14: 3123 | B14: SISE | C14: PRGS | D14: 1100087527 | E14: SORIA CALLAÑAUPA, ESTEFANY DIANA | F14: ADMNE | G14: ADMINISTRACION DE EMPRESAS | H14: ADM2020 | I14: OK | J14: OK | K14: OK | L14: OK | M14: 1 | N14: OK | O14: OK | P14: OK | Q14: OK | R14: 4 | S14: 4 | T14: 4
A15: 3123 | B15: SISE | C15: PRGS | D15: 1100088250 | E15: CARPIO DIPAZ,TEOFILA | F15: COMAU | G15: COMUNICACION AUDIOVISUAL | H15: COAU2020 | I15: OK | J15: OK | K15: 5 | L15: 3 | M15: 4 | N15: 4 | O15: 4 | P15: 4 | Q15: 4 | R15: 4 | S15: 5 | T15: 5
A16: 3123 | B16: SISE | C16: PRGS | D16: 1100089894 | E16: CHUCHEN CARDENAS,SEBASTIAN MATHIAS | F16: REDES | G16: ADM DE REDES Y COMUNICACIONES | H16: RED2020 | I16: 6 | J16: 4 | K16: 4 | L16: 4 | M16: 3 | N16: 4 | O16: 3 | P16: 4 | Q16: 3 | R16: 4 | S16: 4 | T16: 4
A17: 3123 | B17: SISE | C17: PRGS | D17: 1201320407 | E17: Hirata Salvador,Ieykof Michel | F17: FISIO | G17: FISIOTERAPIA Y REHABILITACION | H17: FISYRE2020 | I17: OK | J17: 6 | K17: 5 | L17: 4 | M17: 4 | N17: 5 | O17: 4 | P17: 4 | Q17: 4 | R17: 5 | S17: 4 | T17: 4
A18: 3123 | B18: SISE | C18: PRGS | D18: 1201700494 | E18: REGAL SILVA,MARCELO | F18: COMAU | G18: COMUNICACION AUDIOVISUAL | H18: COAU2020 | I18: 4 | J18: 6 | K18: 5 | L18: 4 | M18: 4 | N18: 4 | O18: 4 | P18: 4 | Q18: 4 | R18: 4 | S18: 5 | T18: 5
A19: 3123 | B19: SISE | C19: PRGS | D19: 2017002838 | E19: CARRERA RICRA,DIANA JHANET | F19: SALUD | G19: ENFERMERIA TECNICA | H19: ENFTEC2020 | I19: OK | J19: OK | K19: OK | L19: OK | M19: OK | N19: OK | O19: 4 | P19: OK | Q19: 3 | R19: 4 | S19: 4 | T19: 4
A20: 3123 | B20: SISE | C20: PRGS | D20: 2017002992 | E20: VASQUEZ TORRES,VALERIA ISABEL | F20: ADMNI | G20: ADM DE NEGOCIOS INTERN | H20: NNII2020 | I20: OK | J20: OK | K20: OK | L20: OK | M20: OK | N20: OK | O20: 3 | P20: 4 | Q20: 3 | R20: 4 | S20: 4 | T20: 4
A21: 3123 | B21: SISE | C21: PRGS | D21: 2017003798 | E21: SANCARRANCO BAYONA,JESUS EDUARDO | F21: DG | G21: DISEÑO GRAFICO PROFESIONAL | H21: DISGRA2020 | I21: OK | J21: OK | K21: 5 | L21: 4 | M21: 4 | N21: 4 | O21: 3 | P21: 4 | Q21: 3 | R21: 5 | S21: 4 | T21: 4
A22: 3123 | B22: SISE | C22: PRGS | D22: 2017006426 | E22: AMACHI UCEDO,LINO JULIAN | F22: DG | G22: DISEÑO GRAFICO PROFESIONAL | H22: DISGRA2020 | I22: OK | J22: OK | K22: OK | L22: OK | M22: 4 | N22: 4 | O22: 3 | P22: 4 | Q22: 3 | R22: 5 | S22: 4 | T22: 4
A23: 3123 | B23: SISE | C23: PRGS | D23: 2017009626 | E23: SUÁREZ RIOS,JHONATAN ELVIS | F23: DG | G23: DISEÑO GRAFICO PROFESIONAL | H23: DISGRA2020 | I23: OK | J23: OK | K23: OK | L23: OK | M23: 4 | N23: 3 | O23: 3 | P23: 4 | Q23: 3 | R23: 5 | S23: 4 | T23: 4
A24: 3123 | B24: SISE | C24: PRGS | D24: 2017010003 | E24: AYALA GARATE,CENAYDA | F24: COMAU | G24: COMUNICACION AUDIOVISUAL | H24: COAU2020 | I24: OK | J24: OK | K24: 1 | L24: OK | M24: OK | N24: OK | O24: OK | P24: OK | Q24: 4 | R24: 4 | S24: 5 | T24: 5
A25: 3123 | B25: SISE | C25: PRGS | D25: 2017012022 | E25: HUERTA ROMERO,SONIA | F25: SALUD | G25: ENFERMERIA TECNICA | H25: ENFTEC2020 | I25: OK | J25: OK | K25: OK | L25: 3 | M25: 4 | N25: 5 | O25: 4 | P25: 4 | Q25: 3 | R25: 4 | S25: 4 | T25: 4
A26: 3123 | B26: SISE | C26: PRGS | D26: 2017012368 | E26: ROSALES HIDALGO,ANGELICA ROSSANA | F26: ADMNE | G26: ADMINISTRACION DE EMPRESAS | H26: ADM2020 | I26: OK | J26: OK | K26: OK | L26: OK | M26: OK | N26: OK | O26: OK | P26: 4 | Q26: 3 | R26: 4 | S26: 4 | T26: 4
A27: 3123 | B27: SISE | C27: PRGS | D27: 2017015666 | E27: HUAMANI VARGAS,MARCO ANDRE | F27: COMAU | G27: COMUNICACION AUDIOVISUAL | H27: COAU2020 | I27: 1 | J27: OK | K27: 5 | L27: 4 | M27: 4 | N27: 4 | O27: 4 | P27: 4 | Q27: 4 | R27: 4 | S27: 5 | T27: 5
A28: 3123 | B28: SISE | C28: PRGS | D28: 2017016000 | E28: MICHUE CHECA,FABRIZIO MICHEL | F28: ADMBF | G28: ADM. BANCARIA Y FINANCIERA | H28: ABF2020 | I28: OK | J28: OK | K28: 4 | L28: 4 | M28: 4 | N28: 4 | O28: 3 | P28: 4 | Q28: 3 | R28: 4 | S28: 4 | T28: 4
A29: 3123 | B29: SISE | C29: PRGS | D29: 2017016618 | E29: ANTEZANA FRAGIDEZ,ELIDIA | F29: SALUD | G29: ENFERMERIA TECNICA | H29: ENFERTECN | I29: OK | J29: 4 | K29: 4 | L29: 5 | M29: 4 | N29: 5 | O29: 4 | P29: 5 | Q29: 3 | R29: 4 | S29: 4 | T29: 4
A30: 3123 | B30: SISE | C30: PRGS | D30: 2017016813 | E30: CORDOVA PIZARRO,AMINADAB | F30: CONTA | G30: CONTABILIDAD | H30: COFI2020 | I30: 4 | J30: 5 | K30: 4 | L30: 4 | M30: 4 | N30: 4 | O30: 3 | P30: 4 | Q30: 3 | R30: 4 | S30: 4 | T30: 4
A31: 3123 | B31: SISE | C31: PRGS | D31: 2017018084 | E31: MELGAREJO RODRIGUEZ,JAIR RODRIGO | F31: DG | G31: DISEÑO GRAFICO PROFESIONAL | H31: DISGRA2020 | I31: 5 | J31: 5 | K31: 5 | L31: 4 | M31: 4 | N31: 4 | O31: 3 | P31: 4 | Q31: 3 | R31: 5 | S31: 4 | T31: 4
A32: 3123 | B32: SISE | C32: PRGS | D32: 2017019575 | E32: VELAZQUEZ DIAZ,GRISEL MEISY | F32: CONTA | G32: CONTABILIDAD | H32: COFI2020 | I32: 2 | J32: 5 | K32: 4 | L32: 4 | M32: 4 | N32: 4 | O32: 3 | P32: 4 | Q32: 3 | R32: 4 | S32: 4 | T32: 4
A33: 3123 | B33: SISE | C33: PRGS | D33: 2017019985 | E33: CARLOS PRIETO,ANGEL GABRIEL | F33: COMAU | G33: COMUNICACION AUDIOVISUAL | H33: COAU2020 | I33: OK | J33: OK | K33: 5 | L33: 4 | M33: 4 | N33: 4 | O33: 4 | P33: 4 | Q33: 4 | R33: 4 | S33: 5 | T33: 5
A34: 3123 | B34: SISE | C34: PRGS | D34: 2017020972 | E34: NINALAYA RODRIGUEZ,YAJAIRA | F34: ADMNE | G34: ADMINISTRACION DE EMPRESAS | H34: ADM2020 | I34: OK | J34: OK | K34: 3 | L34: OK | M34: 4 | N34: 4 | O34: 3 | P34: 4 | Q34: 3 | R34: 4 | S34: 4 | T34: 4
A35: 3123 | B35: SISE | C35: PRGS | D35: 2017021935 | E35: QUITO POLO,DIEGO ADOLFO | F35: ADMNE | G35: ADMINISTRACION DE EMPRESAS | H35: ADM2020 | I35: OK | J35: OK | K35: 4 | L35: OK | M35: 4 | N35: 4 | O35: 3 | P35: 4 | Q35: 3 | R35: 4 | S35: 4 | T35: 4
A36: 3123 | B36: SISE | C36: PRGS | D36: 2017023107 | E36: HERRERA QUINTO,OMAR ALEXIS | F36: GASTR | G36: GASTRONOMIA | H36: GAST2022 | I36: OK | J36: OK | K36: OK | L36: OK | M36: 4 | N36: 4 | O36: 6 | P36: 4
A37: 3123 | B37: SISE | C37: PRGS | D37: 2017023539 | E37: NOLASCO LUME,ROXANA | F37: TECFA | G37: TECNICA EN FARMACIA | H37: TECNFM2020 | I37: 5 | J37: 6 | K37: 5 | L37: 4 | M37: 4 | N37: 4 | O37: 4 | P37: 4 | Q37: 4 | R37: 5 | S37: 4 | T37: 5
A38: 3123 | B38: SISE | C38: PRGS | D38: 2017025086 | E38: CALDERON CANTO,EDGAR | F38: ADMNE | G38: ADMINISTRACION DE EMPRESAS | H38: ADM2020 | I38: OK | J38: 2 | K38: 4 | L38: 1 | M38: 4 | N38: 4 | O38: 3 | P38: 4 | Q38: 3 | R38: 4 | S38: 4 | T38: 4
A39: 3123 | B39: SISE | C39: PRGS | D39: 2017025853 | E39: VENTURO LEON,NINCOL KACELY | F39: COMAU | G39: COMUNICACION AUDIOVISUAL | H39: COAU2020 | I39: 5 | J39: 1 | K39: 5 | L39: 4 | M39: 4 | N39: 4 | O39: 4 | P39: 4 | Q39: 4 | R39: 4 | S39: 5 | T39: 5
A40: 3123 | B40: SISE | C40: PRGS | D40: 2017026543 | E40: AVILA SANCHEZ,ALDHAIR IVAN | F40: DG | G40: DISEÑO GRAFICO PROFESIONAL | H40: DISGRA2020 | I40: OK | J40: 1 | K40: 1 | L40: 1 | M40: 4 | N40: 4 | O40: 3 | P40: 4 | Q40: 3 | R40: 5 | S40: 4 | T40: 4
A41: 3123 | B41: SISE | C41: PRGS | D41: 2017028044 | E41: CHONATE DIAZ,CAROLINA LESLIE | F41: ADMBF | G41: ADM. BANCARIA Y FINANCIERA | H41: ABF2020 | I41: OK | J41: OK | K41: 4 | L41: OK | M41: 4 | N41: 4 | O41: 3 | P41: 4 | Q41: 3 | R41: 4 | S41: 4 | T41: 4
A42: 3123 | B42: SISE | C42: PRGS | D42: 2017028644 | E42: OLANO CALLE,LUIS ALEXANDER | F42: SALUD | G42: ENFERMERIA TECNICA | H42: ENFTEC2020 | I42: 5 | J42: 6 | K42: 5 | L42: 4 | M42: 4 | N42: 5 | O42: 4 | P42: 4 | Q42: 3 | R42: 4 | S42: 4 | T42: 4
A43: 3123 | B43: SISE | C43: PRGS | D43: 2017030459 | E43: SANCHEZ OROCHE,TERESA MAYTE | F43: SALUD | G43: ENFERMERIA TECNICA | H43: ENFTEC2020 | I43: 5 | J43: 2 | K43: 5 | L43: 4 | M43: 4 | N43: 5 | O43: 4 | P43: 4 | Q43: 3 | R43: 4 | S43: 4 | T43: 4
A44: 3123 | B44: SISE | C44: PRGS | D44: 2017030738 | E44: ROJAS ESPINOZA,LUCERO FIORELLA | F44: SALUD | G44: ENFERMERIA TECNICA | H44: ENFTEC2020 | I44: OK | J44: 6 | K44: 5 | L44: 4 | M44: 4 | N44: 5 | O44: 4 | P44: 4 | Q44: 3 | R44: 4 | S44: 4 | T44: 4
A45: 3123 | B45: SISE | C45: PRGS | D45: 2017031386 | E45: ALANYA REQUE,FLAVIA EMILIA | F45: ADMNE | G45: ADMINISTRACION DE EMPRESAS | H45: ADM2020 | I45: OK | J45: OK | K45: OK | L45: OK | M45: 4 | N45: 4 | O45: 3 | P45: 4 | Q45: 3 | R45: 4 | S45: 4 | T45: 4
A46: 3123 | B46: SISE | C46: PRGS | D46: 2017031481 | E46: CHUMPITAZ ROMAN,EBEAHIN MARGARITA | F46: CONTA | G46: CONTABILIDAD | H46: COFI2020 | I46: OK | J46: OK | K46: 3 | L46: OK | M46: 4 | N46: 4 | O46: 3 | P46: 4 | Q46: 3 | R46: 4 | S46: 4 | T46: 4
A47: 3123 | B47: SISE | C47: PRGS | D47: 2017031616 | E47: MORENO ROJAS,JANETH ALEJANDRA | F47: ADMNE | G47: ADMINISTRACION DE EMPRESAS | H47: ADM2020 | I47: OK | J47: OK | K47: 4 | L47: 2 | M47: 4 | N47: 4 | O47: 3 | P47: 4 | Q47: 3 | R47: 4 | S47: 4 | T47: 4
A48: 3123 | B48: SISE | C48: PRGS | D48: 2017032760 | E48: TENORIO MENDEZ,JACK ANDERSON | F48: REDES | G48: ADM DE REDES Y COMUNICACIONES | H48: RED2020 | I48: 6 | J48: OK | K48: 4 | L48: 4 | M48: 3 | N48: 4 | O48: 3 | P48: 4 | Q48: 3 | R48: 4 | S48: 4 | T48: 4
A49: 3123 | B49: SISE | C49: PRGS | D49: 2017032911 | E49: TOLENTINO ALDAZABAL,SUSIBEL BETSY | F49: SALUD | G49: ENFERMERIA TECNICA | H49: ENFTEC2020 | I49: 5 | J49: 6 | K49: 5 | L49: 4 | M49: 4 | N49: 5 | O49: 4 | P49: 4 | Q49: 3 | R49: 4 | S49: 4 | T49: 4
A50: 3123 | B50: SISE | C50: PRGS | D50: 2017033675 | E50: LULIMACHE TORRES,WILTON | F50: ADMNE | G50: ADMINISTRACION DE EMPRESAS | H50: ADM2020 | I50: OK | J50: OK | K50: 4 | L50: OK | M50: 4 | N50: 4 | O50: 3 | P50: 4 | Q50: 3 | R50: 4 | S50: 4 | T50: 4
A51: 3123 | B51: SISE | C51: PRGS | D51: 2017034863 | E51: MENDOZA CASTRO,LUIS FERNANDO | F51: COMAU | G51: COMUNICACION AUDIOVISUAL | H51: COAU2020 | I51: OK | J51: 1 | K51: 1 | L51: 1 | M51: 2 | N51: 1 | O51: 4 | P51: 4 | Q51: 4 | R51: 4 | S51: 5 | T51: 5
A52: 3123 | B52: SISE | C52: PRGS | D52: 2017035294 | E52: PASTOR CCASANI,LEONARDO ALEXANDER | F52: DG | G52: DISEÑO GRAFICO PROFESIONAL | H52: DISGRA2020 | I52: OK | J52: 3 | K52: 5 | L52: OK | M52: 4 | N52: 4 | O52: 3 | P52: 4 | Q52: 3 | R52: 5 | S52: 4 | T52: 4
A53: 3123 | B53: SISE | C53: PRGS | D53: 2017038271 | E53: HUAMANI LANDEO,RUTH SILVIA | F53: ADMNI | G53: ADM DE NEGOCIOS INTERN | H53: NNII2020 | I53: OK | J53: OK | K53: OK | L53: OK | M53: 4 | N53: 4 | O53: 3 | P53: 4 | Q53: 3 | R53: 4 | S53: 4 | T53: 4
A54: 3123 | B54: SISE | C54: PRGS | D54: 2017038474 | E54: VARGAS RENGIFO,EMILY | F54: GASTR | G54: GASTRONOMIA | H54: GAST2022 | I54: OK | J54: OK | K54: 6 | L54: 4 | M54: 4 | N54: 4 | O54: 6 | P54: 4
A55: 3123 | B55: SISE | C55: PRGS | D55: 2017040181 | E55: HUAYTALLA MAMANI,MARIA ALEJANDRA | F55: ADMBF | G55: ADM. BANCARIA Y FINANCIERA | H55: ABF2020 | I55: OK | J55: OK | K55: 1 | L55: OK | M55: 4 | N55: 4 | O55: 3 | P55: 4 | Q55: 3 | R55: 4 | S55: 4 | T55: 4
A56: 3123 | B56: SISE | C56: PRGS | D56: 2017040430 | E56: MALPARTIDA GOMEZ,LINDA EVELIN | F56: ADMNE | G56: ADMINISTRACION DE EMPRESAS | H56: ADM2020 | I56: OK | J56: OK | K56: 1 | L56: OK | M56: OK | N56: 1 | O56: 2 | P56: 1 | Q56: 2 | R56: 4 | S56: 4 | T56: 4
A57: 3123 | B57: SISE | C57: PRGS | D57: 2017041687 | E57: ATANACIO SUDARIO,JHASMIN DANITZA | F57: SALUD | G57: ENFERMERIA TECNICA | H57: ENFTEC2020 | I57: OK | J57: OK | K57: OK | L57: OK | M57: OK | N57: OK | O57: 2 | P57: 4 | Q57: 3 | R57: 4 | S57: 4 | T57: 4
A58: 3123 | B58: SISE | C58: PRGS | D58: 2017041782 | E58: HILARIO SURCO,JONATHAN OSWALDO | F58: SWSIS | G58: DES DE SISTEMAS DE INFORMACION | H58: SOFT2020 | I58: 1 | J58: 1 | K58: 1 | L58: 2 | M58: 3 | N58: 4 | O58: 3 | P58: 4 | Q58: 3 | R58: 4 | S58: 4 | T58: 4
A59: 3123 | B59: SISE | C59: PRGS | D59: 2017041803 | E59: GUEVARA PANDO,VALERIA DINA | F59: ADMNE | G59: ADMINISTRACION DE EMPRESAS | H59: ADM2020 | I59: OK | J59: OK | K59: OK | L59: OK | M59: OK | N59: OK | O59: 3 | P59: 4 | Q59: 3 | R59: 4 | S59: 4 | T59: 4
A60: 3123 | B60: SISE | C60: PRGS | D60: 2017042275 | E60: TOMAS LAZARO,GEORGINA ALEXANDRA | F60: COMAU | G60: COMUNICACION AUDIOVISUAL | H60: COAU2020 | I60: OK | J60: OK | K60: 1 | L60: OK | M60: OK | N60: 1 | O60: 4 | P60: 3 | Q60: 4 | R60: 4 | S60: 5 | T60: 5
A61: 3123 | B61: SISE | C61: PRGS | D61: 2017042290 | E61: YUPANQUI FRANCO,KAREN CIELO | F61: CONTA | G61: CONTABILIDAD | H61: COFI2020 | I61: OK | J61: OK | K61: OK | L61: OK | M61: 4 | N61: OK | O61: 3 | P61: 4 | Q61: 3 | R61: 4 | S61: 4 | T61: 4
A62: 3123 | B62: SISE | C62: PRGS | D62: 2017043469 | E62: MONTENEGRO CURAY,EMILY SOLANCH | F62: ADMNE | G62: ADMINISTRACION DE EMPRESAS | H62: ADM2020 | I62: OK | J62: 1 | K62: 4 | L62: 3 | M62: 4 | N62: 4 | O62: 3 | P62: 4 | Q62: 3 | R62: 4 | S62: 4 | T62: 4
A63: 3123 | B63: SISE | C63: PRGS | D63: 2017044447 | E63: CHUQUIPÓMA VASQUEZ, FABIAN | F63: GASTR | G63: GASTRONOMIA | H63: GAST2022 | I63: OK | J63: OK | K63: OK | L63: OK | M63: OK | N63: 4 | O63: 6 | P63: 4
A64: 3123 | B64: SISE | C64: PRGS | D64: 2017045589 | E64: ROJAS CONTO,ALISSON MICHELL | F64: ADMNE | G64: ADMINISTRACION DE EMPRESAS | H64: ADM2020 | I64: 1 | J64: 5 | K64: 4 | L64: 4 | M64: 4 | N64: 4 | O64: 3 | P64: 4 | Q64: 3 | R64: 4 | S64: 4 | T64: 4
A65: 3123 | B65: SISE | C65: PRGS | D65: 2017047477 | E65: GARCIA GIMA,ANTHONY GERARDO | F65: MARKT | G65: MARKETING | H65: MKT2020 | I65: OK | J65: OK | K65: 4 | L65: OK | M65: 4 | N65: 4 | O65: 3 | P65: 4 | Q65: 3 | R65: 4 | S65: 4 | T65: 4
A66: 3123 | B66: SISE | C66: PRGS | D66: 2017047551 | E66: CCAICO CARHUAPOMA,LUZDY | F66: TECFA | G66: TECNICA EN FARMACIA | H66: TECNFM2020 | I66: OK | J66: OK | K66: OK | L66: 4 | M66: 4 | N66: 4 | O66: 4 | P66: 4 | Q66: 4 | R66: 5 | S66: 4 | T66: 5
A67: 3123 | B67: SISE | C67: PRGS | D67: 2017049480 | E67: MUÑOZ VILLANUEVA,ENZO FRANCHEZCOLLY | F67: DG | G67: DISEÑO GRAFICO PROFESIONAL | H67: DISGRA2020 | I67: 5 | J67: 6 | K67: 5 | L67: 4 | M67: 4 | N67: 4 | O67: 3 | P67: 4 | Q67: 3 | R67: 5 | S67: 4 | T67: 4
A68: 3123 | B68: SISE | C68: PRGS | D68: 2017049555 | E68: MEDINA PORTUGAL,STEFANO EDUARDO | F68: COMAU | G68: COMUNICACION AUDIOVISUAL | H68: COAU2020 | I68: 4 | J68: 3 | K68: 5 | L68: 4 | M68: 4 | N68: 4 | O68: 4 | P68: 4 | Q68: 4 | R68: 4 | S68: 5 | T68: 5
A69: 3123 | B69: SISE | C69: PRGS | D69: 2017051391 | E69: DEL CARPIO LOAYZA,ANNA FHERNANDA | F69: GASTR | G69: GASTRONOMIA | H69: GAST2020 | I69: OK | J69: OK | K69: OK | L69: OK | M69: OK | N69: OK | O69: OK | P69: 4
A70: 3123 | B70: SISE | C70: PRGS | D70: 2017052151 | E70: OJEDA ESTRADA,JOSE MIGUEL | F70: DG | G70: DISEÑO GRAFICO PROFESIONAL | H70: DISGRA2020 | I70: OK | J70: OK | K70: 5 | L70: 4 | M70: 4 | N70: 4 | O70: 3 | P70: 4 | Q70: 3 | R70: 5 | S70: 4 | T70: 4
A71: 3123 | B71: SISE | C71: PRGS | D71: 2017053213 | E71: CONDOR SANCHEZ,CLARISSA YAZMIN | F71: CONTA | G71: CONTABILIDAD | H71: COFI2020 | I71: OK | J71: OK | K71: OK | L71: OK | M71: OK | N71: OK | O71: 3 | P71: 4 | Q71: 3 | R71: 4 | S71: 4 | T71: 4
A72: 3123 | B72: SISE | C72: PRGS | D72: 2017053384 | E72: SILVA TRUJILLO,FRANCESCA ALEJANDRA | F72: COMAU | G72: COMUNICACION AUDIOVISUAL | H72: COAU2020 | I72: OK | J72: OK | K72: OK | L72: OK | M72: OK | N72: OK | O72: 4 | P72: 4 | Q72: 4 | R72: 4 | S72: 5 | T72: 5
A73: 3123 | B73: SISE | C73: PRGS | D73: 2017054467 | E73: HUARACA SILVA,KATHERINE | F73: CONTA | G73: CONTABILIDAD | H73: COFI2020 | I73: OK | J73: OK | K73: 4 | L73: 4 | M73: 4 | N73: 4 | O73: 3 | P73: 4 | Q73: 3 | R73: 4 | S73: 4 | T73: 4
A74: 3123 | B74: SISE | C74: PRGS | D74: 2017055702 | E74: MAMAMI GAMARRA,RAQUEL VICTORIA | F74: COMAU | G74: COMUNICACION AUDIOVISUAL | H74: COAU2020 | I74: OK | J74: OK | K74: OK | L74: OK | M74: OK | N74: OK | O74: 4 | P74: 4 | Q74: 4 | R74: 4 | S74: 5 | T74: 5
A75: 3123 | B75: SISE | C75: PRGS | D75: 2017056533 | E75: VELASQUEZ HANCCO,LILIAN | F75: ADMNE | G75: ADMINISTRACION DE EMPRESAS | H75: ADM2020 | I75: OK | J75: OK | K75: OK | L75: OK | M75: OK | N75: 1 | O75: 3 | P75: 4 | Q75: 3 | R75: 4 | S75: 4 | T75: 4
A76: 3123 | B76: SISE | C76: PRGS | D76: 2017056801 | E76: CAMERO VELIZ,EDISON LUIS | F76: ADMLO | G76: GESTIÓN LOGÍSTICA | H76: ADMLO2020 | I76: OK | J76: OK | K76: 4 | L76: 1 | M76: 3 | N76: 4 | O76: 3 | P76: 4 | Q76: 3 | R76: 4 | S76: 4 | T76: 4
A77: 3123 | B77: SISE | C77: PRGS | D77: 2017057252 | E77: CHICLLASTO CHOQUE,JESUS VALERIO | F77: ADMNE | G77: ADMINISTRACION DE EMPRESAS | H77: ADM2020 | I77: OK | J77: OK | K77: 4 | L77: OK | M77: 4 | N77: 4 | O77: 3 | P77: 4 | Q77: 3 | R77: 4 | S77: 4 | T77: 4
A78: 3123 | B78: SISE | C78: PRGS | D78: 2017059424 | E78: POMA CONISLLA,JHON GREGORIO | F78: ADMNE | G78: ADMINISTRACION DE EMPRESAS | H78: ADM2020 | I78: OK | J78: 5 | K78: 4 | L78: 4 | M78: 4 | N78: 4 | O78: 3 | P78: 4 | Q78: 3 | R78: 4 | S78: 4 | T78: 4
A79: 3123 | B79: SISE | C79: PRGS | D79: 2017059816 | E79: RODRIGUEZ ESPINOZA,GRISEL NURIA | F79: ADMBF | G79: ADM. BANCARIA Y FINANCIERA | H79: ABF2020 | I79: OK | J79: 4 | K79: 4 | L79: 4 | M79: 4 | N79: 4 | O79: 3 | P79: 4 | Q79: 3 | R79: 4 | S79: 4 | T79: 4
A80: 3123 | B80: SISE | C80: PRGS | D80: 2017060277 | E80: CUSI ESPINOZA,PEDRO ANTONIO | F80: FISIO | G80: FISIOTERAPIA Y REHABILITACION | H80: FISYRE2020 | I80: 5 | J80: 6 | K80: 5 | L80: 4 | M80: 4 | N80: 5 | O80: 4 | P80: 4 | Q80: 4 | R80: 5 | S80: 4 | T80: 4
A81: 3123 | B81: SISE | C81: PRGS | D81: 2017060600 | E81: VILCHEZ BARZOLA,YULISSA | F81: CONTA | G81: CONTABILIDAD | H81: COFI2020 | I81: OK | J81: OK | K81: 1 | L81: OK | M81: 1 | N81: OK | O81: 3 | P81: 4 | Q81: 3 | R81: 4 | S81: 4 | T81: 4
A82: 3123 | B82: SISE | C82: PRGS | D82: 2017061290 | E82: MURGA SERRATO,MARIO CESAR | F82: COMAU | G82: COMUNICACION AUDIOVISUAL | H82: COAU2020 | I82: OK | J82: OK | K82: OK | L82: 2 | M82: 4 | N82: 2 | O82: 4 | P82: 4 | Q82: 4 | R82: 4 | S82: 5 | T82: 5
A83: 3123 | B83: SISE | C83: PRGS | D83: 2017062963 | E83: CHAVEZ ARIAS,SHIRLEY PAMELA | F83: ADMNE | G83: ADMINISTRACION DE EMPRESAS | H83: ADM2020 | I83: OK | J83: OK | K83: OK | L83: OK | M83: OK | N83: 1 | O83: 3 | P83: 4 | Q83: 3 | R83: 4 | S83: 4 | T83: 4
A84: 3123 | B84: SISE | C84: PRGS | D84: 2017063088 | E84: PEREIRA LOPEZ,ROGER JUNIOR | F84: SALUD | G84: ENFERMERIA TECNICA | H84: ENFTEC2020 | I84: OK | J84: OK | K84: OK | L84: OK | M84: 4 | N84: 3 | O84: 4 | P84: 4 | Q84: 3 | R84: 4 | S84: 4 | T84: 4
A85: 3123 | B85: SISE | C85: PRGS | D85: 2017065074 | E85: AGUIRRE CAMPOS,SILVIA | F85: SALUD | G85: ENFERMERIA TECNICA | H85: ENFTEC2020 | I85: OK | J85: OK | K85: OK | L85: 4 | M85: 4 | N85: 5 | O85: 4 | P85: 4 | Q85: 3 | R85: 4 | S85: 4 | T85: 4
A86: 3123 | B86: SISE | C86: PRGS | D86: 2017066514 | E86: PAICO VALVERDE,JUNIOR | F86: SWSIS | G86: DES DE SISTEMAS DE INFORMACION | H86: SOFT2020 | I86: OK | J86: OK | K86: OK | L86: OK | M86: OK | N86: 4 | O86: 3 | P86: 4 | Q86: 3 | R86: 4 | S86: 4 | T86: 4
A87: 3123 | B87: SISE | C87: PRGS | D87: 2017066669 | E87: MEZA FLORES,JESUS ARTURO | F87: PA | G87: PERIODISMO AUDIOVISUAL | H87: PEAU2020 | I87: OK | J87: OK | K87: OK | L87: OK | M87: OK | N87: OK | O87: 4 | P87: 1 | Q87: 3 | R87: 5 | S87: 5 | T87: 5
A88: 3123 | B88: SISE | C88: PRGS | D88: 2017066748 | E88: CHAMBI ROJAS,LUIS ARMANDO | F88: ADMNE | G88: ADMINISTRACION DE EMPRESAS | H88: ADM2020 | I88: OK | J88: OK | K88: 4 | L88: 4 | M88: 4 | N88: 4 | O88: 3 | P88: 4 | Q88: 3 | R88: 4 | S88: 4 | T88: 4
A89: 3123 | B89: SISE | C89: PRGS | D89: 2017067972 | E89: RAURAU HUAMANI,ROSA FERNANDA | F89: CONTA | G89: CONTABILIDAD | H89: COFI2020 | I89: OK | J89: OK | K89: 4 | L89: 4 | M89: 4 | N89: 4 | O89: 3 | P89: 4 | Q89: 3 | R89: 4 | S89: 4 | T89: 4
A90: 3123 | B90: SISE | C90: PRGS | D90: 2017069832 | E90: FLORES ORTIZ,KENYI | F90: ADMNE | G90: ADMINISTRACION DE EMPRESAS | H90: ADM2020 | I90: OK | J90: OK | K90: 1 | L90: OK | M90: OK | N90: OK | O90: 3 | P90: 4 | Q90: 3 | R90: 4 | S90: 4 | T90: 4
A91: 3123 | B91: SISE | C91: PRGS | D91: 2017070223 | E91: CONTRERAS ROSAS,ALISON PAOLA | F91: ADMBF | G91: ADM. BANCARIA Y FINANCIERA | H91: ABF2020 | I91: OK | J91: OK | K91: 4 | L91: OK | M91: 4 | N91: 4 | O91: 3 | P91: 4 | Q91: 3 | R91: 4 | S91: 4 | T91: 4
A92: 3123 | B92: SISE | C92: PRGS | D92: 2017070866 | E92: OLIVERA CALDERON,JOSUE ANDRES | F92: DG | G92: DISEÑO GRAFICO PROFESIONAL | H92: DISGRA2020 | I92: OK | J92: OK | K92: 1 | L92: OK | M92: OK | N92: OK | O92: 3 | P92: 4 | Q92: 3 | R92: 5 | S92: 4 | T92: 4
A93: 3123 | B93: SISE | C93: PRGS | D93: 2017071354 | E93: HUANCA VALERIO,EVA MAGDALENA | F93: FISIO | G93: FISIOTERAPIA Y REHABILITACION | H93: FISYRE2020 | I93: OK | J93: OK | K93: 5 | L93: 4 | M93: 4 | N93: 5 | O93: 4 | P93: 4 | Q93: 4 | R93: 5 | S93: 4 | T93: 4
A94: 3123 | B94: SISE | C94: PRGS | D94: 2017073894 | E94: POMA GARAY,YORDY YACK | F94: ADMNI | G94: ADM DE NEGOCIOS INTERN | H94: NNII2020 | I94: OK | J94: OK | K94: OK | L94: OK | M94: 4 | N94: OK | O94: 3 | P94: 4 | Q94: 3 | R94: 4 | S94: 4 | T94: 4
A95: 3123 | B95: SISE | C95: PRGS | D95: 2017074743 | E95: PAIMA QUESQUEN,ANGEL DANIEL | F95: MARKT | G95: MARKETING | H95: MKT2020 | I95: OK | J95: OK | K95: 1 | L95: OK | M95: 4 | N95: 4 | O95: 3 | P95: 4 | Q95: 3 | R95: 4 | S95: 4 | T95: 4
A96: 3123 | B96: SISE | C96: PRGS | D96: 2017074905 | E96: MORALES CABRERA,FABIOLA STEFFANY | F96: TECFA | G96: TECNICA EN FARMACIA | H96: TECNFM2020 | I96: OK | J96: OK | K96: 5 | L96: 4 | M96: 4 | N96: 4 | O96: 4 | P96: 4 | Q96: 4 | R96: 5 | S96: 4 | T96: 5
A97: 3123 | B97: SISE | C97: PRGS | D97: 2017076566 | E97: CORDOVA APONTE,ANA VICTORIA | F97: ADMBF | G97: ADM. BANCARIA Y FINANCIERA | H97: ABF2020 | I97: 4 | J97: OK | K97: 4 | L97: 4 | M97: 4 | N97: 4 | O97: 3 | P97: 4 | Q97: 3 | R97: 4 | S97: 4 | T97: 4
A98: 3123 | B98: SISE | C98: PRGS | D98: 2017076629 | E98: GARCIA ARMENGOD,MONICA KARLA | F98: MARKT | G98: MARKETING | H98: MKT2020 | I98: 4 | J98: 4 | K98: 4 | L98: 4 | M98: 4 | N98: 4 | O98: 3 | P98: 4 | Q98: 3 | R98: 4 | S98: 4 | T98: 4
A99: 3123 | B99: SISE | C99: PRGS | D99: 2017076820 | E99: DEVOTTO VARGAS,EZZIO GIUSEPPE | F99: REDES | G99: ADM DE REDES Y COMUNICACIONES | H99: RED2020 | I99: OK | J99: OK | K99: 4 | L99: 4 | M99: 3 | N99: 4 | O99: 3 | P99: 4 | Q99: 3 | R99: 4 | S99: 4 | T99: 4
A100: 3123 | B100: SISE | C100: PRGS | D100: 2017077181 | E100: ARIAS MOLINA,JOSE ALFREDO | F100: ADMNE | G100: ADMINISTRACION DE EMPRESAS | H100: ADM2020 | I100: OK | J100: OK | K100: OK | L100: OK | M100: 4 | N100: 4 | O100: 3 | P100: 4 | Q100: 3 | R100: 4 | S100: 4 | T100: 4
...

Sheet Hoja3
A1: Sección | B1: Nº Clase | C1: Campus | D1: Nombre Curso | E1: Turno | F1: ID Curso
A2: 1C | B2: 2196 | C2: =VLOOKUP(B2,sheet2!$A$1:$K$1775,2,FALSE) -> #N/A | D2: =VLOOKUP(B2,sheet2!$A$1:$K$1775,5,FALSE) -> #N/A | E2: =VLOOKUP(B2,sheet2!$A$1:$K$1775,11,FALSE) -> #N/A | F2: =VLOOKUP(B2,sheet2!$A$1:$K$1775,4,FALSE) -> #N/A
A3: 1C | B3: 2519 | C3: =VLOOKUP(B3,sheet2!$A$1:$K$1775,2,FALSE) -> SURCO | D3: =VLOOKUP(B3,sheet2!$A$1:$K$1775,5,FALSE) -> CONTABILIDAD BÁSICA | E3: =VLOOKUP(B3,sheet2!$A$1:$K$1775,11,FALSE) -> N | F3: =VLOOKUP(B3,sheet2!$A$1:$K$1775,4,FALSE) -> 668902
A4: 1C | B4: 2503 | C4: =VLOOKUP(B4,sheet2!$A$1:$K$1775,2,FALSE) -> SURCO | D4: =VLOOKUP(B4,sheet2!$A$1:$K$1775,5,FALSE) -> INFOGRAFÍA | E4: =VLOOKUP(B4,sheet2!$A$1:$K$1775,11,FALSE) -> N | F4: =VLOOKUP(B4,sheet2!$A$1:$K$1775,4,FALSE) -> 668848
A5: 1C | B5: 2487 | C5: =VLOOKUP(B5,sheet2!$A$1:$K$1775,2,FALSE) -> SURCO | D5: =VLOOKUP(B5,sheet2!$A$1:$K$1775,5,FALSE) -> EDIC. DIGI.(PREMIERE/AUDITION) | E5: =VLOOKUP(B5,sheet2!$A$1:$K$1775,11,FALSE) -> M | F5: =VLOOKUP(B5,sheet2!$A$1:$K$1775,4,FALSE) -> 668837
A6: 1C1 | B6: 2197 | C6: =VLOOKUP(B6,sheet2!$A$1:$K$1775,2,FALSE) -> #N/A | D6: =VLOOKUP(B6,sheet2!$A$1:$K$1775,5,FALSE) -> #N/A | E6: =VLOOKUP(B6,sheet2!$A$1:$K$1775,11,FALSE) -> #N/A | F6: =VLOOKUP(B6,sheet2!$A$1:$K$1775,4,FALSE) -> #N/A
A7: 1C1 | B7: 2520 | C7: =VLOOKUP(B7,sheet2!$A$1:$K$1775,2,FALSE) -> SURCO | D7: =VLOOKUP(B7,sheet2!$A$1:$K$1775,5,FALSE) -> CONTABILIDAD INTERMEDIA | E7: =VLOOKUP(B7,sheet2!$A$1:$K$1775,11,FALSE) -> M | F7: =VLOOKUP(B7,sheet2!$A$1:$K$1775,4,FALSE) -> 668905
A8: 1C1 | B8: 2504 | C8: =VLOOKUP(B8,sheet2!$A$1:$K$1775,2,FALSE) -> SURCO | D8: =VLOOKUP(B8,sheet2!$A$1:$K$1775,5,FALSE) -> REDACCIÓN DE GUION | E8: =VLOOKUP(B8,sheet2!$A$1:$K$1775,11,FALSE) -> M | F8: =VLOOKUP(B8,sheet2!$A$1:$K$1775,4,FALSE) -> 668864
A9: 1C1 | B9: 2488 | C9: =VLOOKUP(B9,sheet2!$A$1:$K$1775,2,FALSE) -> SURCO | D9: =VLOOKUP(B9,sheet2!$A$1:$K$1775,5,FALSE) -> EDIC. DIGI.(PREMIERE/AUDITION) | E9: =VLOOKUP(B9,sheet2!$A$1:$K$1775,11,FALSE) -> N | F9: =VLOOKUP(B9,sheet2!$A$1:$K$1775,4,FALSE) -> 668837
A10: 1C2 | B10: 2521 | C10: =VLOOKUP(B10,sheet2!$A$1:$K$1775,2,FALSE) -> SURCO | D10: =VLOOKUP(B10,sheet2!$A$1:$K$1775,5,FALSE) -> CONTABILIDAD INTERMEDIA | E10: =VLOOKUP(B10,sheet2!$A$1:$K$1775,11,FALSE) -> N | F10: =VLOOKUP(B10,sheet2!$A$1:$K$1775,4,FALSE) -> 668905
A11: 1C2 | B11: 2489 | C11: =VLOOKUP(B11,sheet2!$A$1:$K$1775,2,FALSE) -> #N/A | D11: =VLOOKUP(B11,sheet2!$A$1:$K$1775,5,FALSE) -> #N/A | E11: =VLOOKUP(B11,sheet2!$A$1:$K$1775,11,FALSE) -> #N/A | F11: =VLOOKUP(B11,sheet2!$A$1:$K$1775,4,FALSE) -> #N/A
A12: 1C2 | B12: 2198 | C12: =VLOOKUP(B12,sheet2!$A$1:$K$1775,2,FALSE) -> #N/A | D12: =VLOOKUP(B12,sheet2!$A$1:$K$1775,5,FALSE) -> #N/A | E12: =VLOOKUP(B12,sheet2!$A$1:$K$1775,11,FALSE) -> #N/A | F12: =VLOOKUP(B12,sheet2!$A$1:$K$1775,4,FALSE) -> #N/A
A13: 1C2 | B13: 2505 | C13: =VLOOKUP(B13,sheet2!$A$1:$K$1775,2,FALSE) -> SURCO | D13: =VLOOKUP(B13,sheet2!$A$1:$K$1775,5,FALSE) -> REDACCIÓN DE GUION | E13: =VLOOKUP(B13,sheet2!$A$1:$K$1775,11,FALSE) -> M | F13: =VLOOKUP(B13,sheet2!$A$1:$K$1775,4,FALSE) -> 668864
... A65: 1C9 | B65: 2534 | C65: =VLOOKUP(B65,sheet2!$A$1:$K$1775,2,FALSE) -> SURCO | D65: =VLOOKUP(B65,sheet2!$A$1:$K$1775,5,FALSE) -> T. DE COM. EF. Y RES. DE CONF. | E65: =VLOOKUP(B65,sheet2!$A$1:$K$1775,11,FALSE) -> M | F65: =VLOOKUP(B65,sheet2!$A$1:$K$1775,4,FALSE) -> 668952
C66: =VLOOKUP(B66,sheet2!$A$1:$K$1775,2,FALSE) -> #N/A | D66: =VLOOKUP(B66,sheet2!$A$1:$K$1775,5,FALSE) -> #N/A | E66: =VLOOKUP(B66,sheet2!$A$1:$K$1775,11,FALSE) -> #N/A | F66: =VLOOKUP(B66,sheet2!$A$1:$K$1775,4,FALSE) -> #N/A
A67: 1D | B67: 2580 | C67: =VLOOKUP(B67,sheet2!$A$1:$K$1775,2,FALSE) -> #N/A | D67: =VLOOKUP(B67,sheet2!$A$1:$K$1775,5,FALSE) -> #N/A | E67: =VLOOKUP(B67,sheet2!$A$1:$K$1775,11,FALSE) -> #N/A | F67: =VLOOKUP(B67,sheet2!$A$1:$K$1775,4,FALSE) -> #N/A
A68: 1D | B68: 2275 | C68: =VLOOKUP(B68,sheet2!$A$1:$K$1775,2,FALSE) -> SURCO | D68: =VLOOKUP(B68,sheet2!$A$1:$K$1775,5,FALSE) -> TRATADOS DE COME INTERNACIONAL | E68: =VLOOKUP(B68,sheet2!$A$1:$K$1775,11,FALSE) -> N | F68: =VLOOKUP(B68,sheet2!$A$1:$K$1775,4,FALSE) -> 9083
A69: 1D | B69: 2256 | C69: =VLOOKUP(B69,sheet2!$A$1:$K$1775,2,FALSE) -> SURCO | D69: =VLOOKUP(B69,sheet2!$A$1:$K$1775,5,FALSE) -> EXPE FORMATIVAS ESPECIALIZADAS | E69: =VLOOKUP(B69,sheet2!$A$1:$K$1775,11,FALSE) -> N | F69: =VLOOKUP(B69,sheet2!$A$1:$K$1775,4,FALSE) -> 9047
A70: 1D1 | B70: 2276 | C70: =VLOOKUP(B70,sheet2!$A$1:$K$1775,2,FALSE) -> SURCO | D70: =VLOOKUP(B70,sheet2!$A$1:$K$1775,5,FALSE) -> PRECI Y COTIZA INTERNACIONALES | E70: =VLOOKUP(B70,sheet2!$A$1:$K$1775,11,FALSE) -> N | F70: =VLOOKUP(B70,sheet2!$A$1:$K$1775,4,FALSE) -> 9100
A71: 1D1 | B71: 2581 | C71: =VLOOKUP(B71,sheet2!$A$1:$K$1775,2,FALSE) -> VENTN | D71: =VLOOKUP(B71,sheet2!$A$1:$K$1775,5,FALSE) -> T. DE INFORM. PARA LA EMPLEAB. | E71: =VLOOKUP(B71,sheet2!$A$1:$K$1775,11,FALSE) -> M | F71: =VLOOKUP(B71,sheet2!$A$1:$K$1775,4,FALSE) -> 668516
A72: 1D1 | B72: 2257 | C72: =VLOOKUP(B72,sheet2!$A$1:$K$1775,2,FALSE) -> SURCO | D72: =VLOOKUP(B72,sheet2!$A$1:$K$1775,5,FALSE) -> GESTIÓN DE CADE DE SUMINISTROS | E72: =VLOOKUP(B72,sheet2!$A$1:$K$1775,11,FALSE) -> N | F72: =VLOOKUP(B72,sheet2!$A$1:$K$1775,4,FALSE) -> 9059
A73: 1D11 | B73: 2277 | C73: =VLOOKUP(B73,sheet2!$A$1:$K$1775,2,FALSE) -> SURCO | D73: =VLOOKUP(B73,sheet2!$A$1:$K$1775,5,FALSE) -> INGLÉS PARA LOS NEGOCIOS III | E73: =VLOOKUP(B73,sheet2!$A$1:$K$1775,11,FALSE) -> N | F73: =VLOOKUP(B73,sheet2!$A$1:$K$1775,4,FALSE) -> 9101
A74: 1D11 | B74: 2582 | C74: =VLOOKUP(B74,sheet2!$A$1:$K$1775,2,FALSE) -> VENTN | D74: =VLOOKUP(B74,sheet2!$A$1:$K$1775,5,FALSE) -> T. DE INFORM. PARA LA EMPLEAB. | E74: =VLOOKUP(B74,sheet2!$A$1:$K$1775,11,FALSE) -> N | F74: =VLOOKUP(B74,sheet2!$A$1:$K$1775,4,FALSE) -> 668516
A75: 1D11 | B75: 2258 | C75: =VLOOKUP(B75,sheet2!$A$1:$K$1775,2,FALSE) -> SURCO | D75: =VLOOKUP(B75,sheet2!$A$1:$K$1775,5,FALSE) -> GEST DE COMER INTERNACIONAL | E75: =VLOOKUP(B75,sheet2!$A$1:$K$1775,11,FALSE) -> N | F75: =VLOOKUP(B75,sheet2!$A$1:$K$1775,4,FALSE) -> 9060
A76: 1D6 | B76: 2265 | C76: =VLOOKUP(B76,sheet2!$A$1:$K$1775,2,FALSE) -> SURCO | D76: =VLOOKUP(B76,sheet2!$A$1:$K$1775,5,FALSE) -> ESTRATEGIA DE COMUNICACIÓN | E76: =VLOOKUP(B76,sheet2!$A$1:$K$1775,11,FALSE) -> M | F76: =VLOOKUP(B76,sheet2!$A$1:$K$1775,4,FALSE) -> 9072
A77: 1D6 | B77: 2589 | C77: =VLOOKUP(B77,sheet2!$A$1:$K$1775,2,FALSE) -> VENTN | D77: =VLOOKUP(B77,sheet2!$A$1:$K$1775,5,FALSE) -> T. DE MET. ÁGIL. PARA LA INNO. | E77: =VLOOKUP(B77,sheet2!$A$1:$K$1775,11,FALSE) -> M | F77: =VLOOKUP(B77,sheet2!$A$1:$K$1775,4,FALSE) -> 668528
A78: 1D6 | B78: 2284 | C78: =VLOOKUP(B78,sheet2!$A$1:$K$1775,2,FALSE) -> SURCO | D78: =VLOOKUP(B78,sheet2!$A$1:$K$1775,5,FALSE) -> METOD. PARA UN APREND. EFIC. | E78: =VLOOKUP(B78,sheet2!$A$1:$K$1775,11,FALSE) -> N | F78: =VLOOKUP(B78,sheet2!$A$1:$K$1775,4,FALSE) -> 668513
... A96: 1D5 | B96: 2283 | C96: =VLOOKUP(B96,sheet2!$A$1:$K$1775,2,FALSE) -> SURCO | D96: =VLOOKUP(B96,sheet2!$A$1:$K$1775,5,FALSE) -> METOD. PARA UN APREND. EFIC. | E96: =VLOOKUP(B96,sheet2!$A$1:$K$1775,11,FALSE) -> M | F96: =VLOOKUP(B96,sheet2!$A$1:$K$1775,4,FALSE) -> 668513
C97: =VLOOKUP(B97,sheet2!$A$1:$K$1775,2,FALSE) -> #N/A | D97: =VLOOKUP(B97,sheet2!$A$1:$K$1775,5,FALSE) -> #N/A | E97: =VLOOKUP(B97,sheet2!$A$1:$K$1775,11,FALSE) -> #N/A | F97: =VLOOKUP(B97,sheet2!$A$1:$K$1775,4,FALSE) -> #N/A
A98: 1U1 | B98: 2624 | C98: =VLOOKUP(B98,sheet2!$A$1:$K$1775,2,FALSE) -> VENTN | D98: =VLOOKUP(B98,sheet2!$A$1:$K$1775,5,FALSE) -> MATEMÁTICA APLICADA EN SALUD | E98: =VLOOKUP(B98,sheet2!$A$1:$K$1775,11,FALSE) -> M | F98: =VLOOKUP(B98,sheet2!$A$1:$K$1775,4,FALSE) -> 668588
A99: 1U1 | B99: 2543 | C99: =VLOOKUP(B99,sheet2!$A$1:$K$1775,2,FALSE) -> SURCO | D99: =VLOOKUP(B99,sheet2!$A$1:$K$1775,5,FALSE) -> DESARROLLO DE ENTORNOS WEB | E99: =VLOOKUP(B99,sheet2!$A$1:$K$1775,11,FALSE) -> N | F99: =VLOOKUP(B99,sheet2!$A$1:$K$1775,4,FALSE) -> 668953
A100: 1U1 | B100: 2535 | C100: =VLOOKUP(B100,sheet2!$A$1:$K$1775,2,FALSE) -> SURCO | D100: =VLOOKUP(B100,sheet2!$A$1:$K$1775,5,FALSE) -> T. DE COM. EF. Y RES. DE CONF. | E100: =VLOOKUP(B100,sheet2!$A$1:$K$1775,11,FALSE) -> M | F100: =VLOOKUP(B100,sheet2!$A$1:$K$1775,4,FALSE) -> 668952
A101: 1U2 | B101: 2544 | C101: =VLOOKUP(B101,sheet2!$A$1:$K$1775,2,FALSE) -> SURCO | D101: =VLOOKUP(B101,sheet2!$A$1:$K$1775,5,FALSE) -> SISTEMAS OPERATIVOS ABIERTOS | E101: =VLOOKUP(B101,sheet2!$A$1:$K$1775,11,FALSE) -> M | F101: =VLOOKUP(B101,sheet2!$A$1:$K$1775,4,FALSE) -> 668955
A102: 1U2 | B102: 2625 | C102: =VLOOKUP(B102,sheet2!$A$1:$K$1775,2,FALSE) -> VENTN | D102: =VLOOKUP(B102,sheet2!$A$1:$K$1775,5,FALSE) -> MATEMÁTICA APLICADA EN SALUD | E102: =VLOOKUP(B102,sheet2!$A$1:$K$1775,11,FALSE) -> N | F102: =VLOOKUP(B102,sheet2!$A$1:$K$1775,4,FALSE) -> 668588
A103: 1U2 | B103: 2536 | C103: =VLOOKUP(B103,sheet2!$A$1:$K$1775,2,FALSE) -> SURCO | D103: =VLOOKUP(B103,sheet2!$A$1:$K$1775,5,FALSE) -> T. DE COM. EF. Y RES. DE CONF. | E103: =VLOOKUP(B103,sheet2!$A$1:$K$1775,11,FALSE) -> M | F103: =VLOOKUP(B103,sheet2!$A$1:$K$1775,4,FALSE) -> 668952
A104: 1U3 | B104: 2626 | C104: =VLOOKUP(B104,sheet2!$A$1:$K$1775,2,FALSE) -> VENTN | D104: =VLOOKUP(B104,sheet2!$A$1:$K$1775,5,FALSE) -> CUID. DE SALUD EN PAC. HOSPIT. | E104: =VLOOKUP(B104,sheet2!$A$1:$K$1775,11,FALSE) -> M | F104: =VLOOKUP(B104,sheet2!$A$1:$K$1775,4,FALSE) -> 668593
A105: 1U3 | B105: 2545 | C105: =VLOOKUP(B105,sheet2!$A$1:$K$1775,2,FALSE) -> SURCO | D105: =VLOOKUP(B105,sheet2!$A$1:$K$1775,5,FALSE) -> SISTEMAS OPERATIVOS ABIERTOS | E105: =VLOOKUP(B105,sheet2!$A$1:$K$1775,11,FALSE) -> N | F105: =VLOOKUP(B105,sheet2!$A$1:$K$1775,4,FALSE) -> 668955
A106: 1U3 | B106: 2537 | C106: =VLOOKUP(B106,sheet2!$A$1:$K$1775,2,FALSE) -> SURCO | D106: =VLOOKUP(B106,sheet2!$A$1:$K$1775,5,FALSE) -> T. DE COM. EF. Y RES. DE CONF. | E106: =VLOOKUP(B106,sheet2!$A$1:$K$1775,11,FALSE) -> N | F106: =VLOOKUP(B106,sheet2!$A$1:$K$1775,4,FALSE) -> 668952
A107: 1U4 | B107: 2546 | C107: =VLOOKUP(B107,sheet2!$A$1:$K$1775,2,FALSE) -> SURCO | D107: =VLOOKUP(B107,sheet2!$A$1:$K$1775,5,FALSE) -> TEO. E HIS. DEL ARTE Y EL DIS. | E107: =VLOOKUP(B107,sheet2!$A$1:$K$1775,11,FALSE) -> N | F107: =VLOOKUP(B107,sheet2!$A$1:$K$1775,4,FALSE) -> 668991
A108: 1U4 | B108: 2538 | C108: =VLOOKUP(B108,sheet2!$A$1:$K$1775,2,FALSE) -> SURCO | D108: =VLOOKUP(B108,sheet2!$A$1:$K$1775,5,FALSE) -> T. DE COM. EF. Y RES. DE CONF. | E108: =VLOOKUP(B108,sheet2!$A$1:$K$1775,11,FALSE) -> N | F108: =VLOOKUP(B108,sheet2!$A$1:$K$1775,4,FALSE) -> 668952
A109: 1U4 | B109: 2727 | C109: =VLOOKUP(B109,sheet2!$A$1:$K$1775,2,FALSE) -> VILLA | D109: =VLOOKUP(B109,sheet2!$A$1:$K$1775,5,FALSE) -> FUNDAMENTOS DE MARKETING | E109: =VLOOKUP(B109,sheet2!$A$1:$K$1775,11,FALSE) -> N | F109: =VLOOKUP(B109,sheet2!$A$1:$K$1775,4,FALSE) -> 668705
... A121: 1X1 | B121: 2550 | C121: =VLOOKUP(B121,sheet2!$A$1:$K$1775,2,FALSE) -> SURCO | D121: =VLOOKUP(B121,sheet2!$A$1:$K$1775,5,FALSE) -> DISEÑO DIGITAL 2D (AUTOCAD) | E121: =VLOOKUP(B121,sheet2!$A$1:$K$1775,11,FALSE) -> M | F121: =VLOOKUP(B121,sheet2!$A$1:$K$1775,4,FALSE) -> 668996
C122: =VLOOKUP(B122,sheet2!$A$1:$K$1775,2,FALSE) -> #N/A | D122: =VLOOKUP(B122,sheet2!$A$1:$K$1775,5,FALSE) -> #N/A | E122: =VLOOKUP(B122,sheet2!$A$1:$K$1775,11,FALSE) -> #N/A | F122: =VLOOKUP(B122,sheet2!$A$1:$K$1775,4,FALSE) -> #N/A
A123: 1V1 | B123: 2285 | C123: =VLOOKUP(B123,sheet2!$A$1:$K$1775,2,FALSE) -> SURCO | D123: =VLOOKUP(B123,sheet2!$A$1:$K$1775,5,FALSE) -> METOD. PARA UN APREND. EFIC. | E123: =VLOOKUP(B123,sheet2!$A$1:$K$1775,11,FALSE) -> N | F123: =VLOOKUP(B123,sheet2!$A$1:$K$1775,4,FALSE) -> 668513
A124: 1V1 | B124: 2266 | C124: =VLOOKUP(B124,sheet2!$A$1:$K$1775,2,FALSE) -> SURCO | D124: =VLOOKUP(B124,sheet2!$A$1:$K$1775,5,FALSE) -> ESTRATEGIA DE COMUNICACIÓN | E124: =VLOOKUP(B124,sheet2!$A$1:$K$1775,11,FALSE) -> N | F124: =VLOOKUP(B124,sheet2!$A$1:$K$1775,4,FALSE) -> 9072
A125: 1V1 | B125: 2631 | C125: =VLOOKUP(B125,sheet2!$A$1:$K$1775,2,FALSE) -> VENTN | D125: =VLOOKUP(B125,sheet2!$A$1:$K$1775,5,FALSE) -> ADMINISTRACIÓN GENERAL | E125: =VLOOKUP(B125,sheet2!$A$1:$K$1775,11,FALSE) -> N | F125: =VLOOKUP(B125,sheet2!$A$1:$K$1775,4,FALSE) -> 668686
A126: 1V2 | B126: 2286 | C126: =VLOOKUP(B126,sheet2!$A$1:$K$1775,2,FALSE) -> #N/A | D126: =VLOOKUP(B126,sheet2!$A$1:$K$1775,5,FALSE) -> #N/A | E126: =VLOOKUP(B126,sheet2!$A$1:$K$1775,11,FALSE) -> #N/A | F126: =VLOOKUP(B126,sheet2!$A$1:$K$1775,4,FALSE) -> #N/A
A127: 1V2 | B127: 2267 | C127: =VLOOKUP(B127,sheet2!$A$1:$K$1775,2,FALSE) -> SURCO | D127: =VLOOKUP(B127,sheet2!$A$1:$K$1775,5,FALSE) -> ESTRATEGIAS DE MKT DIGITAL | E127: =VLOOKUP(B127,sheet2!$A$1:$K$1775,11,FALSE) -> M | F127: =VLOOKUP(B127,sheet2!$A$1:$K$1775,4,FALSE) -> 9073
A128: 1V2 | B128: 2632 | C128: =VLOOKUP(B128,sheet2!$A$1:$K$1775,2,FALSE) -> VENTN | D128: =VLOOKUP(B128,sheet2!$A$1:$K$1775,5,FALSE) -> ADMINISTRACIÓN GENERAL | E128: =VLOOKUP(B128,sheet2!$A$1:$K$1775,11,FALSE) -> N | F128: =VLOOKUP(B128,sheet2!$A$1:$K$1775,4,FALSE) -> 668686
A129: 1V3 | B129: 2633 | C129: =VLOOKUP(B129,sheet2!$A$1:$K$1775,2,FALSE) -> VENTN | D129: =VLOOKUP(B129,sheet2!$A$1:$K$1775,5,FALSE) -> MATEMÁTICA COMERCIAL | E129: =VLOOKUP(B129,sheet2!$A$1:$K$1775,11,FALSE) -> M | F129: =VLOOKUP(B129,sheet2!$A$1:$K$1775,4,FALSE) -> 668692
A130: 1V3 | B130: 2287 | C130: =VLOOKUP(B130,sheet2!$A$1:$K$1775,2,FALSE) -> SURCO | D130: =VLOOKUP(B130,sheet2!$A$1:$K$1775,5,FALSE) -> METOD. PARA UN APREND. EFIC. | E130: =VLOOKUP(B130,sheet2!$A$1:$K$1775,11,FALSE) -> N | F130: =VLOOKUP(B130,sheet2!$A$1:$K$1775,4,FALSE) -> 668513
A131: 1V3 | B131: 2268 | C131: =VLOOKUP(B131,sheet2!$A$1:$K$1775,2,FALSE) -> SURCO | D131: =VLOOKUP(B131,sheet2!$A$1:$K$1775,5,FALSE) -> ESTRATEGIAS DE MKT DIGITAL | E131: =VLOOKUP(B131,sheet2!$A$1:$K$1775,11,FALSE) -> N | F131: =VLOOKUP(B131,sheet2!$A$1:$K$1775,4,FALSE) -> 9073
A132: 1V4 | B132: 2626 | C132: =VLOOKUP(B132,sheet2!$A$1:$K$1775,2,FALSE) -> VENTN | D132: =VLOOKUP(B132,sheet2!$A$1:$K$1775,5,FALSE) -> CUID. DE SALUD EN PAC. HOSPIT. | E132: =VLOOKUP(B132,sheet2!$A$1:$K$1775,11,FALSE) -> M | F132: =VLOOKUP(B132,sheet2!$A$1:$K$1775,4,FALSE) -> 668593
A133: 1V4 | B133: 2288 | C133: =VLOOKUP(B133,sheet2!$A$1:$K$1775,2,FALSE) -> SURCO | D133: =VLOOKUP(B133,sheet2!$A$1:$K$1775,5,FALSE) -> METOD. PARA UN APREND. EFIC. | E133: =VLOOKUP(B133,sheet2!$A$1:$K$1775,11,FALSE) -> N | F133: =VLOOKUP(B133,sheet2!$A$1:$K$1775,4,FALSE) -> 668513
A134: 1V4 | B134: 2269 | C134: =VLOOKUP(B134,sheet2!$A$1:$K$1775,2,FALSE) -> SURCO | D134: =VLOOKUP(B134,sheet2!$A$1:$K$1775,5,FALSE) -> MARKETING DE SERVICIOS | E134: =VLOOKUP(B134,sheet2!$A$1:$K$1775,11,FALSE) -> N | F134: =VLOOKUP(B134,sheet2!$A$1:$K$1775,4,FALSE) -> 9074
... A149: 1W1 | B149: 2293 | C149: =VLOOKUP(B149,sheet2!$A$1:$K$1775,2,FALSE) -> #N/A | D149: =VLOOKUP(B149,sheet2!$A$1:$K$1775,5,FALSE) -> #N/A | E149: =VLOOKUP(B149,sheet2!$A$1:$K$1775,11,FALSE) -> #N/A | F149: =VLOOKUP(B149,sheet2!$A$1:$K$1775,4,FALSE) -> #N/A
C150: =VLOOKUP(B150,sheet2!$A$1:$K$1775,2,FALSE) -> #N/A | D150: =VLOOKUP(B150,sheet2!$A$1:$K$1775,5,FALSE) -> #N/A | E150: =VLOOKUP(B150,sheet2!$A$1:$K$1775,11,FALSE) -> #N/A | F150: =VLOOKUP(B150,sheet2!$A$1:$K$1775,4,FALSE) -> #N/A
A151: 1G | B151: 2412 | C151: =VLOOKUP(B151,sheet2!$A$1:$K$1775,2,FALSE) -> SURCO | D151: =VLOOKUP(B151,sheet2!$A$1:$K$1775,5,FALSE) -> PATRONAJE DIGITAL - AUDACES | E151: =VLOOKUP(B151,sheet2!$A$1:$K$1775,11,FALSE) -> M | F151: =VLOOKUP(B151,sheet2!$A$1:$K$1775,4,FALSE) -> 668668
A152: 1G | B152: 2369 | C152: =VLOOKUP(B152,sheet2!$A$1:$K$1775,2,FALSE) -> SURCO | D152: =VLOOKUP(B152,sheet2!$A$1:$K$1775,5,FALSE) -> TÉC DE MOVIM PARA PACIEN POSTR | E152: =VLOOKUP(B152,sheet2!$A$1:$K$1775,11,FALSE) -> N | F152: =VLOOKUP(B152,sheet2!$A$1:$K$1775,4,FALSE) -> 668581
A153: 1G | B153: 2225 | C153: =VLOOKUP(B153,sheet2!$A$1:$K$1775,2,FALSE) -> SURCO | D153: =VLOOKUP(B153,sheet2!$A$1:$K$1775,5,FALSE) -> CASUÍSTICA CONTABLE | E153: =VLOOKUP(B153,sheet2!$A$1:$K$1775,11,FALSE) -> N | F153: =VLOOKUP(B153,sheet2!$A$1:$K$1775,4,FALSE) -> 7258
A154: 1G1 | B154: 2413 | C154: =VLOOKUP(B154,sheet2!$A$1:$K$1775,2,FALSE) -> SURCO | D154: =VLOOKUP(B154,sheet2!$A$1:$K$1775,5,FALSE) -> MARKETING DIGITAL | E154: =VLOOKUP(B154,sheet2!$A$1:$K$1775,11,FALSE) -> M | F154: =VLOOKUP(B154,sheet2!$A$1:$K$1775,4,FALSE) -> 668671
A155: 1G1 | B155: 2226 | C155: =VLOOKUP(B155,sheet2!$A$1:$K$1775,2,FALSE) -> SURCO | D155: =VLOOKUP(B155,sheet2!$A$1:$K$1775,5,FALSE) -> CONTABILIDAD GERENCIAL | E155: =VLOOKUP(B155,sheet2!$A$1:$K$1775,11,FALSE) -> N | F155: =VLOOKUP(B155,sheet2!$A$1:$K$1775,4,FALSE) -> 7259
A156: 1G1 | B156: 2370 | C156: =VLOOKUP(B156,sheet2!$A$1:$K$1775,2,FALSE) -> SURCO | D156: =VLOOKUP(B156,sheet2!$A$1:$K$1775,5,FALSE) -> BIOSEGURIDAD | E156: =VLOOKUP(B156,sheet2!$A$1:$K$1775,11,FALSE) -> M | F156: =VLOOKUP(B156,sheet2!$A$1:$K$1775,4,FALSE) -> 668582
A157: 1G2 | B157: 2422 | C157: =VLOOKUP(B157,sheet2!$A$1:$K$1775,2,FALSE) -> SURCO | D157: =VLOOKUP(B157,sheet2!$A$1:$K$1775,5,FALSE) -> FUNDAMENTOS DE MARKETING | E157: =VLOOKUP(B157,sheet2!$A$1:$K$1775,11,FALSE) -> N | F157: =VLOOKUP(B157,sheet2!$A$1:$K$1775,4,FALSE) -> 668705
A158: 1G2 | B158: 2235 | C158: =VLOOKUP(B158,sheet2!$A$1:$K$1775,2,FALSE) -> SURCO | D158: =VLOOKUP(B158,sheet2!$A$1:$K$1775,5,FALSE) -> MARKETING DIGITAL | E158: =VLOOKUP(B158,sheet2!$A$1:$K$1775,11,FALSE) -> M | F158: =VLOOKUP(B158,sheet2!$A$1:$K$1775,4,FALSE) -> 9030
A159: 1G2 | B159: 2379 | C159: =VLOOKUP(B159,sheet2!$A$1:$K$1775,2,FALSE) -> SURCO | D159: =VLOOKUP(B159,sheet2!$A$1:$K$1775,5,FALSE) -> MASOTERAPIA EN EL DEPORTE | E159: =VLOOKUP(B159,sheet2!$A$1:$K$1775,11,FALSE) -> M | F159: =VLOOKUP(B159,sheet2!$A$1:$K$1775,4,FALSE) -> 668587
A160: 1G3 | B160: 2382 | C160: =VLOOKUP(B160,sheet2!$A$1:$K$1775,2,FALSE) -> SURCO | D160: =VLOOKUP(B160,sheet2!$A$1:$K$1775,5,FALSE) -> MASOTERAPIA EN EL DEPORTE | E160: =VLOOKUP(B160,sheet2!$A$1:$K$1775,11,FALSE) -> N | F160: =VLOOKUP(B160,sheet2!$A$1:$K$1775,4,FALSE) -> 668587
A161: 1G3 | B161: 2238 | C161: =VLOOKUP(B161,sheet2!$A$1:$K$1775,2,FALSE) -> SURCO | D161: =VLOOKUP(B161,sheet2!$A$1:$K$1775,5,FALSE) -> GES DE TE Y DEL CAP DE TRABAJO | E161: =VLOOKUP(B161,sheet2!$A$1:$K$1775,11,FALSE) -> M | F161: =VLOOKUP(B161,sheet2!$A$1:$K$1775,4,FALSE) -> 9036
A162: 1G3 | B162: 2425 | C162: =VLOOKUP(B162,sheet2!$A$1:$K$1775,2,FALSE) -> SURCO | D162: =VLOOKUP(B162,sheet2!$A$1:$K$1775,5,FALSE) -> CONTABILIDAD I | E162: =VLOOKUP(B162,sheet2!$A$1:$K$1775,11,FALSE) -> M | F162: =VLOOKUP(B162,sheet2!$A$1:$K$1775,4,FALSE) -> 668742
... A204: 1G17 | B204: 2377 | C204: =VLOOKUP(B204,sheet2!$A$1:$K$1775,2,FALSE) -> SURCO | D204: =VLOOKUP(B204,sheet2!$A$1:$K$1775,5,FALSE) -> MASOTERAPIA EN EL DEPORTE | E204: =VLOOKUP(B204,sheet2!$A$1:$K$1775,11,FALSE) -> M | F204: =VLOOKUP(B204,sheet2!$A$1:$K$1775,4,FALSE) -> 668587
C205: =VLOOKUP(B205,sheet2!$A$1:$K$1775,2,FALSE) -> #N/A | D205: =VLOOKUP(B205,sheet2!$A$1:$K$1775,5,FALSE) -> #N/A | E205: =VLOOKUP(B205,sheet2!$A$1:$K$1775,11,FALSE) -> #N/A | F205: =VLOOKUP(B205,sheet2!$A$1:$K$1775,4,FALSE) -> #N/A
A206: 1G25 | B206: 2236 | C206: =VLOOKUP(B206,sheet2!$A$1:$K$1775,2,FALSE) -> SURCO | D206: =VLOOKUP(B206,sheet2!$A$1:$K$1775,5,FALSE) -> GESTIÓN ESTRATÉGICA | E206: =VLOOKUP(B206,sheet2!$A$1:$K$1775,11,FALSE) -> M | F206: =VLOOKUP(B206,sheet2!$A$1:$K$1775,4,FALSE) -> 9031
A207: 1G25 | B207: 2380 | C207: =VLOOKUP(B207,sheet2!$A$1:$K$1775,2,FALSE) -> SURCO | D207: =VLOOKUP(B207,sheet2!$A$1:$K$1775,5,FALSE) -> MASOTERAPIA EN EL DEPORTE | E207: =VLOOKUP(B207,sheet2!$A$1:$K$1775,11,FALSE) -> M | F207: =VLOOKUP(B207,sheet2!$A$1:$K$1775,4,FALSE) -> 668587
A208: 1G25 | B208: 2423 | C208: =VLOOKUP(B208,sheet2!$A$1:$K$1775,2,FALSE) -> SURCO | D208: =VLOOKUP(B208,sheet2!$A$1:$K$1775,5,FALSE) -> ESTADÍS. APLIC. A LOS NEGOCIOS | E208: =VLOOKUP(B208,sheet2!$A$1:$K$1775,11,FALSE) -> M | F208: =VLOOKUP(B208,sheet2!$A$1:$K$1775,4,FALSE) -> 668741
A209: 1G26 | B209: 2381 | C209: =VLOOKUP(B209,sheet2!$A$1:$K$1775,2,FALSE) -> SURCO | D209: =VLOOKUP(B209,sheet2!$A$1:$K$1775,5,FALSE) -> MASOTERAPIA EN EL DEPORTE | E209: =VLOOKUP(B209,sheet2!$A$1:$K$1775,11,FALSE) -> N | F209: =VLOOKUP(B209,sheet2!$A$1:$K$1775,4,FALSE) -> 668587
A210: 1G26 | B210: 2424 | C210: =VLOOKUP(B210,sheet2!$A$1:$K$1775,2,FALSE) -> SURCO | D210: =VLOOKUP(B210,sheet2!$A$1:$K$1775,5,FALSE) -> ESTADÍS. APLIC. A LOS NEGOCIOS | E210: =VLOOKUP(B210,sheet2!$A$1:$K$1775,11,FALSE) -> N | F210: =VLOOKUP(B210,sheet2!$A$1:$K$1775,4,FALSE) -> 668741
A211: 1G26 | B211: 2237 | C211: =VLOOKUP(B211,sheet2!$A$1:$K$1775,2,FALSE) -> SURCO | D211: =VLOOKUP(B211,sheet2!$A$1:$K$1775,5,FALSE) -> EXPE FORMA INTERME (MKT PER) | E211: =VLOOKUP(B211,sheet2!$A$1:$K$1775,11,FALSE) -> M | F211: =VLOOKUP(B211,sheet2!$A$1:$K$1775,4,FALSE) -> 9032
C212: =VLOOKUP(B212,sheet2!$A$1:$K$1775,2,FALSE) -> #N/A | D212: =VLOOKUP(B212,sheet2!$A$1:$K$1775,5,FALSE) -> #N/A | E212: =VLOOKUP(B212,sheet2!$A$1:$K$1775,11,FALSE) -> #N/A | F212: =VLOOKUP(B212,sheet2!$A$1:$K$1775,4,FALSE) -> #N/A
A213: 1G | B213: 2412 | C213: =VLOOKUP(B213,sheet2!$A$1:$K$1775,2,FALSE) -> SURCO | D213: =VLOOKUP(B213,sheet2!$A$1:$K$1775,5,FALSE) -> PATRONAJE DIGITAL - AUDACES | E213: =VLOOKUP(B213,sheet2!$A$1:$K$1775,11,FALSE) -> M | F213: =VLOOKUP(B213,sheet2!$A$1:$K$1775,4,FALSE) -> 668668
A214: 1G | B214: 2369 | C214: =VLOOKUP(B214,sheet2!$A$1:$K$1775,2,FALSE) -> SURCO | D214: =VLOOKUP(B214,sheet2!$A$1:$K$1775,5,FALSE) -> TÉC DE MOVIM PARA PACIEN POSTR | E214: =VLOOKUP(B214,sheet2!$A$1:$K$1775,11,FALSE) -> N | F214: =VLOOKUP(B214,sheet2!$A$1:$K$1775,4,FALSE) -> 668581
A215: 1G | B215: 2225 | C215: =VLOOKUP(B215,sheet2!$A$1:$K$1775,2,FALSE) -> SURCO | D215: =VLOOKUP(B215,sheet2!$A$1:$K$1775,5,FALSE) -> CASUÍSTICA CONTABLE | E215: =VLOOKUP(B215,sheet2!$A$1:$K$1775,11,FALSE) -> N | F215: =VLOOKUP(B215,sheet2!$A$1:$K$1775,4,FALSE) -> 7258
A216: 1G1 | B216: 2413 | C216: =VLOOKUP(B216,sheet2!$A$1:$K$1775,2,FALSE) -> SURCO | D216: =VLOOKUP(B216,sheet2!$A$1:$K$1775,5,FALSE) -> MARKETING DIGITAL | E216: =VLOOKUP(B216,sheet2!$A$1:$K$1775,11,FALSE) -> M | F216: =VLOOKUP(B216,sheet2!$A$1:$K$1775,4,FALSE) -> 668671
A217: 1G1 | B217: 2226 | C217: =VLOOKUP(B217,sheet2!$A$1:$K$1775,2,FALSE) -> SURCO | D217: =VLOOKUP(B217,sheet2!$A$1:$K$1775,5,FALSE) -> CONTABILIDAD GERENCIAL | E217: =VLOOKUP(B217,sheet2!$A$1:$K$1775,11,FALSE) -> N | F217: =VLOOKUP(B217,sheet2!$A$1:$K$1775,4,FALSE) -> 7259
A218: 1G1 | B218: 2370 | C218: =VLOOKUP(B218,sheet2!$A$1:$K$1775,2,FALSE) -> SURCO | D218: =VLOOKUP(B218,sheet2!$A$1:$K$1775,5,FALSE) -> BIOSEGURIDAD | E218: =VLOOKUP(B218,sheet2!$A$1:$K$1775,11,FALSE) -> M | F218: =VLOOKUP(B218,sheet2!$A$1:$K$1775,4,FALSE) -> 668582
A219: 1G2 | B219: 2422 | C219: =VLOOKUP(B219,sheet2!$A$1:$K$1775,2,FALSE) -> SURCO | D219: =VLOOKUP(B219,sheet2!$A$1:$K$1775,5,FALSE) -> FUNDAMENTOS DE MARKETING | E219: =VLOOKUP(B219,sheet2!$A$1:$K$1775,11,FALSE) -> N | F219: =VLOOKUP(B219,sheet2!$A$1:$K$1775,4,FALSE) -> 668705
A220: 1G2 | B220: 2235 | C220: =VLOOKUP(B220,sheet2!$A$1:$K$1775,2,FALSE) -> SURCO | D220: =VLOOKUP(B220,sheet2!$A$1:$K$1775,5,FALSE) -> MARKETING DIGITAL | E220: =VLOOKUP(B220,sheet2!$A$1:$K$1775,11,FALSE) -> M | F220: =VLOOKUP(B220,sheet2!$A$1:$K$1775,4,FALSE) -> 9030
A221: 1G2 | B221: 2379 | C221: =VLOOKUP(B221,sheet2!$A$1:$K$1775,2,FALSE) -> SURCO | D221: =VLOOKUP(B221,sheet2!$A$1:$K$1775,5,FALSE) -> MASOTERAPIA EN EL DEPORTE | E221: =VLOOKUP(B221,sheet2!$A$1:$K$1775,11,FALSE) -> M | F221: =VLOOKUP(B221,sheet2!$A$1:$K$1775,4,FALSE) -> 668587
A222: 1G3 | B222: 2382 | C222: =VLOOKUP(B222,sheet2!$A$1:$K$1775,2,FALSE) -> SURCO | D222: =VLOOKUP(B222,sheet2!$A$1:$K$1775,5,FALSE) -> MASOTERAPIA EN EL DEPORTE | E222: =VLOOKUP(B222,sheet2!$A$1:$K$1775,11,FALSE) -> N | F222: =VLOOKUP(B222,sheet2!$A$1:$K$1775,4,FALSE) -> 668587
A223: 1G3 | B223: 2238 | C223: =VLOOKUP(B223,sheet2!$A$1:$K$1775,2,FALSE) -> SURCO | D223: =VLOOKUP(B223,sheet2!$A$1:$K$1775,5,FALSE) -> GES DE TE Y DEL CAP DE TRABAJO | E223: =VLOOKUP(B223,sheet2!$A$1:$K$1775,11,FALSE) -> M | F223: =VLOOKUP(B223,sheet2!$A$1:$K$1775,4,FALSE) -> 9036
A224: 1G3 | B224: 2425 | C224: =VLOOKUP(B224,sheet2!$A$1:$K$1775,2,FALSE) -> SURCO | D224: =VLOOKUP(B224,sheet2!$A$1:$K$1775,5,FALSE) -> CONTABILIDAD I | E224: =VLOOKUP(B224,sheet2!$A$1:$K$1775,11,FALSE) -> M | F224: =VLOOKUP(B224,sheet2!$A$1:$K$1775,4,FALSE) -> 668742
... A257: 1G17 | B257: 2377 | C257: =VLOOKUP(B257,sheet2!$A$1:$K$1775,2,FALSE) -> SURCO | D257: =VLOOKUP(B257,sheet2!$A$1:$K$1775,5,FALSE) -> MASOTERAPIA EN EL DEPORTE | E257: =VLOOKUP(B257,sheet2!$A$1:$K$1775,11,FALSE) -> M | F257: =VLOOKUP(B257,sheet2!$A$1:$K$1775,4,FALSE) -> 668587
C258: =VLOOKUP(B258,sheet2!$A$1:$K$1775,2,FALSE) -> #N/A | D258: =VLOOKUP(B258,sheet2!$A$1:$K$1775,5,FALSE) -> #N/A | E258: =VLOOKUP(B258,sheet2!$A$1:$K$1775,11,FALSE) -> #N/A | F258: =VLOOKUP(B258,sheet2!$A$1:$K$1775,4,FALSE) -> #N/A
A259: 1R | B259: 2606 | C259: =VLOOKUP(B259,sheet2!$A$1:$K$1775,2,FALSE) -> VENTN | D259: =VLOOKUP(B259,sheet2!$A$1:$K$1775,5,FALSE) -> INYECT Y TÉC DE ADM DE MEDIC | E259: =VLOOKUP(B259,sheet2!$A$1:$K$1775,11,FALSE) -> M | F259: =VLOOKUP(B259,sheet2!$A$1:$K$1775,4,FALSE) -> 668580
A260: 1R | B260: 2479 | C260: =VLOOKUP(B260,sheet2!$A$1:$K$1775,2,FALSE) -> SURCO | D260: =VLOOKUP(B260,sheet2!$A$1:$K$1775,5,FALSE) -> DISEÑO DIGITAL ILLUSTRATOR | E260: =VLOOKUP(B260,sheet2!$A$1:$K$1775,11,FALSE) -> M | F260: =VLOOKUP(B260,sheet2!$A$1:$K$1775,4,FALSE) -> 668835
A261: 1R | B261: 2395 | C261: =VLOOKUP(B261,sheet2!$A$1:$K$1775,2,FALSE) -> SURCO | D261: =VLOOKUP(B261,sheet2!$A$1:$K$1775,5,FALSE) -> ENFE. Y SU TRATAM. FARMACOLÓG. | E261: =VLOOKUP(B261,sheet2!$A$1:$K$1775,11,FALSE) -> N | F261: =VLOOKUP(B261,sheet2!$A$1:$K$1775,4,FALSE) -> 668611
A262: 1R1 | B262: 2607 | C262: =VLOOKUP(B262,sheet2!$A$1:$K$1775,2,FALSE) -> VENTN | D262: =VLOOKUP(B262,sheet2!$A$1:$K$1775,5,FALSE) -> INYECT Y TÉC DE ADM DE MEDIC | E262: =VLOOKUP(B262,sheet2!$A$1:$K$1775,11,FALSE) -> N | F262: =VLOOKUP(B262,sheet2!$A$1:$K$1775,4,FALSE) -> 668580
A263: 1R1 | B263: 2479 | C263: =VLOOKUP(B263,sheet2!$A$1:$K$1775,2,FALSE) -> SURCO | D263: =VLOOKUP(B263,sheet2!$A$1:$K$1775,5,FALSE) -> DISEÑO DIGITAL ILLUSTRATOR | E263: =VLOOKUP(B263,sheet2!$A$1:$K$1775,11,FALSE) -> M | F263: =VLOOKUP(B263,sheet2!$A$1:$K$1775,4,FALSE) -> 668835
A264: 1R1 | B264: 2396 | C264: =VLOOKUP(B264,sheet2!$A$1:$K$1775,2,FALSE) -> SURCO | D264: =VLOOKUP(B264,sheet2!$A$1:$K$1775,5,FALSE) -> BIOMECÁNICA Y MECANOTERAPIA | E264: =VLOOKUP(B264,sheet2!$A$1:$K$1775,11,FALSE) -> M | F264: =VLOOKUP(B264,sheet2!$A$1:$K$1775,4,FALSE) -> 668631
A265: 1R2 | B265: 2403 | C265: =VLOOKUP(B265,sheet2!$A$1:$K$1775,2,FALSE) -> SURCO | D265: =VLOOKUP(B265,sheet2!$A$1:$K$1775,5,FALSE) -> DISEÑO INDUMENTARIA FEMENINA | E265: =VLOOKUP(B265,sheet2!$A$1:$K$1775,11,FALSE) -> M | F265: =VLOOKUP(B265,sheet2!$A$1:$K$1775,4,FALSE) -> 668654
A266: 1R2 | B266: 2479 | C266: =VLOOKUP(B266,sheet2!$A$1:$K$1775,2,FALSE) -> SURCO | D266: =VLOOKUP(B266,sheet2!$A$1:$K$1775,5,FALSE) -> DISEÑO DIGITAL ILLUSTRATOR | E266: =VLOOKUP(B266,sheet2!$A$1:$K$1775,11,FALSE) -> M | F266: =VLOOKUP(B266,sheet2!$A$1:$K$1775,4,FALSE) -> 668835
...

Sheet CONSOLIDADO
A1: Institución | B1: Grado | C1: Prog Acad | D1: Plan Acad | E1: Ciclo | F1: Bloque | G1: Descr Corta | H1: Descr | I1: Lista Cso | J1: Descr Corta | K1: Sec Curso | L1: ID Curso | M1: Descr2 | N1: Línea | O1: Descr | P1: Tipo Línea | Q1: Descr | R1: Mín Uni | S1: Máx Uni | T1: OPRID | U1: FECHA | V1: HORA | W1: Gp Cond | X1: Línea | Y1: Tp Req | Z1: Conector | AA1: Corchete_Entrada | AB1: ID Curso | AC1: Descr | AD1: Cond | AE1: Descr | AF1: Corchete_Salida | AG1: Ciclo2 | AH1: Requisito | AI1: Programas
A2: SISE | B2: PRGS | C2: ADMNE | D2: ADM2020 | E2: 0001 | F2: 0001 | G2: AEMC1B1 20 | H2: ADM DE EMPRESAS DCB 2020 | I2: 000000845 | J2: AEMC1B1 20 | K2: 1 | L2: 667275 | M2: ADMINISTRACIÓN GENERAL | N2: 0010 | O2: ADM EMPRESAS DCB 2020 C1B1 | P2: MT | Q2: ADMINISTRACIÓN DE EMPRESAS DCB 2020 C1B1 | R2: 3 | S2: 3 | U2: 26/09/2023 | V2: 01:18:08 p.m. | W2: 001637 | X2: 0010 | Y2: Req Adic | AD2: 000000785 | AE2: ADM BANC DCB 2020 C1B1 | AG2: C1B1 | AH2: NINGUNO | AI2: ADMBF / ADMLO / ADMNE / ADMNI / CONTA / MARKT
A3: SISE | B3: PRGS | C3: ADMNE | D3: ADM2020 | E3: 0001 | F3: 0001 | G3: AEMC1B1 20 | H3: ADM DE EMPRESAS DCB 2020 | I3: 000000845 | J3: AEMC1B1 20 | K3: 2 | L3: 667276 | M3: FUNDAMENTOS DE MARKETING | N3: 0010 | O3: ADM EMPRESAS DCB 2020 C1B1 | P3: MT | Q3: ADMINISTRACIÓN DE EMPRESAS DCB 2020 C1B1 | R3: 2 | S3: 2 | U3: 26/09/2023 | V3: 01:18:08 p.m. | W3: 001637 | X3: 0010 | Y3: Req Adic | AD3: 000000785 | AE3: ADM BANC DCB 2020 C1B1 | AG3: C1B1 | AH3: NINGUNO | AI3: ADMBF / ADMLO / ADMNE / ADMNI / CONTA / MARKT
A4: SISE | B4: PRGS | C4: ADMNE | D4: ADM2020 | E4: 0001 | F4: 0001 | G4: AEMC1B1 20 | H4: ADM DE EMPRESAS DCB 2020 | I4: 000000845 | J4: AEMC1B1 20 | K4: 3 | L4: 667277 | M4: CONTABILIDAD BÁSICA | N4: 0010 | O4: ADM EMPRESAS DCB 2020 C1B1 | P4: MT | Q4: ADMINISTRACIÓN DE EMPRESAS DCB 2020 C1B1 | R4: 4 | S4: 4 | U4: 26/09/2023 | V4: 01:18:08 p.m. | W4: 001637 | X4: 0010 | Y4: Req Adic | AD4: 000000785 | AE4: ADM BANC DCB 2020 C1B1 | AG4: C1B1 | AH4: NINGUNO | AI4: ADMBF / ADMNE / ADMNI / CONTA / MARKT
A5: SISE | B5: PRGS | C5: ADMNE | D5: ADM2020 | E5: 0001 | F5: 0001 | G5: AEMC1B1 20 | H5: ADM DE EMPRESAS DCB 2020 | I5: 000000845 | J5: AEMC1B1 20 | K5: 4 | L5: 667278 | M5: COMUNICACIÓN EFECTIVA | N5: 0010 | O5: ADM EMPRESAS DCB 2020 C1B1 | P5: MT | Q5: ADMINISTRACIÓN DE EMPRESAS DCB 2020 C1B1 | R5: 2 | S5: 2 | U5: 26/09/2023 | V5: 01:18:08 p.m. | W5: 001635 | X5: 0010 | Y5: Req Adic | AD5: 000000773 | AE5: DIS GRAFICO DCB 2020 C1B1 | AG5: C1B1 | AH5: NINGUNO | AI5: ADHYR / ADMBF / ADMLO / ADMNE / ADMNI / COMAU / CONTA / DG / DYGMO / FISIO / GASTR / MARKT / PA / REDES / SALUD / SECRE / SWSIS / TECFA
A6: SISE | B6: PRGS | C6: ADMNE | D6: ADM2020 | E6: 0002 | F6: 0001 | G6: AEMC1B2 20 | H6: ADM DE EMPRESAS DCB 2020 | I6: 000000846 | J6: AEMC1B2 20 | K6: 1 | L6: 667281 | M6: INTRODUCCIÓN AL SISTEMA FINANC | N6: 0020 | O6: ADM EMPRESAS DCB 2020 C1B2 | P6: MT | Q6: ADMINISTRACIÓN DE EMPRESAS DCB 2020 C1B2 | R6: 2 | S6: 2 | U6: 26/09/2023 | V6: 01:18:08 p.m. | W6: 001622 | X6: 0010 | Y6: Req Adic | AD6: 000000822 | AE6: ADM EMPRESAS DCB 2020 C1B2 | AG6: C1B2 | AH6: NINGUNO | AI6: ADMBF / ADMNE / ADMNI / CONTA / MARKT
A7: SISE | B7: PRGS | C7: ADMNE | D7: ADM2020 | E7: 0002 | F7: 0001 | G7: AEMC1B2 20 | H7: ADM DE EMPRESAS DCB 2020 | I7: 000000846 | J7: AEMC1B2 20 | K7: 2 | L7: 667279 | M7: EXCEL PARA LOS NEGOCIOS | N7: 0020 | O7: ADM EMPRESAS DCB 2020 C1B2 | P7: MT | Q7: ADMINISTRACIÓN DE EMPRESAS DCB 2020 C1B2 | R7: 2 | S7: 2 | U7: 26/09/2023 | V7: 01:18:08 p.m. | W7: 001622 | X7: 0010 | Y7: Req Adic | AD7: 000000822 | AE7: ADM EMPRESAS DCB 2020 C1B2 | AG7: C1B2 | AH7: NINGUNO | AI7: ADMBF / ADMLO / ADMNE / ADMNI / CONTA / MARKT
A8: SISE | B8: PRGS | C8: ADMNE | D8: ADM2020 | E8: 0002 | F8: 0001 | G8: AEMC1B2 20 | H8: ADM DE EMPRESAS DCB 2020 | I8: 000000846 | J8: AEMC1B2 20 | K8: 3 | L8: 667280 | M8: TÉCNICAS DE VENTAS | N8: 0020 | O8: ADM EMPRESAS DCB 2020 C1B2 | P8: MT | Q8: ADMINISTRACIÓN DE EMPRESAS DCB 2020 C1B2 | R8: 2 | S8: 2 | U8: 26/09/2023 | V8: 01:18:08 p.m. | W8: 001622 | X8: 0010 | Y8: Req Adic | AD8: 000000822 | AE8: ADM EMPRESAS DCB 2020 C1B2 | AG8: C1B2 | AH8: NINGUNO | AI8: ADMBF / ADMLO / ADMNE / ADMNI / CONTA / MARKT
A9: SISE | B9: PRGS | C9: ADMNE | D9: ADM2020 | E9: 0002 | F9: 0001 | G9: AEMC1B2 20 | H9: ADM DE EMPRESAS DCB 2020 | I9: 000000846 | J9: AEMC1B2 20 | K9: 4 | L9: 667353 | M9: LIDERAZGO Y TRABAJO EN EQUIPO | N9: 0020 | O9: ADM EMPRESAS DCB 2020 C1B2 | P9: MT | Q9: ADMINISTRACIÓN DE EMPRESAS DCB 2020 C1B2 | R9: 3 | S9: 3 | U9: 26/09/2023 | V9: 01:18:08 p.m. | W9: 001623 | X9: 0010 | Y9: Req Adic | AD9: 000000786 | AE9: ADM BANC DCB 2020 C1B2 | AG9: C1B2 | AH9: NINGUNO | AI9: ADHYR / ADMBF / ADMLO / ADMNE / ADMNI / COMAU / CONTA / DG / DYGMO / FISIO / GASTR / MARKT / PA / REDES / SALUD / SECRE / SWSIS / TECFA
A10: SISE | B10: PRGS | C10: ADMNE | D10: ADM2020 | E10: 0002 | F10: 0001 | G10: AEMC1B2 20 | H10: ADM DE EMPRESAS DCB 2020 | I10: 000000846 | J10: AEMC1B2 20 | K10: 5 | L10: 667282 | M10: EDUCACIÓN FINANCIERA (V) | N10: 0020 | O10: ADM EMPRESAS DCB 2020 C1B2 | P10: MT | Q10: ADMINISTRACIÓN DE EMPRESAS DCB 2020 C1B2 | R10: 3 | S10: 3 | U10: 26/09/2023 | V10: 01:18:08 p.m. | W10: 001624 | X10: 0010 | Y10: Req Adic | AD10: 000000786 | AE10: ADM BANC DCB 2020 C1B2 | AG10: C1B2 | AH10: NINGUNO | AI10: ADHYR / ADMBF / ADMLO / ADMNE / ADMNI / COMAU / CONTA / DG / DYGMO / GASTR / MARKT / PA / REDES / SECRE / SWSIS
A11: SISE | B11: PRGS | C11: ADMNE | D11: ADM2020 | E11: 0003 | F11: 0001 | G11: AEMC2B1 20 | H11: ADM DE EMPRESAS DCB 2020 | I11: 000000847 | J11: AEMC2B1 20 | K11: 1 | L11: 667283 | M11: COSTOS Y PRESUPUESTOS | N11: 0030 | O11: ADM EMPRESAS DCB 2020 C2B1 | P11: MT | Q11: ADMINISTRACIÓN DE EMPRESAS DCB 2020 C2B1 | R11: 2 | S11: 2 | U11: 26/09/2023 | V11: 01:18:08 p.m. | W11: 000388 | X11: 0010 | Y11: Req Previo | AB11: 667277 | AC11: CONTABILIDAD BÁSICA | AG11: C2B1 | AH11: CONTABILIDAD BÁSICA | AI11: ADMBF / ADMLO / ADMNE / ADMNI / CONTA / MARKT
A12: SISE | B12: PRGS | C12: ADMNE | D12: ADM2020 | E12: 0003 | F12: 0001 | G12: AEMC2B1 20 | H12: ADM DE EMPRESAS DCB 2020 | I12: 000000847 | J12: AEMC2B1 20 | K12: 2 | L12: 667541 | M12: ÉTICA Y CIUDADANÍA | N12: 0030 | O12: ADM EMPRESAS DCB 2020 C2B1 | P12: MT | Q12: ADMINISTRACIÓN DE EMPRESAS DCB 2020 C2B1 | R12: 2 | S12: 2 | U12: 26/09/2023 | V12: 01:18:08 p.m. | W12: 001636 | X12: 0010 | Y12: Req Adic | AD12: 000000775 | AE12: DIS GRAFICO DCB 2020 C2B1 | AG12: C2B1 | AH12: NINGUNO | AI12: ADHYR / ADMBF / ADMLO / ADMNE / ADMNI / COMAU / CONTA / DG / DYGMO / FISIO / MARKT / PA / REDES / SALUD / SECRE / SWSIS / TECFA
A13: SISE | B13: PRGS | C13: ADMNE | D13: ADM2020 | E13: 0003 | F13: 0001 | G13: AEMC2B1 20 | H13: ADM DE EMPRESAS DCB 2020 | I13: 000000847 | J13: AEMC2B1 20 | K13: 3 | L13: 9010 | M13: COMERCIO INTERNACIONAL | N13: 0030 | O13: ADM EMPRESAS DCB 2020 C2B1 | P13: MT | Q13: ADMINISTRACIÓN DE EMPRESAS DCB 2020 C2B1 | R13: 2 | S13: 2 | U13: 26/09/2023 | V13: 01:18:08 p.m. | W13: 001332 | X13: 0010 | Y13: Req Previo | AB13: 667280 | AC13: TÉCNICAS DE VENTAS | AG13: C2B1 | AH13: TÉCNICAS DE VENTAS | AI13: ADMNE / ADMNI / MARKT
A14: SISE | B14: PRGS | C14: ADMNE | D14: ADM2020 | E14: 0003 | F14: 0001 | G14: AEMC2B1 20 | H14: ADM DE EMPRESAS DCB 2020 | I14: 000000847 | J14: AEMC2B1 20 | K14: 4 | L14: 9011 | M14: INNOVACIÓN Y NEGOCIOS | N14: 0030 | O14: ADM EMPRESAS DCB 2020 C2B1 | P14: MT | Q14: ADMINISTRACIÓN DE EMPRESAS DCB 2020 C2B1 | R14: 2 | S14: 2 | U14: 26/09/2023 | V14: 01:18:08 p.m. | W14: 001655 | X14: 0030 | Y14: Req Adic | AD14: 000000811 | AE14: ADM LOGISTICA DCB 2020 C2B1 | AG14: C2B1 | AH14: NINGUNO | AI14: ADMLO / ADMNE / ADMNI / MARKT
A15: SISE | B15: PRGS | C15: ADMNE | D15: ADM2020 | E15: 0004 | F15: 0001 | G15: AEMC2B2 20 | H15: ADM DE EMPRESAS DCB 2020 | I15: 000000848 | J15: AEMC2B2 20 | K15: 1 | L15: 667285 | M15: LEG COMERCIAL Y TRIBUTARIA | N15: 0040 | O15: ADM EMPRESAS DCB 2020 C2B2 | P15: MT | Q15: ADMINISTRACIÓN DE EMPRESAS DCB 2020 C2B2 | R15: 2 | S15: 2 | U15: 26/09/2023 | V15: 01:18:08 p.m. | W15: 001661 | X15: 0030 | Y15: Req Adic | AD15: 000000788 | AE15: ADM BANC DCB 2020 C2B2 | AG15: C2B2 | AH15: NINGUNO | AI15: ADMBF / ADMLO / ADMNE / ADMNI / CONTA / MARKT
A16: SISE | B16: PRGS | C16: ADMNE | D16: ADM2020 | E16: 0004 | F16: 0001 | G16: AEMC2B2 20 | H16: ADM DE EMPRESAS DCB 2020 | I16: 000000848 | J16: AEMC2B2 20 | K16: 2 | L16: 667286 | M16: MATEMÁTICA COMERCIAL | N16: 0040 | O16: ADM EMPRESAS DCB 2020 C2B2 | P16: MT | Q16: ADMINISTRACIÓN DE EMPRESAS DCB 2020 C2B2 | R16: 2 | S16: 2 | U16: 26/09/2023 | V16: 01:18:08 p.m. | W16: 001669 | X16: 0030 | Y16: Req Adic | AD16: 000000812 | AE16: ADM LOGISTICA DCB 2020 C2B2 | AG16: C2B2 | AH16: NINGUNO | AI16: ADMNE / ADMNI / MARKT
A17: SISE | B17: PRGS | C17: ADMNE | D17: ADM2020 | E17: 0004 | F17: 0001 | G17: AEMC2B2 20 | H17: ADM DE EMPRESAS DCB 2020 | I17: 000000848 | J17: AEMC2B2 20 | K17: 3 | L17: 667287 | M17: SOCIAL MEDIA | N17: 0040 | O17: ADM EMPRESAS DCB 2020 C2B2 | P17: MT | Q17: ADMINISTRACIÓN DE EMPRESAS DCB 2020 C2B2 | R17: 2 | S17: 2 | U17: 26/09/2023 | V17: 01:18:08 p.m. | W17: 001663 | X17: 0010 | Y17: Req Previo | AB17: 667276 | AC17: FUNDAMENTOS DE MARKETING | AG17: C2B2 | AH17: FUNDAMENTOS DE MARKETING | AI17: ADMLO / ADMNE / ADMNI / MARKT
A18: SISE | B18: PRGS | C18: ADMNE | D18: ADM2020 | E18: 0004 | F18: 0001 | G18: AEMC2B2 20 | H18: ADM DE EMPRESAS DCB 2020 | I18: 000000848 | J18: AEMC2B2 20 | K18: 4 | L18: 667288 | M18: EXP FORMA BÁSICAS (HERR INFOR) | N18: 0040 | O18: ADM EMPRESAS DCB 2020 C2B2 | P18: MT | Q18: ADMINISTRACIÓN DE EMPRESAS DCB 2020 C2B2 | R18: 4 | S18: 4 | U18: 26/09/2023 | V18: 01:18:08 p.m. | W18: 001661 | X18: 0030 | Y18: Req Adic | AD18: 000000788 | AE18: ADM BANC DCB 2020 C2B2 | AG18: C2B2 | AH18: NINGUNO | AI18: ADMBF / ADMLO / ADMNE / ADMNI / CONTA / MARKT
A19: SISE | B19: PRGS | C19: ADMNE | D19: ADM2020 | E19: 0005 | F19: 0001 | G19: AEMC3B1 20 | H19: ADM DE EMPRESAS DCB 2020 | I19: 000000849 | J19: AEMC3B1 20 | K19: 1 | L19: 667293 | M19: MATEMÁTICA FINANCIERA | N19: 0050 | O19: ADM EMPRESAS DCB 2020 C3B1 | P19: MT | Q19: ADMINISTRACIÓN DE EMPRESAS DCB 2020 C3B1 | R19: 3 | S19: 3 | U19: 26/09/2023 | V19: 01:18:08 p.m. | W19: 001676 | X19: 0010 | Y19: Req Previo | AB19: 667286 | AC19: MATEMÁTICA COMERCIAL | AG19: C3B1 | AH19: MATEMÁTICA COMERCIAL | AI19: ADMBF / ADMNE / ADMNI / CONTA / MARKT
A20: SISE | B20: PRGS | C20: ADMNE | D20: ADM2020 | E20: 0005 | F20: 0001 | G20: AEMC3B1 20 | H20: ADM DE EMPRESAS DCB 2020 | I20: 000000849 | J20: AEMC3B1 20 | K20: 2 | L20: 667294 | M20: ESTADÍSTICA APLICADA A LOS NEG | N20: 0050 | O20: ADM EMPRESAS DCB 2020 C3B1 | P20: MT | Q20: ADMINISTRACIÓN DE EMPRESAS DCB 2020 C3B1 | R20: 3 | S20: 3 | U20: 26/09/2023 | V20: 01:18:08 p.m. | W20: 001678 | X20: 0010 | Y20: Req Previo | AB20: 667279 | AC20: EXCEL PARA LOS NEGOCIOS | AG20: C3B1 | AH20: EXCEL PARA LOS NEGOCIOS | AI20: ADMBF / ADMLO / ADMNE / ADMNI / CONTA / MARKT
A21: SISE | B21: PRGS | C21: ADMNE | D21: ADM2020 | E21: 0005 | F21: 0001 | G21: AEMC3B1 20 | H21: ADM DE EMPRESAS DCB 2020 | I21: 000000849 | J21: AEMC3B1 20 | K21: 3 | L21: 667295 | M21: GESTIÓN DE CLIENTES - CRM | N21: 0050 | O21: ADM EMPRESAS DCB 2020 C3B1 | P21: MT | Q21: ADMINISTRACIÓN DE EMPRESAS DCB 2020 C3B1 | R21: 3 | S21: 3 | U21: 26/09/2023 | V21: 01:18:08 p.m. | W21: 001682 | X21: 0010 | Y21: Req Previo | AB21: 667287 | AC21: SOCIAL MEDIA | AG21: C3B1 | AH21: SOCIAL MEDIA | AI21: ADMBF / ADMLO / ADMNE / ADMNI / CONTA / MARKT
A22: SISE | B22: PRGS | C22: ADMNE | D22: ADM2020 | E22: 0005 | F22: 0001 | G22: AEMC3B1 20 | H22: ADM DE EMPRESAS DCB 2020 | I22: 000000849 | J22: AEMC3B1 20 | K22: 4 | L22: 667296 | M22: AMBIENTE Y DESARROLLO(VIRTUAL) | N22: 0050 | O22: ADM EMPRESAS DCB 2020 C3B1 | P22: MT | Q22: ADMINISTRACIÓN DE EMPRESAS DCB 2020 C3B1 | R22: 3 | S22: 3 | U22: 26/09/2023 | V22: 01:18:08 p.m. | W22: 001693 | X22: 0010 | Y22: Req Adic | AD22: 000000242 | AE22: DISEÑO GRÁFICO 2017 C3 B2 | AG22: C3B1 | AH22: NINGUNO | AI22: ADHYR / ADMBF / ADMLO / ADMNE / ADMNI / COMAU / CONTA / DG / DYGMO / FISIO / GASTR / MARKT / PA / REDES / SALUD / SECRE / SWSIS / TECFA
A23: SISE | B23: PRGS | C23: ADMNE | D23: ADM2020 | E23: 0006 | F23: 0001 | G23: AEMC3B2 20 | H23: ADM DE EMPRESAS DCB 2020 | I23: 000000850 | J23: AEMC3B2 20 | K23: 1 | L23: 667297 | M23: FINANZAS BÁSICAS | N23: 0060 | O23: ADM EMPRESAS DCB 2020 C3B2 | P23: MT | Q23: ADMINISTRACIÓN DE EMPRESAS DCB 2020 C3B2 | R23: 3 | S23: 3 | U23: 26/09/2023 | V23: 01:18:08 p.m. | W23: 001686 | X23: 0010 | Y23: Req Previo | AB23: 667281 | AC23: INTRODUCCIÓN AL SISTEMA FINANC | AG23: C3B2 | AH23: INTRODUCCIÓN AL SISTEMA FINANC | AI23: ADMBF / ADMLO / ADMNE / ADMNI / CONTA / MARKT
A24: SISE | B24: PRGS | C24: ADMNE | D24: ADM2020 | E24: 0006 | F24: 0001 | G24: AEMC3B2 20 | H24: ADM DE EMPRESAS DCB 2020 | I24: 000000850 | J24: AEMC3B2 20 | K24: 2 | L24: 667298 | M24: CONTABILIDAD APLICADA | N24: 0060 | O24: ADM EMPRESAS DCB 2020 C3B2 | P24: MT | Q24: ADMINISTRACIÓN DE EMPRESAS DCB 2020 C3B2 | R24: 3 | S24: 3 | U24: 26/09/2023 | V24: 01:18:08 p.m. | W24: 001687 | X24: 0010 | Y24: Req Previo | AB24: 667283 | AC24: COSTOS Y PRESUPUESTOS | AG24: C3B2 | AH24: COSTOS Y PRESUPUESTOS | AI24: ADMBF / ADMLO / ADMNE / ADMNI / CONTA / MARKT
A25: SISE | B25: PRGS | C25: ADMNE | D25: ADM2020 | E25: 0006 | F25: 0001 | G25: AEMC3B2 20 | H25: ADM DE EMPRESAS DCB 2020 | I25: 000000850 | J25: AEMC3B2 20 | K25: 3 | L25: 667299 | M25: PLAN DE NEGOCIOS | N25: 0060 | O25: ADM EMPRESAS DCB 2020 C3B2 | P25: MT | Q25: ADMINISTRACIÓN DE EMPRESAS DCB 2020 C3B2 | R25: 3 | S25: 3 | U25: 26/09/2023 | V25: 01:18:08 p.m. | W25: 001691 | X25: 0020 | Y25: Req Adic | AD25: 000000583 | AE25: ADM NEG INTER EXPONENCIAL C3B2 | AG25: C3B2 | AH25: INNOVACIÓN Y NEGOCIOS | AI25: ADMBF / ADMLO / ADMNE / ADMNI / CONTA / MARKT
A26: SISE | B26: PRGS | C26: ADMNE | D26: ADM2020 | E26: 0006 | F26: 0001 | G26: AEMC3B2 20 | H26: ADM DE EMPRESAS DCB 2020 | I26: 000000850 | J26: AEMC3B2 20 | K26: 4 | L26: 667300 | M26: EMPREND Y RESPONS SOCIAL | N26: 0060 | O26: ADM EMPRESAS DCB 2020 C3B2 | P26: MT | Q26: ADMINISTRACIÓN DE EMPRESAS DCB 2020 C3B2 | R26: 3 | S26: 3 | U26: 26/09/2023 | V26: 01:18:08 p.m. | W26: 001692 | X26: 0010 | Y26: Req Adic | AD26: 000000583 | AE26: ADM NEG INTER EXPONENCIAL C3B2 | AG26: C3B2 | AH26: NINGUNO | AI26: ADMBF / ADMLO / ADMNE / ADMNI / CONTA / MARKT
A27: SISE | B27: PRGS | C27: ADMNE | D27: ADM2020 | E27: 0007 | F27: 0001 | G27: AEMC4B1 20 | H27: ADM DE EMPRESAS DCB 2020 | I27: 000000851 | J27: AEMC4B1 20 | K27: 1 | L27: 9025 | M27: INVESTIGACIÓN DE MERCADOS | N27: 0070 | O27: ADM EMPRESAS DCB 2020 C4B1 | P27: MT | Q27: ADMINISTRACIÓN DE EMPRESAS DCB 2020 C4B1 | R27: 2 | S27: 2 | U27: 26/09/2023 | V27: 01:18:08 p.m. | W27: 001334 | X27: 0010 | Y27: Req Previo | AB27: 667294 | AC27: ESTADÍSTICA APLICADA A LOS NEG | AG27: C4B1 | AH27: ESTADÍSTICA APLICADA A LOS NEG | AI27: ADMNE / ADMNI / MARKT
A28: SISE | B28: PRGS | C28: ADMNE | D28: ADM2020 | E28: 0007 | F28: 0001 | G28: AEMC4B1 20 | H28: ADM DE EMPRESAS DCB 2020 | I28: 000000851 | J28: AEMC4B1 20 | K28: 2 | L28: 9026 | M28: ECONOMÍA PARA LOS NEGOCIOS | N28: 0070 | O28: ADM EMPRESAS DCB 2020 C4B1 | P28: MT | Q28: ADMINISTRACIÓN DE EMPRESAS DCB 2020 C4B1 | R28: 3 | S28: 3 | U28: 26/09/2023 | V28: 01:18:08 p.m. | W28: 001701 | X28: 0010 | Y28: Req Adic | AD28: 000000584 | AE28: ADM NEG INTER EXPONENCIAL C4B1 | AG28: C4B1 | AH28: NINGUNO | AI28: ADMNE / ADMNI / MARKT
A29: SISE | B29: PRGS | C29: ADMNE | D29: ADM2020 | E29: 0007 | F29: 0001 | G29: AEMC4B1 20 | H29: ADM DE EMPRESAS DCB 2020 | I29: 000000851 | J29: AEMC4B1 20 | K29: 3 | L29: 9027 | M29: CONTABILIDAD DE COSTOS | N29: 0070 | O29: ADM EMPRESAS DCB 2020 C4B1 | P29: MT | Q29: ADMINISTRACIÓN DE EMPRESAS DCB 2020 C4B1 | R29: 2 | S29: 2 | U29: 26/09/2023 | V29: 01:18:08 p.m. | W29: 001701 | X29: 0010 | Y29: Req Adic | AD29: 000000584 | AE29: ADM NEG INTER EXPONENCIAL C4B1 | AG29: C4B1 | AH29: NINGUNO | AI29: ADMNE / ADMNI / MARKT
A30: SISE | B30: PRGS | C30: ADMNE | D30: ADM2020 | E30: 0008 | F30: 0001 | G30: AEMC4B2 20 | H30: ADM DE EMPRESAS DCB 2020 | I30: 000000852 | J30: AEMC4B2 20 | K30: 1 | L30: 9029 | M30: E-COMMERCE | N30: 0080 | O30: ADM EMPRESAS DCB 2020 C4B2 | P30: MT | Q30: ADMINISTRACIÓN DE EMPRESAS DCB 2020 C4B2 | R30: 2 | S30: 2 | U30: 26/09/2023 | V30: 01:18:08 p.m. | W30: 001335 | X30: 0010 | Y30: Req Previo | AB30: 009010 | AC30: COMERCIO INTERNACIONAL | AG30: C4B2 | AH30: COMERCIO INTERNACIONAL | AI30: ADMNE / ADMNI / MARKT
A31: SISE | B31: PRGS | C31: ADMNE | D31: ADM2020 | E31: 0008 | F31: 0001 | G31: AEMC4B2 20 | H31: ADM DE EMPRESAS DCB 2020 | I31: 000000852 | J31: AEMC4B2 20 | K31: 2 | L31: 9030 | M31: MARKETING DIGITAL | N31: 0080 | O31: ADM EMPRESAS DCB 2020 C4B2 | P31: MT | Q31: ADMINISTRACIÓN DE EMPRESAS DCB 2020 C4B2 | R31: 2 | S31: 2 | U31: 26/09/2023 | V31: 01:18:08 p.m. | W31: 001336 | X31: 0010 | Y31: Req Previo | AB31: 667295 | AC31: GESTIÓN DE CLIENTES - CRM | AG31: C4B2 | AH31: GESTIÓN DE CLIENTES - CRM | AI31: ADMNE / ADMNI / MARKT
A32: SISE | B32: PRGS | C32: ADMNE | D32: ADM2020 | E32: 0008 | F32: 0001 | G32: AEMC4B2 20 | H32: ADM DE EMPRESAS DCB 2020 | I32: 000000852 | J32: AEMC4B2 20 | K32: 3 | L32: 9031 | M32: GESTIÓN ESTRATÉGICA | N32: 0080 | O32: ADM EMPRESAS DCB 2020 C4B2 | P32: MT | Q32: ADMINISTRACIÓN DE EMPRESAS DCB 2020 C4B2 | R32: 2 | S32: 2 | U32: 26/09/2023 | V32: 01:18:08 p.m. | W32: 001720 | X32: 0010 | Y32: Req Adic | AD32: 000000585 | AE32: ADM NEG INTER EXPONENCIAL C4B2 | AG32: C4B2 | AH32: NINGUNO | AI32: ADMNE / MARKT
A33: SISE | B33: PRGS | C33: ADMNE | D33: ADM2020 | E33: 0008 | F33: 0001 | G33: AEMC4B2 20 | H33: ADM DE EMPRESAS DCB 2020 | I33: 000000852 | J33: AEMC4B2 20 | K33: 4 | L33: 9032 | M33: EXPE FORMA INTERME (MKT PER) | N33: 0080 | O33: ADM EMPRESAS DCB 2020 C4B2 | P33: MT | Q33: ADMINISTRACIÓN DE EMPRESAS DCB 2020 C4B2 | R33: 4 | S33: 4 | U33: 26/09/2023 | V33: 01:18:08 p.m. | W33: 001193 | X33: 0010 | Y33: Req Previo | AB33: 667288 | AC33: EXP FORMA BÁSICAS (HERR INFOR) | AG33: C4B2 | AH33: EXP FORMA BÁSICAS (HERR INFOR) | AI33: ADMLO / ADMNE / ADMNI / MARKT
A34: SISE | B34: PRGS | C34: ADMNE | D34: ADM2020 | E34: 0009 | F34: 0001 | G34: AEMC5B1 20 | H34: ADM DE EMPRESAS DCB 2020 | I34: 000000853 | J34: AEMC5B1 20 | K34: 1 | L34: 9033 | M34: LEGISLACIÓN LABORAL | N34: 0090 | O34: ADM EMPRESAS DCB 2020 C5B1 | P34: MT | Q34: ADMINISTRACIÓN DE EMPRESAS DCB 2020 C5B1 | R34: 3 | S34: 3 | U34: 26/09/2023 | V34: 01:18:08 p.m. | W34: 001337 | X34: 0010 | Y34: Req Previo | AB34: 667285 | AC34: LEG COMERCIAL Y TRIBUTARIA | AG34: C5B1 | AH34: LEG COMERCIAL Y TRIBUTARIA | AI34: ADMNE
A35: SISE | B35: PRGS | C35: ADMNE | D35: ADM2020 | E35: 0009 | F35: 0001 | G35: AEMC5B1 20 | H35: ADM DE EMPRESAS DCB 2020 | I35: 000000853 | J35: AEMC5B1 20 | K35: 2 | L35: 9034 | M35: GESTIÓN DE PYMES | N35: 0090 | O35: ADM EMPRESAS DCB 2020 C5B1 | P35: MT | Q35: ADMINISTRACIÓN DE EMPRESAS DCB 2020 C5B1 | R35: 3 | S35: 3 | U35: 26/09/2023 | V35: 01:18:08 p.m. | W35: 001736 | X35: 0010 | Y35: Req Adic | AD35: 000000606 | AE35: ADM EMPRESAS EXPONENCIAL C5B1 | AG35: C5B1 | AH35: NINGUNO | AI35: ADMNE
A36: SISE | B36: PRGS | C36: ADMNE | D36: ADM2020 | E36: 0009 | F36: 0001 | G36: AEMC5B1 20 | H36: ADM DE EMPRESAS DCB 2020 | I36: 000000853 | J36: AEMC5B1 20 | K36: 3 | L36: 9035 | M36: GEST LOGIST Y DE OPERACIONES | N36: 0090 | O36: ADM EMPRESAS DCB 2020 C5B1 | P36: MT | Q36: ADMINISTRACIÓN DE EMPRESAS DCB 2020 C5B1 | R36: 3 | S36: 3 | U36: 26/09/2023 | V36: 01:18:08 p.m. | W36: 001736 | X36: 0010 | Y36: Req Adic | AD36: 000000606 | AE36: ADM EMPRESAS EXPONENCIAL C5B1 | AG36: C5B1 | AH36: NINGUNO | AI36: ADMNE
A37: SISE | B37: PRGS | C37: ADMNE | D37: ADM2020 | E37: 0010 | F37: 0001 | G37: AEMC5B2 20 | H37: ADM DE EMPRESAS DCB 2020 | I37: 000000854 | J37: AEMC5B2 20 | K37: 1 | L37: 9036 | M37: GES DE TE Y DEL CAP DE TRABAJO | N37: 0100 | O37: ADM EMPRESAS DCB 2020 C5B2 | P37: MT | Q37: ADMINISTRACIÓN DE EMPRESAS DCB 2020 C5B2 | R37: 2 | S37: 2 | U37: 26/09/2023 | V37: 01:18:08 p.m. | W37: 001338 | X37: 0010 | Y37: Req Previo | AB37: 667297 | AC37: FINANZAS BÁSICAS | AG37: C5B2 | AH37: FINANZAS BÁSICAS | AI37: ADMNE
A38: SISE | B38: PRGS | C38: ADMNE | D38: ADM2020 | E38: 0010 | F38: 0001 | G38: AEMC5B2 20 | H38: ADM DE EMPRESAS DCB 2020 | I38: 000000854 | J38: AEMC5B2 20 | K38: 2 | L38: 9037 | M38: GESTIÓN DEL TALENTO HUMANO | N38: 0100 | O38: ADM EMPRESAS DCB 2020 C5B2 | P38: MT | Q38: ADMINISTRACIÓN DE EMPRESAS DCB 2020 C5B2 | R38: 3 | S38: 3 | U38: 26/09/2023 | V38: 01:18:08 p.m. | W38: 001743 | X38: 0010 | Y38: Req Adic | AD38: 000000607 | AE38: ADM EMPRESAS EXPONENCIAL C5B2 | AG38: C5B2 | AH38: NINGUNO | AI38: ADMNE
A39: SISE | B39: PRGS | C39: ADMNE | D39: ADM2020 | E39: 0010 | F39: 0001 | G39: AEMC5B2 20 | H39: ADM DE EMPRESAS DCB 2020 | I39: 000000854 | J39: AEMC5B2 20 | K39: 3 | L39: 9038 | M39: ADMINISTRACIÓN PÚBLICA | N39: 0100 | O39: ADM EMPRESAS DCB 2020 C5B2 | P39: MT | Q39: ADMINISTRACIÓN DE EMPRESAS DCB 2020 C5B2 | R39: 3 | S39: 3 | U39: 26/09/2023 | V39: 01:18:08 p.m. | W39: 001743 | X39: 0010 | Y39: Req Adic | AD39: 000000607 | AE39: ADM EMPRESAS EXPONENCIAL C5B2 | AG39: C5B2 | AH39: NINGUNO | AI39: ADMNE
A40: SISE | B40: PRGS | C40: ADMNE | D40: ADM2020 | E40: 0010 | F40: 0001 | G40: AEMC5B2 20 | H40: ADM DE EMPRESAS DCB 2020 | I40: 000000854 | J40: AEMC5B2 20 | K40: 4 | L40: 5437 | M40: INNOVACION TECNOLOGIC(VIRTUAL) | N40: 0100 | O40: ADM EMPRESAS DCB 2020 C5B2 | P40: MT | Q40: ADMINISTRACIÓN DE EMPRESAS DCB 2020 C5B2 | R40: 2 | S40: 2 | U40: 26/09/2023 | V40: 01:18:08 p.m. | W40: 001744 | X40: 0010 | Y40: Req Adic | AD40: 000000587 | AE40: ADM NEG INTER EXPONENCIAL C5B2 | AG40: C5B2 | AH40: NINGUNO | AI40: ADMLO / ADMNE / ADMNI / MARKT
A41: SISE | B41: PRGS | C41: ADMNE | D41: ADM2020 | E41: 0011 | F41: 0001 | G41: AEMC6B1 20 | H41: ADM DE EMPRESAS DCB 2020 | I41: 000000855 | J41: AEMC6B1 20 | K41: 1 | L41: 9040 | M41: ANALISIS E INTERPRE DE EEFF | N41: 0110 | O41: ADM EMPRESAS DCB 2020 C6B1 | P41: MT | Q41: ADMINISTRACIÓN DE EMPRESAS DCB 2020 C6B1 | R41: 2 | S41: 2 | U41: 26/09/2023 | V41: 01:18:08 p.m. | W41: 001339 | X41: 0010 | Y41: Req Previo | AB41: 009036 | AC41: GES DE TE Y DEL CAP DE TRABAJO | AG41: C6B1 | AH41: GES DE TE Y DEL CAP DE TRABAJO | AI41: ADMNE
A42: SISE | B42: PRGS | C42: ADMNE | D42: ADM2020 | E42: 0011 | F42: 0001 | G42: AEMC6B1 20 | H42: ADM DE EMPRESAS DCB 2020 | I42: 000000855 | J42: AEMC6B1 20 | K42: 2 | L42: 9041 | M42: PSI DEL COMPOR ORGANIZACIONAL | N42: 0110 | O42: ADM EMPRESAS DCB 2020 C6B1 | P42: MT | Q42: ADMINISTRACIÓN DE EMPRESAS DCB 2020 C6B1 | R42: 3 | S42: 3 | U42: 26/09/2023 | V42: 01:18:08 p.m. | W42: 001340 | X42: 0010 | Y42: Req Previo | AB42: 009037 | AC42: GESTIÓN DEL TALENTO HUMANO | AG42: C6B1 | AH42: GESTIÓN DEL TALENTO HUMANO | AI42: ADMNE
A43: SISE | B43: PRGS | C43: ADMNE | D43: ADM2020 | E43: 0011 | F43: 0001 | G43: AEMC6B1 20 | H43: ADM DE EMPRESAS DCB 2020 | I43: 000000855 | J43: AEMC6B1 20 | K43: 3 | L43: 9042 | M43: GESTIÓN DE LA CALIDAD | N43: 0110 | O43: ADM EMPRESAS DCB 2020 C6B1 | P43: MT | Q43: ADMINISTRACIÓN DE EMPRESAS DCB 2020 C6B1 | R43: 2 | S43: 2 | U43: 26/09/2023 | V43: 01:18:08 p.m. | W43: 002129 | X43: 0010 | Y43: Req Adic | AD43: 000000608 | AE43: ADM EMPRESAS EXPONENCIAL C6B1 | AG43: C6B1 | AH43: NINGUNO | AI43: ADMNE
A44: SISE | B44: PRGS | C44: ADMNE | D44: ADM2020 | E44: 0011 | F44: 0001 | G44: AEMC6B1 20 | H44: ADM DE EMPRESAS DCB 2020 | I44: 000000855 | J44: AEMC6B1 20 | K44: 4 | L44: 5441 | M44: DIS DES PROY PROD INN(VIRTUAL) | N44: 0110 | O44: ADM EMPRESAS DCB 2020 C6B1 | P44: MT | Q44: ADMINISTRACIÓN DE EMPRESAS DCB 2020 C6B1 | R44: 2 | S44: 2 | U44: 26/09/2023 | V44: 01:18:08 p.m. | W44: 001794 | X44: 0010 | Y44: Req Adic | AD44: 000000393 | AE44: ADM NEG INTER 2017 C6B1 | AG44: C6B1 | AH44: NINGUNO | AI44: ADMLO / ADMNE / ADMNI / MARKT
A45: SISE | B45: PRGS | C45: ADMNE | D45: ADM2020 | E45: 0012 | F45: 0001 | G45: AEMC6B2 20 | H45: ADM DE EMPRESAS DCB 2020 | I45: 000000856 | J45: AEMC6B2 20 | K45: 1 | L45: 9044 | M45: AUDITORÍA ADMINISTRATIVA | N45: 0120 | O45: ADM EMPRESAS DCB 2020 C6B2 | P45: MT | Q45: ADMINISTRACIÓN DE EMPRESAS DCB 2020 C6B2 | R45: 2 | S45: 2 | U45: 26/09/2023 | V45: 01:18:08 p.m. | W45: 002141 | X45: 0010 | Y45: Req Adic | AD45: 000000609 | AE45: ADM EMPRESAS EXPONENCIAL C6B2 | AG45: C6B2 | AH45: NINGUNO | AI45: ADMNE
A46: SISE | B46: PRGS | C46: ADMNE | D46: ADM2020 | E46: 0012 | F46: 0001 | G46: AEMC6B2 20 | H46: ADM DE EMPRESAS DCB 2020 | I46: 000000856 | J46: AEMC6B2 20 | K46: 2 | L46: 9045 | M46: GESTIÓN DE PROCESOS | N46: 0120 | O46: ADM EMPRESAS DCB 2020 C6B2 | P46: MT | Q46: ADMINISTRACIÓN DE EMPRESAS DCB 2020 C6B2 | R46: 2 | S46: 2 | U46: 26/09/2023 | V46: 01:18:08 p.m. | W46: 001341 | X46: 0010 | Y46: Req Previo | AB46: 009035 | AC46: GEST LOGIST Y DE OPERACIONES | AG46: C6B2 | AH46: GEST LOGIST Y DE OPERACIONES | AI46: ADMNE
A47: SISE | B47: PRGS | C47: ADMNE | D47: ADM2020 | E47: 0012 | F47: 0001 | G47: AEMC6B2 20 | H47: ADM DE EMPRESAS DCB 2020 | I47: 000000856 | J47: AEMC6B2 20 | K47: 3 | L47: 9046 | M47: ADMI DE LA PRODUCCION | N47: 0120 | O47: ADM EMPRESAS DCB 2020 C6B2 | P47: MT | Q47: ADMINISTRACIÓN DE EMPRESAS DCB 2020 C6B2 | R47: 3 | S47: 3 | U47: 26/09/2023 | V47: 01:18:08 p.m. | W47: 002141 | X47: 0010 | Y47: Req Adic | AD47: 000000609 | AE47: ADM EMPRESAS EXPONENCIAL C6B2 | AG47: C6B2 | AH47: NINGUNO | AI47: ADMNE
A48: SISE | B48: PRGS | C48: ADMNE | D48: ADM2020 | E48: 0012 | F48: 0001 | G48: AEMC6B2 20 | H48: ADM DE EMPRESAS DCB 2020 | I48: 000000856 | J48: AEMC6B2 20 | K48: 4 | L48: 9047 | M48: EXPE FORMATIVAS ESPECIALIZADAS | N48: 0120 | O48: ADM EMPRESAS DCB 2020 C6B2 | P48: MT | Q48: ADMINISTRACIÓN DE EMPRESAS DCB 2020 C6B2 | R48: 4 | S48: 4 | U48: 26/09/2023 | V48: 01:18:08 p.m. | W48: 001267 | X48: 0010 | Y48: Req Previo | AB48: 009032 | AC48: EXPE FORMA INTERME (MKT PER) | AG48: C6B2 | AH48: EXPE FORMA INTERME (MKT PER) | AI48: ADMLO / ADMNE / ADMNI / MARKT
A49: SISE | B49: PRGS | C49: ADMNI | D49: NNII2020 | E49: 0001 | F49: 0001 | G49: ANEC1B1 20 | H49: ADM NEG INTER DCB 2020 | I49: 000000857 | J49: ANEC1B1 20 | K49: 1 | L49: 667275 | M49: ADMINISTRACIÓN GENERAL | N49: 0010 | O49: ADM NEG INTER DCB 2020 C1B1 | P49: MT | Q49: ADMINISTRACIÓN DE NEGOCIOS INTERNACIONALES DCB 2020 C1B1 | R49: 3 | S49: 3 | U49: 26/09/2023 | V49: 02:57:38 p.m. | W49: 001637 | X49: 0010 | Y49: Req Adic | AD49: 000000785 | AE49: ADM BANC DCB 2020 C1B1 | AG49: C1B1 | AH49: NINGUNO | AI49: ADMBF / ADMLO / ADMNE / ADMNI / CONTA / MARKT
A50: SISE | B50: PRGS | C50: ADMNI | D50: NNII2020 | E50: 0001 | F50: 0001 | G50: ANEC1B1 20 | H50: ADM NEG INTER DCB 2020 | I50: 000000857 | J50: ANEC1B1 20 | K50: 2 | L50: 667276 | M50: FUNDAMENTOS DE MARKETING | N50: 0010 | O50: ADM NEG INTER DCB 2020 C1B1 | P50: MT | Q50: ADMINISTRACIÓN DE NEGOCIOS INTERNACIONALES DCB 2020 C1B1 | R50: 2 | S50: 2 | U50: 26/09/2023 | V50: 02:57:38 p.m. | W50: 001637 | X50: 0010 | Y50: Req Adic | AD50: 000000785 | AE50: ADM BANC DCB 2020 C1B1 | AG50: C1B1 | AH50: NINGUNO | AI50: ADMBF / ADMLO / ADMNE / ADMNI / CONTA / MARKT
A51: SISE | B51: PRGS | C51: ADMNI | D51: NNII2020 | E51: 0001 | F51: 0001 | G51: ANEC1B1 20 | H51: ADM NEG INTER DCB 2020 | I51: 000000857 | J51: ANEC1B1 20 | K51: 3 | L51: 667277 | M51: CONTABILIDAD BÁSICA | N51: 0010 | O51: ADM NEG INTER DCB 2020 C1B1 | P51: MT | Q51: ADMINISTRACIÓN DE NEGOCIOS INTERNACIONALES DCB 2020 C1B1 | R51: 4 | S51: 4 | U51: 26/09/2023 | V51: 02:57:38 p.m. | W51: 001637 | X51: 0010 | Y51: Req Adic | AD51: 000000785 | AE51: ADM BANC DCB 2020 C1B1 | AG51: C1B1 | AH51: NINGUNO | AI51: ADMBF / ADMNE / ADMNI / CONTA / MARKT
A52: SISE | B52: PRGS | C52: ADMNI | D52: NNII2020 | E52: 0001 | F52: 0001 | G52: ANEC1B1 20 | H52: ADM NEG INTER DCB 2020 | I52: 000000857 | J52: ANEC1B1 20 | K52: 4 | L52: 667278 | M52: COMUNICACIÓN EFECTIVA | N52: 0010 | O52: ADM NEG INTER DCB 2020 C1B1 | P52: MT | Q52: ADMINISTRACIÓN DE NEGOCIOS INTERNACIONALES DCB 2020 C1B1 | R52: 2 | S52: 2 | U52: 26/09/2023 | V52: 02:57:38 p.m. | W52: 001635 | X52: 0010 | Y52: Req Adic | AD52: 000000773 | AE52: DIS GRAFICO DCB 2020 C1B1 | AG52: C1B1 | AH52: NINGUNO | AI52: ADHYR / ADMBF / ADMLO / ADMNE / ADMNI / COMAU / CONTA / DG / DYGMO / FISIO / GASTR / MARKT / PA / REDES / SALUD / SECRE / SWSIS / TECFA
A53: SISE | B53: PRGS | C53: ADMNI | D53: NNII2020 | E53: 0002 | F53: 0001 | G53: ANEC1B2 20 | H53: ADM NEG INTER DCB 2020 | I53: 000000858 | J53: ANEC1B2 20 | K53: 1 | L53: 667281 | M53: INTRODUCCIÓN AL SISTEMA FINANC | N53: 0020 | O53: ADM NEG INTER DCB 2020 C1B2 | P53: MT | Q53: ADMINISTRACIÓN DE NEGOCIOS INTERNACIONALES DCB 2020 C1B2 | R53: 2 | S53: 2 | U53: 26/09/2023 | V53: 02:57:38 p.m. | W53: 001622 | X53: 0010 | Y53: Req Adic | AD53: 000000822 | AE53: ADM EMPRESAS DCB 2020 C1B2 | AG53: C1B2 | AH53: NINGUNO | AI53: ADMBF / ADMNE / ADMNI / CONTA / MARKT
A54: SISE | B54: PRGS | C54: ADMNI | D54: NNII2020 | E54: 0002 | F54: 0001 | G54: ANEC1B2 20 | H54: ADM NEG INTER DCB 2020 | I54: 000000858 | J54: ANEC1B2 20 | K54: 2 | L54: 667279 | M54: EXCEL PARA LOS NEGOCIOS | N54: 0020 | O54: ADM NEG INTER DCB 2020 C1B2 | P54: MT | Q54: ADMINISTRACIÓN DE NEGOCIOS INTERNACIONALES DCB 2020 C1B2 | R54: 2 | S54: 2 | U54: 26/09/2023 | V54: 02:57:38 p.m. | W54: 001622 | X54: 0010 | Y54: Req Adic | AD54: 000000822 | AE54: ADM EMPRESAS DCB 2020 C1B2 | AG54: C1B2 | AH54: NINGUNO | AI54: ADMBF / ADMLO / ADMNE / ADMNI / CONTA / MARKT
A55: SISE | B55: PRGS | C55: ADMNI | D55: NNII2020 | E55: 0002 | F55: 0001 | G55: ANEC1B2 20 | H55: ADM NEG INTER DCB 2020 | I55: 000000858 | J55: ANEC1B2 20 | K55: 3 | L55: 667280 | M55: TÉCNICAS DE VENTAS | N55: 0020 | O55: ADM NEG INTER DCB 2020 C1B2 | P55: MT | Q55: ADMINISTRACIÓN DE NEGOCIOS INTERNACIONALES DCB 2020 C1B2 | R55: 2 | S55: 2 | U55: 26/09/2023 | V55: 02:57:38 p.m. | W55: 001622 | X55: 0010 | Y55: Req Adic | AD55: 000000822 | AE55: ADM EMPRESAS DCB 2020 C1B2 | AG55: C1B2 | AH55: NINGUNO | AI55: ADMBF / ADMLO / ADMNE / ADMNI / CONTA / MARKT
A56: SISE | B56: PRGS | C56: ADMNI | D56: NNII2020 | E56: 0002 | F56: 0001 | G56: ANEC1B2 20 | H56: ADM NEG INTER DCB 2020 | I56: 000000858 | J56: ANEC1B2 20 | K56: 4 | L56: 667353 | M56: LIDERAZGO Y TRABAJO EN EQUIPO | N56: 0020 | O56: ADM NEG INTER DCB 2020 C1B2 | P56: MT | Q56: ADMINISTRACIÓN DE NEGOCIOS INTERNACIONALES DCB 2020 C1B2 | R56: 3 | S56: 3 | U56: 26/09/2023 | V56: 02:57:38 p.m. | W56: 001623 | X56: 0010 | Y56: Req Adic | AD56: 000000786 | AE56: ADM BANC DCB 2020 C1B2 | AG56: C1B2 | AH56: NINGUNO | AI56: ADHYR / ADMBF / ADMLO / ADMNE / ADMNI / COMAU / CONTA / DG / DYGMO / FISIO / GASTR / MARKT / PA / REDES / SALUD / SECRE / SWSIS / TECFA
A57: SISE | B57: PRGS | C57: ADMNI | D57: NNII2020 | E57: 0002 | F57: 0001 | G57: ANEC1B2 20 | H57: ADM NEG INTER DCB 2020 | I57: 000000858 | J57: ANEC1B2 20 | K57: 5 | L57: 667282 | M57: EDUCACIÓN FINANCIERA (V) | N57: 0020 | O57: ADM NEG INTER DCB 2020 C1B2 | P57: MT | Q57: ADMINISTRACIÓN DE NEGOCIOS INTERNACIONALES DCB 2020 C1B2 | R57: 3 | S57: 3 | U57: 26/09/2023 | V57: 02:57:38 p.m. | W57: 001624 | X57: 0010 | Y57: Req Adic | AD57: 000000786 | AE57: ADM BANC DCB 2020 C1B2 | AG57: C1B2 | AH57: NINGUNO | AI57: ADHYR / ADMBF / ADMLO / ADMNE / ADMNI / COMAU / CONTA / DG / DYGMO / GASTR / MARKT / PA / REDES / SECRE / SWSIS
A58: SISE | B58: PRGS | C58: ADMNI | D58: NNII2020 | E58: 0003 | F58: 0001 | G58: ANEC2B1 20 | H58: ADM NEG INTER DCB 2020 | I58: 000000859 | J58: ANEC2B1 20 | K58: 1 | L58: 667283 | M58: COSTOS Y PRESUPUESTOS | N58: 0030 | O58: ADM NEG INTER DCB 2020 C2B1 | P58: MT | Q58: ADMINISTRACIÓN DE NEGOCIOS INTERNACIONALES DCB 2020 C2B1 | R58: 2 | S58: 2 | U58: 26/09/2023 | V58: 02:57:38 p.m. | W58: 000388 | X58: 0010 | Y58: Req Previo | AB58: 667277 | AC58: CONTABILIDAD BÁSICA | AG58: C2B1 | AH58: CONTABILIDAD BÁSICA | AI58: ADMBF / ADMLO / ADMNE / ADMNI / CONTA / MARKT
A59: SISE | B59: PRGS | C59: ADMNI | D59: NNII2020 | E59: 0003 | F59: 0001 | G59: ANEC2B1 20 | H59: ADM NEG INTER DCB 2020 | I59: 000000859 | J59: ANEC2B1 20 | K59: 2 | L59: 667541 | M59: ÉTICA Y CIUDADANÍA | N59: 0030 | O59: ADM NEG INTER DCB 2020 C2B1 | P59: MT | Q59: ADMINISTRACIÓN DE NEGOCIOS INTERNACIONALES DCB 2020 C2B1 | R59: 2 | S59: 2 | U59: 26/09/2023 | V59: 02:57:38 p.m. | W59: 001636 | X59: 0010 | Y59: Req Adic | AD59: 000000775 | AE59: DIS GRAFICO DCB 2020 C2B1 | AG59: C2B1 | AH59: NINGUNO | AI59: ADHYR / ADMBF / ADMLO / ADMNE / ADMNI / COMAU / CONTA / DG / DYGMO / FISIO / MARKT / PA / REDES / SALUD / SECRE / SWSIS / TECFA
A60: SISE | B60: PRGS | C60: ADMNI | D60: NNII2020 | E60: 0003 | F60: 0001 | G60: ANEC2B1 20 | H60: ADM NEG INTER DCB 2020 | I60: 000000859 | J60: ANEC2B1 20 | K60: 3 | L60: 9010 | M60: COMERCIO INTERNACIONAL | N60: 0030 | O60: ADM NEG INTER DCB 2020 C2B1 | P60: MT | Q60: ADMINISTRACIÓN DE NEGOCIOS INTERNACIONALES DCB 2020 C2B1 | R60: 2 | S60: 2 | U60: 26/09/2023 | V60: 02:57:38 p.m. | W60: 001332 | X60: 0010 | Y60: Req Previo | AB60: 667280 | AC60: TÉCNICAS DE VENTAS | AG60: C2B1 | AH60: TÉCNICAS DE VENTAS | AI60: ADMNE / ADMNI / MARKT
A61: SISE | B61: PRGS | C61: ADMNI | D61: NNII2020 | E61: 0003 | F61: 0001 | G61: ANEC2B1 20 | H61: ADM NEG INTER DCB 2020 | I61: 000000859 | J61: ANEC2B1 20 | K61: 4 | L61: 9011 | M61: INNOVACIÓN Y NEGOCIOS | N61: 0030 | O61: ADM NEG INTER DCB 2020 C2B1 | P61: MT | Q61: ADMINISTRACIÓN DE NEGOCIOS INTERNACIONALES DCB 2020 C2B1 | R61: 2 | S61: 2 | U61: 26/09/2023 | V61: 02:57:38 p.m. | W61: 001655 | X61: 0030 | Y61: Req Adic | AD61: 000000811 | AE61: ADM LOGISTICA DCB 2020 C2B1 | AG61: C2B1 | AH61: NINGUNO | AI61: ADMLO / ADMNE / ADMNI / MARKT
A62: SISE | B62: PRGS | C62: ADMNI | D62: NNII2020 | E62: 0004 | F62: 0001 | G62: ANEC2B2 20 | H62: ADM NEG INTER DCB 2020 | I62: 000000860 | J62: ANEC2B2 20 | K62: 1 | L62: 667285 | M62: LEG COMERCIAL Y TRIBUTARIA | N62: 0040 | O62: ADM NEG INTER DCB 2020 C2B2 | P62: MT | Q62: ADMINISTRACIÓN DE NEGOCIOS INTERNACIONALES DCB 2020 C2B2 | R62: 2 | S62: 2 | U62: 26/09/2023 | V62: 02:57:38 p.m. | W62: 001661 | X62: 0030 | Y62: Req Adic | AD62: 000000788 | AE62: ADM BANC DCB 2020 C2B2 | AG62: C2B2 | AH62: NINGUNO | AI62: ADMBF / ADMLO / ADMNE / ADMNI / CONTA / MARKT
A63: SISE | B63: PRGS | C63: ADMNI | D63: NNII2020 | E63: 0004 | F63: 0001 | G63: ANEC2B2 20 | H63: ADM NEG INTER DCB 2020 | I63: 000000860 | J63: ANEC2B2 20 | K63: 2 | L63: 667286 | M63: MATEMÁTICA COMERCIAL | N63: 0040 | O63: ADM NEG INTER DCB 2020 C2B2 | P63: MT | Q63: ADMINISTRACIÓN DE NEGOCIOS INTERNACIONALES DCB 2020 C2B2 | R63: 2 | S63: 2 | U63: 26/09/2023 | V63: 02:57:38 p.m. | W63: 001669 | X63: 0030 | Y63: Req Adic | AD63: 000000812 | AE63: ADM LOGISTICA DCB 2020 C2B2 | AG63: C2B2 | AH63: NINGUNO | AI63: ADMNE / ADMNI / MARKT
A64: SISE | B64: PRGS | C64: ADMNI | D64: NNII2020 | E64: 0004 | F64: 0001 | G64: ANEC2B2 20 | H64: ADM NEG INTER DCB 2020 | I64: 000000860 | J64: ANEC2B2 20 | K64: 3 | L64: 667287 | M64: SOCIAL MEDIA | N64: 0040 | O64: ADM NEG INTER DCB 2020 C2B2 | P64: MT | Q64: ADMINISTRACIÓN DE NEGOCIOS INTERNACIONALES DCB 2020 C2B2 | R64: 2 | S64: 2 | U64: 26/09/2023 | V64: 02:57:38 p.m. | W64: 001663 | X64: 0010 | Y64: Req Previo | AB64: 667276 | AC64: FUNDAMENTOS DE MARKETING | AG64: C2B2 | AH64: FUNDAMENTOS DE MARKETING | AI64: ADMLO / ADMNE / ADMNI / MARKT
A65: SISE | B65: PRGS | C65: ADMNI | D65: NNII2020 | E65: 0004 | F65: 0001 | G65: ANEC2B2 20 | H65: ADM NEG INTER DCB 2020 | I65: 000000860 | J65: ANEC2B2 20 | K65: 4 | L65: 667288 | M65: EXP FORMA BÁSICAS (HERR INFOR) | N65: 0040 | O65: ADM NEG INTER DCB 2020 C2B2 | P65: MT | Q65: ADMINISTRACIÓN DE NEGOCIOS INTERNACIONALES DCB 2020 C2B2 | R65: 4 | S65: 4 | U65: 26/09/2023 | V65: 02:57:38 p.m. | W65: 001661 | X65: 0030 | Y65: Req Adic | AD65: 000000788 | AE65: ADM BANC DCB 2020 C2B2 | AG65: C2B2 | AH65: NINGUNO | AI65: ADMBF / ADMLO / ADMNE / ADMNI / CONTA / MARKT
A66: SISE | B66: PRGS | C66: ADMNI | D66: NNII2020 | E66: 0005 | F66: 0001 | G66: ANEC3B1 20 | H66: ADM NEG INTER DCB 2020 | I66: 000000861 | J66: ANEC3B1 20 | K66: 1 | L66: 667293 | M66: MATEMÁTICA FINANCIERA | N66: 0050 | O66: ADM NEG INTER DCB 2020 C3B1 | P66: MT | Q66: ADMINISTRACIÓN DE NEGOCIOS INTERNACIONALES DCB 2020 C3B1 | R66: 3 | S66: 3 | U66: 26/09/2023 | V66: 02:57:38 p.m. | W66: 001676 | X66: 0010 | Y66: Req Previo | AB66: 667286 | AC66: MATEMÁTICA COMERCIAL | AG66: C3B1 | AH66: MATEMÁTICA COMERCIAL | AI66: ADMBF / ADMNE / ADMNI / CONTA / MARKT
A67: SISE | B67: PRGS | C67: ADMNI | D67: NNII2020 | E67: 0005 | F67: 0001 | G67: ANEC3B1 20 | H67: ADM NEG INTER DCB 2020 | I67: 000000861 | J67: ANEC3B1 20 | K67: 2 | L67: 667294 | M67: ESTADÍSTICA APLICADA A LOS NEG | N67: 0050 | O67: ADM NEG INTER DCB 2020 C3B1 | P67: MT | Q67: ADMINISTRACIÓN DE NEGOCIOS INTERNACIONALES DCB 2020 C3B1 | R67: 3 | S67: 3 | U67: 26/09/2023 | V67: 02:57:38 p.m. | W67: 001678 | X67: 0010 | Y67: Req Previo | AB67: 667279 | AC67: EXCEL PARA LOS NEGOCIOS | AG67: C3B1 | AH67: EXCEL PARA LOS NEGOCIOS | AI67: ADMBF / ADMLO / ADMNE / ADMNI / CONTA / MARKT
A68: SISE | B68: PRGS | C68: ADMNI | D68: NNII2020 | E68: 0005 | F68: 0001 | G68: ANEC3B1 20 | H68: ADM NEG INTER DCB 2020 | I68: 000000861 | J68: ANEC3B1 20 | K68: 3 | L68: 667295 | M68: GESTIÓN DE CLIENTES - CRM | N68: 0050 | O68: ADM NEG INTER DCB 2020 C3B1 | P68: MT | Q68: ADMINISTRACIÓN DE NEGOCIOS INTERNACIONALES DCB 2020 C3B1 | R68: 3 | S68: 3 | U68: 26/09/2023 | V68: 02:57:38 p.m. | W68: 001682 | X68: 0010 | Y68: Req Previo | AB68: 667287 | AC68: SOCIAL MEDIA | AG68: C3B1 | AH68: SOCIAL MEDIA | AI68: ADMBF / ADMLO / ADMNE / ADMNI / CONTA / MARKT
A69: SISE | B69: PRGS | C69: ADMNI | D69: NNII2020 | E69: 0005 | F69: 0001 | G69: ANEC3B1 20 | H69: ADM NEG INTER DCB 2020 | I69: 000000861 | J69: ANEC3B1 20 | K69: 4 | L69: 667296 | M69: AMBIENTE Y DESARROLLO(VIRTUAL) | N69: 0050 | O69: ADM NEG INTER DCB 2020 C3B1 | P69: MT | Q69: ADMINISTRACIÓN DE NEGOCIOS INTERNACIONALES DCB 2020 C3B1 | R69: 3 | S69: 3 | U69: 26/09/2023 | V69: 02:57:38 p.m. | W69: 001693 | X69: 0010 | Y69: Req Adic | AD69: 000000242 | AE69: DISEÑO GRÁFICO 2017 C3 B2 | AG69: C3B1 | AH69: NINGUNO | AI69: ADHYR / ADMBF / ADMLO / ADMNE / ADMNI / COMAU / CONTA / DG / DYGMO / FISIO / GASTR / MARKT / PA / REDES / SALUD / SECRE / SWSIS / TECFA
A70: SISE | B70: PRGS | C70: ADMNI | D70: NNII2020 | E70: 0006 | F70: 0001 | G70: ANEC3B2 20 | H70: ADM NEG INTER DCB 2020 | I70: 000000862 | J70: ANEC3B2 20 | K70: 1 | L70: 667297 | M70: FINANZAS BÁSICAS | N70: 0060 | O70: ADM NEG INTER DCB 2020 C3B2 | P70: MT | Q70: ADMINISTRACIÓN DE NEGOCIOS INTERNACIONALES DCB 2020 C3B2 | R70: 3 | S70: 3 | U70: 26/09/2023 | V70: 02:57:38 p.m. | W70: 001686 | X70: 0010 | Y70: Req Previo | AB70: 667281 | AC70: INTRODUCCIÓN AL SISTEMA FINANC | AG70: C3B2 | AH70: INTRODUCCIÓN AL SISTEMA FINANC | AI70: ADMBF / ADMLO / ADMNE / ADMNI / CONTA / MARKT
A71: SISE | B71: PRGS | C71: ADMNI | D71: NNII2020 | E71: 0006 | F71: 0001 | G71: ANEC3B2 20 | H71: ADM NEG INTER DCB 2020 | I71: 000000862 | J71: ANEC3B2 20 | K71: 2 | L71: 667298 | M71: CONTABILIDAD APLICADA | N71: 0060 | O71: ADM NEG INTER DCB 2020 C3B2 | P71: MT | Q71: ADMINISTRACIÓN DE NEGOCIOS INTERNACIONALES DCB 2020 C3B2 | R71: 3 | S71: 3 | U71: 26/09/2023 | V71: 02:57:38 p.m. | W71: 001687 | X71: 0010 | Y71: Req Previo | AB71: 667283 | AC71: COSTOS Y PRESUPUESTOS | AG71: C3B2 | AH71: COSTOS Y PRESUPUESTOS | AI71: ADMBF / ADMLO / ADMNE / ADMNI / CONTA / MARKT
A72: SISE | B72: PRGS | C72: ADMNI | D72: NNII2020 | E72: 0006 | F72: 0001 | G72: ANEC3B2 20 | H72: ADM NEG INTER DCB 2020 | I72: 000000862 | J72: ANEC3B2 20 | K72: 3 | L72: 667299 | M72: PLAN DE NEGOCIOS | N72: 0060 | O72: ADM NEG INTER DCB 2020 C3B2 | P72: MT | Q72: ADMINISTRACIÓN DE NEGOCIOS INTERNACIONALES DCB 2020 C3B2 | R72: 3 | S72: 3 | U72: 26/09/2023 | V72: 02:57:38 p.m. | W72: 001691 | X72: 0020 | Y72: Req Adic | AD72: 000000583 | AE72: ADM NEG INTER EXPONENCIAL C3B2 | AG72: C3B2 | AH72: INNOVACIÓN Y NEGOCIOS | AI72: ADMBF / ADMLO / ADMNE / ADMNI / CONTA / MARKT
A73: SISE | B73: PRGS | C73: ADMNI | D73: NNII2020 | E73: 0006 | F73: 0001 | G73: ANEC3B2 20 | H73: ADM NEG INTER DCB 2020 | I73: 000000862 | J73: ANEC3B2 20 | K73: 4 | L73: 667300 | M73: EMPREND Y RESPONS SOCIAL | N73: 0060 | O73: ADM NEG INTER DCB 2020 C3B2 | P73: MT | Q73: ADMINISTRACIÓN DE NEGOCIOS INTERNACIONALES DCB 2020 C3B2 | R73: 3 | S73: 3 | U73: 26/09/2023 | V73: 02:57:38 p.m. | W73: 001692 | X73: 0010 | Y73: Req Adic | AD73: 000000583 | AE73: ADM NEG INTER EXPONENCIAL C3B2 | AG73: C3B2 | AH73: NINGUNO | AI73: ADMBF / ADMLO / ADMNE / ADMNI / CONTA / MARKT
A74: SISE | B74: PRGS | C74: ADMNI | D74: NNII2020 | E74: 0007 | F74: 0001 | G74: ANEC4B1 20 | H74: ADM NEG INTER DCB 2020 | I74: 000000863 | J74: ANEC4B1 20 | K74: 1 | L74: 9025 | M74: INVESTIGACIÓN DE MERCADOS | N74: 0070 | O74: ADM NEG INTER DCB 2020 C4B1 | P74: MT | Q74: ADMINISTRACIÓN DE NEGOCIOS INTERNACIONALES DCB 2020 C4B1 | R74: 2 | S74: 2 | U74: 26/09/2023 | V74: 02:57:38 p.m. | W74: 001334 | X74: 0010 | Y74: Req Previo | AB74: 667294 | AC74: ESTADÍSTICA APLICADA A LOS NEG | AG74: C4B1 | AH74: ESTADÍSTICA APLICADA A LOS NEG | AI74: ADMNE / ADMNI / MARKT
A75: SISE | B75: PRGS | C75: ADMNI | D75: NNII2020 | E75: 0007 | F75: 0001 | G75: ANEC4B1 20 | H75: ADM NEG INTER DCB 2020 | I75: 000000863 | J75: ANEC4B1 20 | K75: 2 | L75: 9026 | M75: ECONOMÍA PARA LOS NEGOCIOS | N75: 0070 | O75: ADM NEG INTER DCB 2020 C4B1 | P75: MT | Q75: ADMINISTRACIÓN DE NEGOCIOS INTERNACIONALES DCB 2020 C4B1 | R75: 3 | S75: 3 | U75: 26/09/2023 | V75: 02:57:38 p.m. | W75: 001701 | X75: 0010 | Y75: Req Adic | AD75: 000000584 | AE75: ADM NEG INTER EXPONENCIAL C4B1 | AG75: C4B1 | AH75: NINGUNO | AI75: ADMNE / ADMNI / MARKT
A76: SISE | B76: PRGS | C76: ADMNI | D76: NNII2020 | E76: 0007 | F76: 0001 | G76: ANEC4B1 20 | H76: ADM NEG INTER DCB 2020 | I76: 000000863 | J76: ANEC4B1 20 | K76: 3 | L76: 9027 | M76: CONTABILIDAD DE COSTOS | N76: 0070 | O76: ADM NEG INTER DCB 2020 C4B1 | P76: MT | Q76: ADMINISTRACIÓN DE NEGOCIOS INTERNACIONALES DCB 2020 C4B1 | R76: 2 | S76: 2 | U76: 26/09/2023 | V76: 02:57:38 p.m. | W76: 001701 | X76: 0010 | Y76: Req Adic | AD76: 000000584 | AE76: ADM NEG INTER EXPONENCIAL C4B1 | AG76: C4B1 | AH76: NINGUNO | AI76: ADMNE / ADMNI / MARKT
A77: SISE | B77: PRGS | C77: ADMNI | D77: NNII2020 | E77: 0008 | F77: 0001 | G77: ANEC4B2 20 | H77: ADM NEG INTER DCB 2020 | I77: 000000864 | J77: ANEC4B2 20 | K77: 1 | L77: 9029 | M77: E-COMMERCE | N77: 0080 | O77: ADM NEG INTER DCB 2020 C4B2 | P77: MT | Q77: ADMINISTRACIÓN DE NEGOCIOS INTERNACIONALES DCB 2020 C4B2 | R77: 2 | S77: 2 | U77: 26/09/2023 | V77: 02:57:38 p.m. | W77: 001335 | X77: 0010 | Y77: Req Previo | AB77: 009010 | AC77: COMERCIO INTERNACIONAL | AG77: C4B2 | AH77: COMERCIO INTERNACIONAL | AI77: ADMNE / ADMNI / MARKT
A78: SISE | B78: PRGS | C78: ADMNI | D78: NNII2020 | E78: 0008 | F78: 0001 | G78: ANEC4B2 20 | H78: ADM NEG INTER DCB 2020 | I78: 000000864 | J78: ANEC4B2 20 | K78: 2 | L78: 9030 | M78: MARKETING DIGITAL | N78: 0080 | O78: ADM NEG INTER DCB 2020 C4B2 | P78: MT | Q78: ADMINISTRACIÓN DE NEGOCIOS INTERNACIONALES DCB 2020 C4B2 | R78: 2 | S78: 2 | U78: 26/09/2023 | V78: 02:57:38 p.m. | W78: 001336 | X78: 0010 | Y78: Req Previo | AB78: 667295 | AC78: GESTIÓN DE CLIENTES - CRM | AG78: C4B2 | AH78: GESTIÓN DE CLIENTES - CRM | AI78: ADMNE / ADMNI / MARKT
A79: SISE | B79: PRGS | C79: ADMNI | D79: NNII2020 | E79: 0008 | F79: 0001 | G79: ANEC4B2 20 | H79: ADM NEG INTER DCB 2020 | I79: 000000864 | J79: ANEC4B2 20 | K79: 3 | L79: 9032 | M79: EXPE FORMA INTERME (MKT PER) | N79: 0080 | O79: ADM NEG INTER DCB 2020 C4B2 | P79: MT | Q79: ADMINISTRACIÓN DE NEGOCIOS INTERNACIONALES DCB 2020 C4B2 | R79: 4 | S79: 4 | U79: 26/09/2023 | V79: 02:57:38 p.m. | W79: 001193 | X79: 0010 | Y79: Req Previo | AB79: 667288 | AC79: EXP FORMA BÁSICAS (HERR INFOR) | AG79: C4B2 | AH79: EXP FORMA BÁSICAS (HERR INFOR) | AI79: ADMLO / ADMNE / ADMNI / MARKT
A80: SISE | B80: PRGS | C80: ADMNI | D80: NNII2020 | E80: 0008 | F80: 0001 | G80: ANEC4B2 20 | H80: ADM NEG INTER DCB 2020 | I80: 000000864 | J80: ANEC4B2 20 | K80: 4 | L80: 9080 | M80: INGLÉS PARA LOS NEGOCIOS I | N80: 0080 | O80: ADM NEG INTER DCB 2020 C4B2 | P80: MT | Q80: ADMINISTRACIÓN DE NEGOCIOS INTERNACIONALES DCB 2020 C4B2 | R80: 2 | S80: 2 | U80: 26/09/2023 | V80: 02:57:38 p.m. | W80: 001900 | X80: 0010 | Y80: Req Adic | AD80: 000000585 | AE80: ADM NEG INTER EXPONENCIAL C4B2 | AG80: C4B2 | AH80: NINGUNO | AI80: ADMNI
A81: SISE | B81: PRGS | C81: ADMNI | D81: NNII2020 | E81: 0009 | F81: 0001 | G81: ANEC5B1 20 | H81: ADM NEG INTER DCB 2020 | I81: 000000865 | J81: ANEC5B1 20 | K81: 1 | L81: 9081 | M81: DERE DEL COMER INTERNACIONAL | N81: 0090 | O81: ADM NEG INTER DCB 2020 C5B1 | P81: MT | Q81: ADMINISTRACIÓN DE NEGOCIOS INTERNACIONALES DCB 2020 C5B1 | R81: 3 | S81: 3 | U81: 26/09/2023 | V81: 02:57:38 p.m. | W81: 001342 | X81: 0010 | Y81: Req Previo | AB81: 667285 | AC81: LEG COMERCIAL Y TRIBUTARIA | AG81: C5B1 | AH81: LEG COMERCIAL Y TRIBUTARIA | AI81: ADMNI
A82: SISE | B82: PRGS | C82: ADMNI | D82: NNII2020 | E82: 0009 | F82: 0001 | G82: ANEC5B1 20 | H82: ADM NEG INTER DCB 2020 | I82: 000000865 | J82: ANEC5B1 20 | K82: 2 | L82: 9082 | M82: PROCEDIMIENTO Y DESPA ADUANERO | N82: 0090 | O82: ADM NEG INTER DCB 2020 C5B1 | P82: MT | Q82: ADMINISTRACIÓN DE NEGOCIOS INTERNACIONALES DCB 2020 C5B1 | R82: 3 | S82: 3 | U82: 26/09/2023 | V82: 02:57:38 p.m. | W82: 001738 | X82: 0010 | Y82: Req Adic | AD82: 000000586 | AE82: ADM NEG INTER EXPONENCIAL C5B1 | AG82: C5B1 | AH82: NINGUNO | AI82: ADMNI
A83: SISE | B83: PRGS | C83: ADMNI | D83: NNII2020 | E83: 0009 | F83: 0001 | G83: ANEC5B1 20 | H83: ADM NEG INTER DCB 2020 | I83: 000000865 | J83: ANEC5B1 20 | K83: 3 | L83: 9083 | M83: TRATADOS DE COME INTERNACIONAL | N83: 0090 | O83: ADM NEG INTER DCB 2020 C5B1 | P83: MT | Q83: ADMINISTRACIÓN DE NEGOCIOS INTERNACIONALES DCB 2020 C5B1 | R83: 3 | S83: 3 | U83: 26/09/2023 | V83: 02:57:38 p.m. | W83: 001738 | X83: 0010 | Y83: Req Adic | AD83: 000000586 | AE83: ADM NEG INTER EXPONENCIAL C5B1 | AG83: C5B1 | AH83: NINGUNO | AI83: ADMNI
A84: SISE | B84: PRGS | C84: ADMNI | D84: NNII2020 | E84: 0010 | F84: 0001 | G84: ANEC5B2 20 | H84: ADM NEG INTER DCB 2020 | I84: 000000866 | J84: ANEC5B2 20 | K84: 1 | L84: 5437 | M84: INNOVACION TECNOLOGIC(VIRTUAL) | N84: 0100 | O84: ADM NEG INTER DCB 2020 C5B2 | P84: MT | Q84: ADMINISTRACIÓN DE NEGOCIOS INTERNACIONALES DCB 2020 C5B2 | R84: 2 | S84: 2 | U84: 26/09/2023 | V84: 02:57:38 p.m. | W84: 001744 | X84: 0010 | Y84: Req Adic | AD84: 000000587 | AE84: ADM NEG INTER EXPONENCIAL C5B2 | AG84: C5B2 | AH84: NINGUNO | AI84: ADMLO / ADMNE / ADMNI / MARKT
A85: SISE | B85: PRGS | C85: ADMNI | D85: NNII2020 | E85: 0010 | F85: 0001 | G85: ANEC5B2 20 | H85: ADM NEG INTER DCB 2020 | I85: 000000866 | J85: ANEC5B2 20 | K85: 2 | L85: 9084 | M85: INGLÉS PARA LOS NEGOCIOS II | N85: 0100 | O85: ADM NEG INTER DCB 2020 C5B2 | P85: MT | Q85: ADMINISTRACIÓN DE NEGOCIOS INTERNACIONALES DCB 2020 C5B2 | R85: 2 | S85: 2 | U85: 26/09/2023 | V85: 02:57:38 p.m. | W85: 001343 | X85: 0010 | Y85: Req Previo | AB85: 009080 | AC85: INGLÉS PARA LOS NEGOCIOS I | AG85: C5B2 | AH85: INGLÉS PARA LOS NEGOCIOS I | AI85: ADMNI
A86: SISE | B86: PRGS | C86: ADMNI | D86: NNII2020 | E86: 0010 | F86: 0001 | G86: ANEC5B2 20 | H86: ADM NEG INTER DCB 2020 | I86: 000000866 | J86: ANEC5B2 20 | K86: 3 | L86: 9085 | M86: ENVASES Y EMBALAJES | N86: 0100 | O86: ADM NEG INTER DCB 2020 C5B2 | P86: MT | Q86: ADMINISTRACIÓN DE NEGOCIOS INTERNACIONALES DCB 2020 C5B2 | R86: 3 | S86: 3 | U86: 26/09/2023 | V86: 02:57:38 p.m. | W86: 002155 | X86: 0010 | Y86: Req Adic | AD86: 000000816 | AE86: ADM LOGISTICA DCB 2020 C4B2 | AG86: C5B2 | AH86: NINGUNO | AI86: ADMLO / ADMNI
A87: SISE | B87: PRGS | C87: ADMNI | D87: NNII2020 | E87: 0010 | F87: 0001 | G87: ANEC5B2 20 | H87: ADM NEG INTER DCB 2020 | I87: 000000866 | J87: ANEC5B2 20 | K87: 4 | L87: 9086 | M87: TRANSPORTES Y SEGUROS | N87: 0100 | O87: ADM NEG INTER DCB 2020 C5B2 | P87: MT | Q87: ADMINISTRACIÓN DE NEGOCIOS INTERNACIONALES DCB 2020 C5B2 | R87: 3 | S87: 3 | U87: 26/09/2023 | V87: 02:57:38 p.m. | W87: 001751 | X87: 0010 | Y87: Req Adic | AD87: 000000587 | AE87: ADM NEG INTER EXPONENCIAL C5B2 | AG87: C5B2 | AH87: NINGUNO | AI87: ADMNI
A88: SISE | B88: PRGS | C88: ADMNI | D88: NNII2020 | E88: 0011 | F88: 0001 | G88: ANEC6B1 20 | H88: ADM NEG INTER DCB 2020 | I88: 000000867 | J88: ANEC6B1 20 | K88: 1 | L88: 5441 | M88: DIS DES PROY PROD INN(VIRTUAL) | N88: 0110 | O88: ADM NEG INTER DCB 2020 C6B1 | P88: MT | Q88: ADMINISTRACIÓN DE NEGOCIOS INTERNACIONALES DCB 2020 C6B1 | R88: 2 | S88: 2 | U88: 26/09/2023 | V88: 02:57:38 p.m. | W88: 001794 | X88: 0010 | Y88: Req Adic | AD88: 000000393 | AE88: ADM NEG INTER 2017 C6B1 | AG88: C6B1 | AH88: NINGUNO | AI88: ADMLO / ADMNE / ADMNI / MARKT
A89: SISE | B89: PRGS | C89: ADMNI | D89: NNII2020 | E89: 0011 | F89: 0001 | G89: ANEC6B1 20 | H89: ADM NEG INTER DCB 2020 | I89: 000000867 | J89: ANEC6B1 20 | K89: 2 | L89: 9089 | M89: MARKETING INTERNACIONAL | N89: 0110 | O89: ADM NEG INTER DCB 2020 C6B1 | P89: MT | Q89: ADMINISTRACIÓN DE NEGOCIOS INTERNACIONALES DCB 2020 C6B1 | R89: 2 | S89: 2 | U89: 26/09/2023 | V89: 02:57:38 p.m. | W89: 002131 | X89: 0010 | Y89: Req Adic | AD89: 000000588 | AE89: ADM NEG INTER EXPONENCIAL C6B1 | AG89: C6B1 | AH89: NINGUNO | AI89: ADMNI
A90: SISE | B90: PRGS | C90: ADMNI | D90: NNII2020 | E90: 0011 | F90: 0001 | G90: ANEC6B1 20 | H90: ADM NEG INTER DCB 2020 | I90: 000000867 | J90: ANEC6B1 20 | K90: 3 | L90: 9087 | M90: INTELI DE MERC INTERNACIONALES | N90: 0110 | O90: ADM NEG INTER DCB 2020 C6B1 | P90: MT | Q90: ADMINISTRACIÓN DE NEGOCIOS INTERNACIONALES DCB 2020 C6B1 | R90: 2 | S90: 2 | U90: 26/09/2023 | V90: 02:57:38 p.m. | W90: 001344 | X90: 0010 | Y90: Req Previo | AB90: 009083 | AC90: TRATADOS DE COME INTERNACIONAL | AG90: C6B1 | AH90: TRATADOS DE COME INTERNACIONAL | AI90: ADMNI
A91: SISE | B91: PRGS | C91: ADMNI | D91: NNII2020 | E91: 0011 | F91: 0001 | G91: ANEC6B1 20 | H91: ADM NEG INTER DCB 2020 | I91: 000000867 | J91: ANEC6B1 20 | K91: 4 | L91: 9088 | M91: CALIDAD DEL COME INTERNACIONAL | N91: 0110 | O91: ADM NEG INTER DCB 2020 C6B1 | P91: MT | Q91: ADMINISTRACIÓN DE NEGOCIOS INTERNACIONALES DCB 2020 C6B1 | R91: 3 | S91: 3 | U91: 26/09/2023 | V91: 02:57:38 p.m. | W91: 002131 | X91: 0010 | Y91: Req Adic | AD91: 000000588 | AE91: ADM NEG INTER EXPONENCIAL C6B1 | AG91: C6B1 | AH91: NINGUNO | AI91: ADMNI
A92: SISE | B92: PRGS | C92: ADMNI | D92: NNII2020 | E92: 0012 | F92: 0001 | G92: ANEC6B2 20 | H92: ADM NEG INTER DCB 2020 | I92: 000000868 | J92: ANEC6B2 20 | K92: 1 | L92: 9047 | M92: EXPE FORMATIVAS ESPECIALIZADAS | N92: 0120 | O92: ADM NEG INTER DCB 2020 C6B2 | P92: MT | Q92: ADMINISTRACIÓN DE NEGOCIOS INTERNACIONALES DCB 2020 C6B2 | R92: 4 | S92: 4 | U92: 26/09/2023 | V92: 02:57:38 p.m. | W92: 001267 | X92: 0010 | Y92: Req Previo | AB92: 009032 | AC92: EXPE FORMA INTERME (MKT PER) | AG92: C6B2 | AH92: EXPE FORMA INTERME (MKT PER) | AI92: ADMLO / ADMNE / ADMNI / MARKT
A93: SISE | B93: PRGS | C93: ADMNI | D93: NNII2020 | E93: 0012 | F93: 0001 | G93: ANEC6B2 20 | H93: ADM NEG INTER DCB 2020 | I93: 000000868 | J93: ANEC6B2 20 | K93: 2 | L93: 9100 | M93: PRECI Y COTIZA INTERNACIONALES | N93: 0120 | O93: ADM NEG INTER DCB 2020 C6B2 | P93: MT | Q93: ADMINISTRACIÓN DE NEGOCIOS INTERNACIONALES DCB 2020 C6B2 | R93: 2 | S93: 2 | U93: 26/09/2023 | V93: 02:57:38 p.m. | W93: 002142 | X93: 0010 | Y93: Req Adic | AD93: 000000589 | AE93: ADM NEG INTER EXPONENCIAL C6B2 | AG93: C6B2 | AH93: NINGUNO | AI93: ADMNI
A94: SISE | B94: PRGS | C94: ADMNI | D94: NNII2020 | E94: 0012 | F94: 0001 | G94: ANEC6B2 20 | H94: ADM NEG INTER DCB 2020 | I94: 000000868 | J94: ANEC6B2 20 | K94: 3 | L94: 9101 | M94: INGLÉS PARA LOS NEGOCIOS III | N94: 0120 | O94: ADM NEG INTER DCB 2020 C6B2 | P94: MT | Q94: ADMINISTRACIÓN DE NEGOCIOS INTERNACIONALES DCB 2020 C6B2 | R94: 2 | S94: 2 | U94: 26/09/2023 | V94: 02:57:38 p.m. | W94: 001345 | X94: 0010 | Y94: Req Previo | AB94: 009084 | AC94: INGLÉS PARA LOS NEGOCIOS II | AG94: C6B2 | AH94: INGLÉS PARA LOS NEGOCIOS II | AI94: ADMNI
A95: SISE | B95: PRGS | C95: ADMNI | D95: NNII2020 | E95: 0012 | F95: 0001 | G95: ANEC6B2 20 | H95: ADM NEG INTER DCB 2020 | I95: 000000868 | J95: ANEC6B2 20 | K95: 4 | L95: 9102 | M95: FINAN DEL COMER INTERNACIONAL | N95: 0120 | O95: ADM NEG INTER DCB 2020 C6B2 | P95: MT | Q95: ADMINISTRACIÓN DE NEGOCIOS INTERNACIONALES DCB 2020 C6B2 | R95: 3 | S95: 3 | U95: 26/09/2023 | V95: 02:57:38 p.m. | W95: 002142 | X95: 0010 | Y95: Req Adic | AD95: 000000589 | AE95: ADM NEG INTER EXPONENCIAL C6B2 | AG95: C6B2 | AH95: NINGUNO | AI95: ADMNI
A96: SISE | B96: PRGS | C96: MARKT | D96: MKT2020 | E96: 0001 | F96: 0001 | G96: MKTC1B1 20 | H96: MARKETING DCB 2020 | I96: 000000869 | J96: MKTC1B1 20 | K96: 1 | L96: 667275 | M96: ADMINISTRACIÓN GENERAL | N96: 0010 | O96: MARKETING DCB 2020 C1B1 | P96: MT | Q96: MARKETING DCB 2020 C1B1 | R96: 3 | S96: 3 | U96: 26/09/2023 | V96: 03:06:10 p.m. | W96: 001637 | X96: 0010 | Y96: Req Adic | AD96: 000000785 | AE96: ADM BANC DCB 2020 C1B1 | AG96: C1B1 | AH96: NINGUNO | AI96: ADMBF / ADMLO / ADMNE / ADMNI / CONTA / MARKT
A97: SISE | B97: PRGS | C97: MARKT | D97: MKT2020 | E97: 0001 | F97: 0001 | G97: MKTC1B1 20 | H97: MARKETING DCB 2020 | I97: 000000869 | J97: MKTC1B1 20 | K97: 2 | L97: 667276 | M97: FUNDAMENTOS DE MARKETING | N97: 0010 | O97: MARKETING DCB 2020 C1B1 | P97: MT | Q97: MARKETING DCB 2020 C1B1 | R97: 2 | S97: 2 | U97: 26/09/2023 | V97: 03:06:10 p.m. | W97: 001637 | X97: 0010 | Y97: Req Adic | AD97: 000000785 | AE97: ADM BANC DCB 2020 C1B1 | AG97: C1B1 | AH97: NINGUNO | AI97: ADMBF / ADMLO / ADMNE / ADMNI / CONTA / MARKT
A98: SISE | B98: PRGS | C98: MARKT | D98: MKT2020 | E98: 0001 | F98: 0001 | G98: MKTC1B1 20 | H98: MARKETING DCB 2020 | I98: 000000869 | J98: MKTC1B1 20 | K98: 3 | L98: 667277 | M98: CONTABILIDAD BÁSICA | N98: 0010 | O98: MARKETING DCB 2020 C1B1 | P98: MT | Q98: MARKETING DCB 2020 C1B1 | R98: 4 | S98: 4 | U98: 26/09/2023 | V98: 03:06:10 p.m. | W98: 001637 | X98: 0010 | Y98: Req Adic | AD98: 000000785 | AE98: ADM BANC DCB 2020 C1B1 | AG98: C1B1 | AH98: NINGUNO | AI98: ADMBF / ADMNE / ADMNI / CONTA / MARKT
A99: SISE | B99: PRGS | C99: MARKT | D99: MKT2020 | E99: 0001 | F99: 0001 | G99: MKTC1B1 20 | H99: MARKETING DCB 2020 | I99: 000000869 | J99: MKTC1B1 20 | K99: 4 | L99: 667278 | M99: COMUNICACIÓN EFECTIVA | N99: 0010 | O99: MARKETING DCB 2020 C1B1 | P99: MT | Q99: MARKETING DCB 2020 C1B1 | R99: 2 | S99: 2 | U99: 26/09/2023 | V99: 03:06:10 p.m. | W99: 001635 | X99: 0010 | Y99: Req Adic | AD99: 000000773 | AE99: DIS GRAFICO DCB 2020 C1B1 | AG99: C1B1 | AH99: NINGUNO | AI99: ADHYR / ADMBF / ADMLO / ADMNE / ADMNI / COMAU / CONTA / DG / DYGMO / FISIO / GASTR / MARKT / PA / REDES / SALUD / SECRE / SWSIS / TECFA
A100: SISE | B100: PRGS | C100: MARKT | D100: MKT2020 | E100: 0002 | F100: 0001 | G100: MKTC1B2 20 | H100: MARKETING DCB 2020 | I100: 000000870 | J100: MKTC1B2 20 | K100: 1 | L100: 667281 | M100: INTRODUCCIÓN AL SISTEMA FINANC | N100: 0020 | O100: MARKETING DCB 2020 C1B2 | P100: MT | Q100: MARKETING DCB 2020 C1B2 | R100: 2 | S100: 2 | U100: 26/09/2023 | V100: 03:06:10 p.m. | W100: 001622 | X100: 0010 | Y100: Req Adic | AD100: 000000822 | AE100: ADM EMPRESAS DCB 2020 C1B2 | AG100: C1B2 | AH100: NINGUNO | AI100: ADMBF / ADMNE / ADMNI / CONTA / MARKT
...
